Workbook

Sheet CALCULO GERAL
C3: 7.968 | D3: =C3/2500 -> 0.0031872 | F3: =1.82 -> 1.82 | J3: =D23/C20 -> 8.0049385 | K3: =J3/C11 -> 1.594927
F4: 2.18 | G4: =F4/F3-1 -> 0.1978022 | K4: =G10*K3 -> 10048.04
A5: =23841.99/25500 -> 0.93498 | B5: CÁLCULO DE PREÇOS PROCESSO | I5: CALCULO ITEM 1 | M5: =25315.76-27845.34 -> -2529.58 | R5: CALCULO ITEM 2 | AA5: BASE DE CALCULO CUSTOS | AG5: CALCIULAR PREÇO FINAL
I8: IMPORTAÇÃO - MG | R8: IMPORTAÇÃO - MG | V8: VENDA - INTERESTADUAL | AG8: Dolar Final | AH8: VENDA EM DÓLAR | AI8: Preço Final R$ | AJ8: Container | AK8: Valor Final
I9: Descrição | M9: CUSTO TOTAL UNITÁRIO | O9: =K41 -> 3.817462 | R9: Descrição | S9: % | AC9: ITEM 1 | AD9: ITEM 2 | AG9: =(5.4571*0.2)+(5.2137*0.8) -> 5.26238 | AH9: =C22 -> 0.83 | AI9: =AG9*AH9 -> 4.3677754 | AJ9: 117.421 metros | AK9: =AI9*K12 -> 1091943.9
B10: TRANSPORTE | C10: IBITINGA | D10: OPERAÇÃO | E10: INTER | F10: FRETE INTERNAC. USD | G10: 6300 | I10: NCM | K10: =F14 -> 5407.52.10 | M10: (-) CRÉDITOS S/ IMPORT | O10: =SUM(O11:O14) -> 0.32779189 | R10: NCM | T10: =F29 -> 5407.52.10 | V10: CUSTO TOTAL UNITÁRIO | X10: =T41 -> 4.494633 | AB10: CELULA NCM | AC10: 80 | AD10: 80 | AG10: 5,4571x 20 por cento da entrada
A11: =C11+0.15 -> 5.169 | B11: DÓLAR FISCAL | C11: 5.019 | D11: COMISSÃO | E11: 0.02 | F11: CAPADIDADE CNTR | G11: 1 | I11: Vr. FOB Unitário | K11: =C17 -> 0.47 | M11: (-) IPI | O11: =K43/$K$12 -> 0 | R11: Vr. FOB Unitário | T11: =C32 -> 0.56 | V11: (-) CRÉDITOS S/ IMPORT | X11: =SUM(X12:X15) -> 0 | AB11: CELULA ICMS | AC11: 2
B12: MESES | C12: 5 | D12: JUROS | E12: =G12/12 -> 0.012083333 | F12: JUROS A.A. | G12: 0.145 | I12: Quantidade | K12: =C16 -> 250000 | M12: (-) PIS | O12: =K44/$K$12 -> 0.05484964 | R12: Quantidade | T12: =C31 -> 115000 | V12: (-) IPI | X12: =T43/$T$12 -> 0 | AA12: 1 | AB12: CABOTAGEM | AC12: 0.14 | AD12: INTRA | AE12: 0.14 | AG12: 5,2137 x 80 por cento do saldo | AN12: 8308.42 | AO12: =AO14/AN14*AN12 -> 8420.5822 | AP12: =AO12-AN12 -> 112.16217
I13: Vr. FOB TOTAL | K13: =K12*K11 -> 117500 | M13: (-) COFINS | O13: =K45/$K$12 -> 0.27294225 | R13: Vr. FOB TOTAL | T13: =T12*T11 -> 64400 | V13: (-) PIS | X13: =T44/$T$12 -> 0 | AA13: 2 | AB13: IBITINGA | AC13: 0.015 | AD13: INTER | AE13: 0.015 | AN13: 4579.16 | AO13: =AO14/AN14*AN13 -> 4640.9778 | AP13: =AO13-AN13 -> 61.817832
A14: de | B14: PRODUTO 1 | C14: TEC MIC 85GSM ESTAMPADO 250CM | E14: NCM | F14: =VLOOKUP(C14,'NCMS E ALÍQUOTAS'!B2:C2225,2,FALSE) -> 5407.52.10 | I14: TX CONVERSÃO FISCAL | K14: =C11 -> 5.019 | M14: (-) ICMS | O14: =K46/$K$12 -> 0 | R14: TX CONVERSÃO FISCAL | T14: =C11 -> 5.019 | V14: (-) COFINS | X14: =T45/$T$12 -> 0 | AA14: 3 | AB14: MINAS | AC14: 1 | AN14: 12887.58 | AO14: 13061.56
B15: QUANTIDADE CNTR | C15: 2 | D15: =$C$15/$G$11 -> 2 | G15: =158*65*146/1000000 -> 1.49942 | I15: Total FOB R$ | K15: =K13*K14 -> 589732.5 | M15: CUSTO FINAL | O15: =O9-O10 -> 3.4896701 | P15: =P16-K16 -> 1580.985 | R15: Total FOB R$ | T15: =T13*T14 -> 323223.6 | V15: (-) ICMS | X15: =T46/$T$12 -> 0 | AB15: CABOTAGEM
A16: =C16 -> 250000 | B16: QUANTIDADE | C16: 250000 | D16: QUANTIDADE 1x40 | E16: 125000 | F16: =C16*0.8*0.255 -> 51000 | G16: =G15*50 -> 74.971 | I16: Frete Internacional | J16: =C19 -> 12600 | K16: =J16*K14 -> 63239.4 | M16: Outros Gastos | O16: =SUM(O17:O23) -> 0.0833154 | P16: =K16*1.025 -> 64820.385 | R16: Frete Internacional | S16: =C34 -> 6300 | T16: =S16*T14 -> 31619.7 | V16: CUSTO FINAL | X16: =X10-X11 -> 4.494633 | AB16: CALCULO TRANSPORTADORA IDA | AE16: CABOTAGEM
A17: =C17 -> 0.47 | B17: VALOR FOB | C17: 0.47 | D17: VALOR FOB TABELA | E17: =VLOOKUP(C14,'TABELA MATRIZ MG'!$A$2:$Y$329,25,FALSE) -> 0.519 | F17: Xx | G17: =VLOOKUP(C14,'TABELA MATRIZ MG'!$A$2:$Y$438,24,FALSE) -> 0.48 | I17: Capatazia | N17: 0 | O17: =N17/K12 -> 0 | R17: Capatazia | T17: 0 | V17: Outros Gastos | X17: =SUM(X18:X33) -> 0.0983724 | AB17: FRETE PESO | AC17: 2966 | AD17: =AC17 -> 2966 | AE17: 15000
A18: =C17 -> 0.47 | B18: TOTAL FOB | C18: =C16*C17 -> 117500 | D18: TOTAL FOB R$ | E18: =C18*C11 -> 589732.5 | F18: 0.2 | G18: =E18*0.2 -> 117946.5 | I18: Valor CIF | K18: =SUM(K15:K17) -> 652971.9 | M18: Comissão de vendas | N18: =E11 -> 0.02 | O18: =N18*G22 -> 0.0833154 | P18: =O18*K12 -> 20828.85 | R18: Valor aduaneiro | T18: =SUM(T15:T17) -> 354843.3 | W18: 0 | X18: =W18/T12 -> 0 | AB18: PEDÁGIO | AC18: 61.8 | AD18: =AC18 -> 61.8
A19: =A16*A17 -> 117500 | B19: FRETE INTERNAC. USD | C19: =G10*D15 -> 12600 | D19: FRETE INTERNAC. R$ | E19: =C19*C11 -> 63239.4 | F19: 0.8 | G19: =E18*0.8 -> 471786 | I19: Imp. Importação | J19: =VLOOKUP($C$14,'NCMS E ALÍQUOTAS'!$B$2:$O$2225,3,FALSE) -> 0.26 | K19: =$K$18*$J$19 -> 169772.69 | O19: =N19/K12 -> 0 | R19: Imp. Importação | S19: =VLOOKUP($C$29,'NCMS E ALÍQUOTAS'!$B$2:$O$2225,3,FALSE) -> 0.26 | T19: =S19*T18 -> 92259.258 | V19: Comissão de vendas | W19: =E11 -> 0.02 | X19: =W19*G37 -> 0.0983724 | Y19: =X19*$T$12 -> 11312.826 | AB19: AD. VALOREM | AD19: =AC19*K24 -> 0
A20: =A16*A18 -> 117500 | B20: Total CIF USD | C20: =C19+C18 -> 130100 | D20: Total CIF R$ | E20: =C20*C11 -> 652971.9 | F20: CUSTO EM USD | G20: CUSTO EM REAIS | I20: IPI | J20: =VLOOKUP($C$14,'NCMS E ALÍQUOTAS'!$B$2:$O$2225,4,FALSE) -> 0 | K20: =$K$18*$J$20 -> 0 | M20: Operador Logistico | N20: 0 | O20: =N20/K12 -> 0 | P20: =15152.3+4237.51+19518.22+4079.56+2572.48 -> 45560.07 | R20: IPI | S20: =VLOOKUP($C$29,'NCMS E ALÍQUOTAS'!$B$2:$O$2225,4,FALSE) -> 0 | T20: =S20*$T$18 -> 0 | V20: Administração | X20: =W20/T12 -> 0 | AB20: ADICIONAL 25 TON | AC20: 0.15 | AD20: =AC17*AC20 -> 444.9 | AL20: =2.18*25000 -> 54500
A21: =A19/A20-1 -> 0 | B21: CUSTO PROCESSO | D21: =K40+P28+P29+P31+P18+P33+P36+P37+P38-K42 -> 1013140.7 | F21: =G21/$C$11 -> 0.80744425 | G21: =D21/C16 -> 4.0525627 | I21: PIS | J21: =VLOOKUP($C$14,'NCMS E ALÍQUOTAS'!$B$2:$O$2225,5,FALSE) -> 0.021 | K21: =$K$18*$J$21 -> 13712.41 | M21: Contador | N21: 0 | O21: =N21/K12 -> 0 | P21: =P20+K47 -> 917977.59 | R21: PIS | S21: =VLOOKUP($C$29,'NCMS E ALÍQUOTAS'!$B$2:$O$2225,5,FALSE) -> 0.021 | T21: =S21*$T$18 -> 7451.7093 | V21: Operador Logistico | W21: 0 | X21: =W21/T12 -> 0 | AB21: ICMS | AC21: 0.12 | AD21: =SUM(AD17:AD20)*AC21/0.88 -> 473.55 | AL21: =AL20*C11 -> 273535.5 | AN21: =22 -> 22
A22: =A19-A20 -> 0 | B22: PV em USD | C22: 0.83 | D22: PV TABELA | E22: =C22*C16 -> 207500 | F22: PV em R$ | G22: =$C$22*$C$11 -> 4.16577 | I22: COFINS | J22: =VLOOKUP($C$14,'NCMS E ALÍQUOTAS'!$B$2:$O$2225,6,FALSE) -> 0.1045 | K22: =$K$18*$J$22 -> 68235.564 | O22: =N22/K13 -> 0 | P22: =271970.98 -> 271970.98 | R22: COFINS | S22: =VLOOKUP($C$29,'NCMS E ALÍQUOTAS'!$B$2:$O$2225,6,FALSE) -> 0.1045 | T22: =S22*$T$18 -> 37081.125 | V22: Contador | X22: =W22/T12 -> 0 | AB22: TOTAL | AD22: =SUM(AD17:AD20)/0.88 -> 3946.25 | AN22: =AN21-2.2 -> 19.8 | AP22: 60
A23: =A22*A11 -> 0 | B23: 0.84 | D23: =G22*C16 -> 1041442.5 | F23: =G23/C11 -> 62250 | G23: =D23*0.3 -> 312432.75 | I23: Total Valor Aduaneiro | K23: =SUM(K18:K22) -> 904692.57 | O23: 0 | P23: =P22-P21 -> -646006.61 | R23: Total Valor Aduaneiro | T23: =SUM(T18:T22) -> 491635.39 | V23: Salários | X23: =W23/T13 -> 0 | AB23: IBITINGA | AN23: =G22/AN21 -> 0.18935318 | AP23: 25000
A24: =A23/D23 -> 0 | B24: MARGEM | C24: =E24/D23 -> 0.0271756 | E24: =D23-D21-A23 -> 28301.825 | F24: 0.8 | G24: =D23*0.7 -> 729009.75 | I24: BC ICMS | K24: =(SUM($K$18:$K$22)+$K$26+$K$27)/(1-$J$25) -> 909964.51 | M24: CUSTO TOTAL UNITÁRIO ANTES DA NOTA | O24: =O15+O16+O28+O29+O31+O33+O20+O21 -> 4.0150258 | P24: =O24*K12 -> 1003756.4 | R24: BC ICMS | T24: =(SUM($T$18:$T$22)+$T$26+$T$27)/(1-$S$25) -> 494340.4 | V24: xxx | W24: 0 | X24: =W24/T14 -> 0 | AB24: CALCULO TRANSPORTADORA RETORNO | AP24: =AP23 -> 25000
I25: ICMS | J25: 0 | K25: =K24*J25 -> 0 | M25: Valor Unitário USD / tx dolar di | O25: =O24/K14 -> 0.79996528 | P25: =O25*K12 -> 199991.32 | R25: ICMS | S25: 0 | T25: =T24*S25 -> 0 | V25: xxx | X25: 0 | AB25: FRETE PESO | AC25: 2966 | AD25: =AC25/1.3 -> 2281.5385
B26: PV em USD | C26: =(C27+G23)/C16/C11 -> 0.8659607 | D26: =G26*C16 -> 1086564.2 | F26: PV em R$ | G26: =$C$26*$C$11 -> 4.3462567 | I26: Siscomex | K26: =115.67+38.56*2 -> 192.79 | M26: Margem | N26: =O26/O24 -> 0.037545026 | O26: =O39-O24 -> 0.15074425 | P26: =N26*P39 -> 39100.986 | R26: Siscomex | T26: =115.67+38.56 -> 154.23 | V26: xxx | X26: 0 | AB26: PEDÁGIO | AC26: 197 | AD26: =AC26 -> 197 | AG26: =670000 -> 670000
C27: =FV(E12,C12,,G24)*-1 -> 774131.43 | E27: =D26-D21-A23 -> 73423.508 | F27: =29211.53 -> 29211.53 | G27: =F27-E24 -> 909.7049 | I27: AFRMM | J27: 0.08 | K27: =(K16)*J27+20 -> 5079.152 | M27: Base de Cálculo PIS/COFINS | O27: =G22-O33-O31 -> 4.1032835 | P27: =P24*N29 -> 76285.489 | R27: AFRMM | S27: 0.08 | T27: =(T16+T17)*S27+21.2 -> 2550.776 | V27: xxx | X27: 0 | AB27: AD. VALOREM | AC27: 0.001 | AD27: =AC27*K24 -> 909.96451 | AG27: =AG26*0.001 -> 670 | AH27: 570000
C28: =20000*8 -> 160000 | G28: =G27/2 -> 454.85245 | I28: S.D.A./Despachante | K28: =AD43*$D$15 -> 5000 | M28: PIS | N28: 0.0165 | O28: =$O$27*N28 -> 0.067704177 | P28: =O28*$K$12 -> 16926.044 | R28: S.D.A./Despachante | T28: =AD43*$D$30 -> 2500 | V28: xxx | X28: 0 | AB28: ADICIONAL 25 TON | AC28: 0.15 | AD28: =AC25*AC28 -> 444.9 | AH28: =AH27*0.001 -> 570
B29: PRODUTO 2 | C29: TEC MIC 85GSM TINTO 250CM | E29: NCM | F29: =VLOOKUP(C29,'NCMS E ALÍQUOTAS'!$B$3:$C$254,2,FALSE) -> 5407.52.10 | I29: Diferença frete internacional | J29: =K14*1.025 -> 5.144475 | K29: =(J16*J29)-K16 -> 1580.985 | M29: COFINS | N29: 0.076 | O29: =$O$27*N29 -> 0.31184954 | P29: =O29*$K$12 -> 77962.386 | R29: Diferença frete internacional | S29: =T14*1.02 -> 5.11938 | T29: =(S16*S29)-T16 -> 632.394 | V29: xxx | X29: 0 | AB29: ICMS | AC29: 0.12 | AD29: =SUM(AD25:AD28)*AC29/0.88 -> 522.73677
A30: =C30 -> 1 | B30: QUANTIDADE CNTR | C30: 1 | D30: =$C$30/$G$11 -> 1 | I30: Valores Agente de cargas | K30: =AD45*$D$15 -> 3600 | M30: Base de Cálculo ICMS | O30: =G22-O33 -> 4.16577 | P30: =P24*N31 -> 15056.347 | R30: Valores Agente de cargas | T30: =AD45*$D$30 -> 1800 | V30: xxx | X30: 0 | AB30: TOTAL | AD30: =SUM(AD25:AD28)/0.88 -> 4356.1397
A31: =C31 -> 115000 | B31: QUANTIDADE | C31: 115000 | D31: QUANTIDADE 1x40 | E31: =VLOOKUP(C29,'TABELA MATRIZ MG'!$A$2:$Y$329,14,FALSE) -> 120000 | F31: =C31*0.85*0.28 -> 27370 | I31: Armazenagem PORTO | K31: =AD46*$D$15 -> 5200 | M31: ICMS | N31: 0.015 | O31: =$G$22*$N$31 -> 0.06248655 | P31: =O31*$K$12 -> 15621.638 | R31: Armazenagem PORTO | T31: =AD46*$D$30 -> 2600 | V31: xxx | X31: 0
A32: =C32 -> 0.56 | B32: VALOR FOB | C32: 0.56 | D32: VALOR FOB TABELA | E32: =VLOOKUP(C29,'TABELA MATRIZ MG'!$A$2:$Y$329,25,FALSE) -> 0.489375 | F32: MENOR FOB | G32: =VLOOKUP(C29,'TABELA MATRIZ MG'!$A$2:$BN$329,24,FALSE) -> 0.455 | I32: Capatazia | K32: =AD47*$D$15 -> 2020 | M32: BC IPI | N32: 0.04 | O32: =G22/(1+N33) -> 4.16577 | R32: Capatazia | T32: =AD47*$D$30 -> 1010 | V32: xxx | X32: 0 | AB32: CALCULO TRANSPORTADORA - IBITINGA
A33: =C32 -> 0.56 | B33: TOTAL FOB | C33: =C31*C32 -> 64400 | D33: TOTAL FOB R$ | E33: =C33*C11 -> 323223.6 | F33: 0.2 | G33: =E33*0.2 -> 64644.72 | I33: Custo Desembaraço - Santos | K33: =K23+SUM(K25:K32) -> 927365.49 | M33: IPI | N33: =J20 -> 0 | O33: =N33*O32 -> 0 | P33: =O33*$K$12 -> 0 | R33: Custo Desembaraço - Santos | T33: =T23+SUM(T25:T32) -> 502882.79 | V33: xxx | X33: 0 | AB33: FRETE PESO | AC33: 6316 | AD33: =AC33 -> 6316
A34: =A31*A32 -> 64400 | B34: FRETE INTERNAC. USD | C34: =G10*D30 -> 6300 | D34: FRETE INTERNAC. R$ | E34: =C34*C11 -> 31619.7 | F34: 0.8 | I34: Frete Interno | K34: =AD49*$D$15 -> 26000 | O34: =O24+O28+O29+O31 -> 4.457066 | P34: 0 | R34: Frete Interno - Pouso Alegre | T34: =AD49*$D$30 -> 13000 | V34: CUSTO TOTAL UNITÁRIO | X34: =X16+X17+X39+X40+X42+X44+X47+X48+X49 -> 4.9380589 | Y34: =X34*T12 -> 567876.77 | AB34: PEDÁGIO | AC34: 866.8 | AD34: =AC34 -> 866.8
A35: =A31*A33 -> 64400 | B35: Total CIF USD | C35: =C34+C33 -> 70700 | D35: Total CIF R$ | E35: =C35*C11 -> 354843.3 | F35: CUSTO EM USD | G35: CUSTO EM REAIS | M35: Base de Calculo lucro presumido | O35: =P26 -> 39100.986 | P35: 59999.99 | V35: Valor Unitário USD / tx dolar di | X35: =X34/T14 -> 0.98387306 | AB35: AD. VALOREM | AC35: 0.001 | AD35: =AC35*(K33+T33) -> 1430.2483
A36: =A35/A34-1 -> 0 | B36: CUSTO PROCESSO | D36: =T47+Y19+Y39+Y40+Y42+Y44+Y47+Y48+Y49-T43+Y57 -> 567876.77 | F36: =G36/$C$11 -> 0.98387306 | G36: =D36/C31 -> 4.9380589 | I36: Operador Logistico | K36: 1000 | M36: CCSLL | N36: 0.09 | O36: =P36/$K$12 -> 0.014076355 | P36: =O35*N36 -> 3519.0887 | R36: Operador Logistico | T36: 1000 | V36: Margem | W36: =X36/X34 -> -0.0039365397 | X36: =X37-X34 -> -0.019438865 | Y36: =W36*Y37 -> -2226.6694 | AB36: ADICIONAL 25 TON | AC36: 0.15 | AD36: =AC33*AC36 -> 947.4
A37: =A34-A35 -> 0 | B37: PV em USD | C37: 0.98 | D37: PV TABELA | E37: =VLOOKUP(C29,'TABELA MATRIZ MG'!$A$2:$BN$329,66,FALSE) -> 0.87 | F37: PV em R$ | G37: =$C$37*$C$11 -> 4.91862 | I37: Operação de carga e descarga | K37: 0 | M37: IR | N37: 0.15 | O37: =P37/$K$12 -> 0.023460592 | P37: =N37*O35 -> 5865.1479 | R37: Operação de carga e descarga | V37: PREÇO DE VENDA S/ Impostos | X37: =G37 -> 4.91862 | Y37: =X37*T12 -> 565641.3 | AB37: ICMS | AC37: 0.12 | AD37: =SUM(AD33:AD36)*AC37/0.88 -> 1303.6975
A38: =A37*A26 -> 0 | B38: TOTAL VENDA | D38: =G37*C31 -> 565641.3 | F38: 0.2 | G38: =D38*0.2 -> 113128.26 | I38: coleta vazio | K38: 0 | M38: adicional de IR | N38: 0.1 | O38: =P38/$K$12 -> 0 | P38: =IF(O35>=P35,(O35-P35)*N38,IF(O35<P35,P34*N38)) -> 0 | R38: coleta vazio | V38: Base de Cálculo PIS/COFINS | X38: =G37-X44-X42 -> 4.8448407 | AB38: TOTAL | AD38: =SUM(AD33:AD36)+AD22 -> 13506.698
B39: MARGEM | C39: =E39/D38 -> -0.0039520973 | D39: LUCRO | E39: =D38-D36 -> -2235.4694 | F39: 0.8 | G39: =D38*0.8 -> 452513.04 | I39: CABOTAGEM | K39: 0 | M39: PREÇO DE VENDA | N39: =O39/5.45 -> 0.76436147 | O39: =G22 -> 4.16577 | P39: =O39*K12 -> 1041442.5 | R39: CABOTAGEM | T39: =IF(C10="CABOTAGEM",AE17,IF(C10="IBITINGA",AE32,IF(C10="MINAS",AE22)))*$D$30 -> 0 | V39: PIS | W39: =VLOOKUP($C$29,'NCMS E ALÍQUOTAS'!$B$2:$O$2225,7,FALSE) -> 0.0065 | X39: =$X$38*W39 -> 0.031491465 | Y39: =X39*$T$12 -> 3621.5184
E40: =E39-A35 -> -66635.469 | I40: Custo Processo | K40: =SUM(K33:K39) -> 954365.49 | M40: Base de Calculo DIFAL | O40: =D23+P33 -> 1041442.5 | P40: =O40/0.82 -> 1270051.8 | R40: Custo Processo | T40: =SUM(T33:T39) -> 516882.79 | V40: COFINS | W40: =VLOOKUP($C$29,'NCMS E ALÍQUOTAS'!$B$2:$O$2225,8,FALSE) -> 0.03 | X40: =$X$38*W40 -> 0.14534522 | Y40: =X40*$T$12 -> 16714.7
B41: TOTAL VENDA | E41: =D38+D23 -> 1607083.8 | I41: Custo Total Unitário | K41: =K40/K12 -> 3.817462 | M41: icms difal | N41: 0.18 | P41: =P40*N41 -> 228609.33 | R41: Custo Total Unitário | T41: =T40/T12 -> 4.494633 | V41: Base de Cálculo ICMS | X41: =P21-X44 -> 917977.59
B42: LUCRO OPERAÇÃO | E42: =E39+E24 -> 26066.356 | F42: =E42/2 -> 13033.178 | I42: (-) CRÉDITOS S/ INSUMOS | K42: =SUM(K43:K46) -> 81947.973 | M42: icms difal mg | N42: 0.04 | P42: =N42*P40 -> 50802.073 | R42: (-) CRÉDITOS S/ INSUMOS | T42: =SUM(T43:T46) -> 0 | V42: ICMS | W42: =VLOOKUP($E$10,$AD$12:$AE$13,2,FALSE) -> 0.015 | X42: =$G$37*$W$42 -> 0.0737793 | Y42: =X42*$T$12 -> 8484.6195 | AB42: CUSTOS FIXOS
I43: (-) IPI | J43: =J20 -> 0 | K43: =K20 -> 0 | M43: TOTAL DIFAL | R43: (-) IPI | T43: =T20 -> 0 | V43: BC IPI | X43: =P21/(1+W44) -> 917977.59 | AB43: S.D.A./Despachante | AD43: 2500
C44: =280/250 -> 1.12 | D44: =C32*C44 -> 0.6272 | E44: 0.98 | I44: (-) PIS | J44: =J21 -> 0.021 | K44: =$J$44*K18 -> 13712.41 | R44: (-) PIS | S44: 0 | T44: =$S$44*T18 -> 0 | V44: IPI | W44: =VLOOKUP($C$29,'NCMS E ALÍQUOTAS'!$B$2:$O$2225,4,FALSE) -> 0 | X44: =W44*X43 -> 0 | Y44: =X44*$T$12 -> 0
I45: (-) COFINS | J45: =J22 -> 0.1045 | K45: =K18*$J$45 -> 68235.564 | M45: =878417.52-872137.52 -> 6280 | R45: (-) COFINS | S45: 0 | T45: =T18*$S$45 -> 0 | X45: =X34+X39+X40+X42 -> 5.1886749 | Y45: 0 | AB45: Valores Agente de cargas | AD45: 1800
A46: =B46*C46 -> 18270 | B46: 0.435 | C46: 42000 | D46: 0.785 | E46: =C46*D46 -> 32970 | G46: =96000*0.32 -> 30720 | I46: (-) ICMS | K46: =K25 -> 0 | R46: (-) ICMS | T46: =T25 -> 0 | V46: Base de Calculo lucro presumido | W46: 0.08 | X46: =Y37*W46 -> 45251.304 | Y46: 59999.99 | AB46: Armazenagem PORTO | AD46: 2600
A47: =B47*C47 -> 4350 | B47: 0.435 | C47: 10000 | D47: 0.775 | E47: =C47*D47 -> 7750 | I47: CUSTO IMPORTACAO FINAL TOTAL | K47: =K40-K42 -> 872417.52 | L47: VALOR TOTAL DO CUSTO DE ENTRADA NA IMPORTACAO | R47: CUSTO FINAL TOTAL | T47: =T40-T42 -> 516882.79 | V47: CCSLL | W47: 0.09 | X47: =Y47/$T$12 -> 0.035414064 | Y47: =X46*W47 -> 4072.6174 | AB47: Capatazia | AD47: 1010
A48: =B48*C48 -> 12450 | B48: 0.415 | C48: 30000 | D48: 0.735 | E48: =C48*D48 -> 22050 | I48: CUSTO IMPORTACAO FINAL UNITÁRIO | K48: =K47/K12 -> 3.4896701 | M48: =870917.52-K47 -> -1500.001 | R48: CUSTO FINAL UNITÁRIO | T48: =T47/T12 -> 4.494633 | V48: IR | W48: 0.15 | X48: =Y48/$T$12 -> 0.05902344 | Y48: =W48*X46 -> 6787.6956
A49: =B49*C49 -> 16600 | B49: 0.415 | C49: 40000 | D49: 0.725 | E49: =C49*D49 -> 29000 | V49: adicional de IR | W49: 0.1 | X49: =Y49/$T$12 -> 0 | Y49: =IF(X46>=Y46,(X46-Y46)*W49,IF(X46<Y46,Y45*W49)) -> 0 | AB49: Frete NACIONAL ALL-IN | AD49: 13000
A50: =B50*C50 -> 53120 | B50: 0.415 | C50: 128000 | D50: 0.725 | E50: =C50*D50 -> 92800
V51: Base de Calculo DIFAL | X51: =D38+Y44 -> 565641.3 | Y51: =X51/0.82 -> 689806.46 | AB51: Operador Logistico | AD51: 1000
A52: =SUM(A46:A50) -> 104790 | E52: =SUM(E46:E50) -> 184570 | V52: icms difal | W52: 0.18 | Y52: =Y51*W52 -> 124165.16 | AB52: Operação de carga e descarga
B53: =A52/C53 -> 0.41916 | C53: =SUM(C46:C51) -> 250000 | D53: =E52/C53 -> 0.73828 | I53: 100000 | J53: =I53*0.021 -> 2100 | K53: =J53+J55 -> 3725 | V53: icms difal mg | W53: 0.04 | Y53: =W53*Y51 -> 27592.259 | AB53: coleta vazio
I54: 100000 | J54: =I54*0.0965 -> 9650 | K54: =J54+J56 -> 17150 | V54: adicional de IR | Y54: =Y52-Y53 -> 96572.905 | AB54: CABOTAGEM | AD54: =IF(C10="CABOTAGEM",AE17,IF(C10="IBITINGA",AE32,IF(C10="MINAS",AE22))) -> 0
I55: 250000 | J55: =I55*0.0065 -> 1625
I56: 250000 | J56: =I56*0.03 -> 7500
I57: 100000 | J57: =I57*0.0165 -> 1650
I58: 100000 | J58: =I58*0.0765 -> 7650
I59: 250000 | J59: =I59*0.0165 -> 4125 | K59: =J59-J57 -> 2475
D60: 5150 | I60: 250000 | J60: =I60*0.0765 -> 19125 | K60: =J60-J58 -> 11475
D61: =D60*7 -> 36050
F65: 10.5
F69: =46.8 -> 46.8 | G69: =F69/4 -> 11.7
F70: 62.1 | G70: =F70/4 -> 15.525
C74: =30720 -> 30720 | D74: =C74*4 -> 122880 | E74: =8.97 -> 8.97 | F74: =E74*4 -> 35.88
F77: =68/E74 -> 7.580825
F78: =F77*E74 -> 68 | G78: =C74*F77 -> 232882.94
F187: =F186/E186 -> #DIV/0! | G187: =G186*49.54 -> 0
D189: =0.02*10000 -> 200
C201: 115000 | D201: 68 | E201: =C201/D201 -> 1691.1765
E202: =E201*56 -> 94705.882

Sheet CALCULO GERAL (2)
C3: 7.968 | D3: =C3/2500 -> 0.0031872 | F3: =1.82 -> 1.82 | J3: =D23/C20 -> 8.1216353 | K3: =J3/C11 -> 1.6057327
F4: 2.18 | G4: =F4/F3-1 -> 0.1978022 | K4: =G10*K3 -> 4014.3317
A5: =23841.99/25500 -> 0.93498 | B5: CÁLCULO DE PREÇOS PROCESSO | I5: CALCULO ITEM 1 | M5: =25315.76-27845.34 -> -2529.58 | R5: CALCULO ITEM 2 | AA5: BASE DE CALCULO CUSTOS | AG5: CALCIULAR PREÇO FINAL
I8: IMPORTAÇÃO - MG | R8: IMPORTAÇÃO - MG | V8: VENDA - INTERESTADUAL | AG8: Dolar Final | AH8: VENDA EM DÓLAR | AI8: Preço Final R$ | AJ8: Container | AK8: Valor Final
I9: Descrição | M9: CUSTO TOTAL UNITÁRIO | O9: =K41 -> 4.1114742 | R9: Descrição | S9: % | AC9: ITEM 1 | AD9: ITEM 2 | AG9: =(5.4571*0.2)+(5.2137*0.8) -> 5.26238 | AH9: =C22 -> 0.9 | AI9: =AG9*AH9 -> 4.736142 | AJ9: 117.421 metros | AK9: =AI9*K12 -> 577809.32
B10: TRANSPORTE | C10: IBITINGA | D10: OPERAÇÃO | E10: INTER | F10: FRETE INTERNAC. USD | G10: 2500 | I10: NCM | K10: =F14 -> 5407.52.10 | M10: (-) CRÉDITOS S/ IMPORT | O10: =SUM(O11:O14) -> 0.35578139 | R10: NCM | T10: =F29 -> 0.12397778 | V10: CUSTO TOTAL UNITÁRIO | X10: =T41 -> #N/A | AB10: CELULA NCM | AC10: 80 | AD10: 80 | AG10: 5,4571x 20 por cento da entrada
A11: =C11+0.15 -> 5.2079 | B11: DÓLAR FISCAL | C11: 5.0579 | D11: COMISSÃO | E11: 0.02 | F11: CAPADIDADE CNTR | G11: 1 | I11: Vr. FOB Unitário | K11: =C17 -> 0.54 | M11: (-) IPI | O11: =K43/$K$12 -> 0 | R11: Vr. FOB Unitário | T11: =C32 -> 0 | V11: (-) CRÉDITOS S/ IMPORT | X11: =SUM(X12:X15) -> #N/A | AB11: CELULA ICMS | AC11: 2
B12: MESES | C12: 5 | D12: JUROS | E12: =G12/12 -> 0.012083333 | F12: JUROS A.A. | G12: 0.145 | I12: Quantidade | K12: =C16 -> 122000 | M12: (-) PIS | O12: =K44/$K$12 -> 0.059533141 | P12: =O12*K12 -> 7263.0432 | R12: Quantidade | T12: =C31 -> 0 | V12: (-) IPI | X12: =T43/$T$12 -> #N/A | AA12: 1 | AB12: CABOTAGEM | AC12: 0.14 | AD12: INTRA | AE12: 0.14 | AG12: 5,2137 x 80 por cento do saldo | AN12: 8308.42 | AO12: =AO14/AN14*AN12 -> 8420.5822 | AP12: =AO12-AN12 -> 112.16217
I13: Vr. FOB TOTAL | K13: =K12*K11 -> 65880 | M13: (-) COFINS | O13: =K45/$K$12 -> 0.29624825 | P13: =O13*K13 -> 19516.835 | R13: Vr. FOB TOTAL | T13: =T12*T11 -> 0 | V13: (-) PIS | X13: =T44/$T$12 -> #DIV/0! | AA13: 2 | AB13: IBITINGA | AC13: 0.015 | AD13: INTER | AE13: 0.015 | AN13: 4579.16 | AO13: =AO14/AN14*AN13 -> 4640.9778 | AP13: =AO13-AN13 -> 61.817832
A14: de | B14: PRODUTO 1 | C14: TEC MIC 90GSM TINTO 260CM | E14: NCM | F14: =VLOOKUP(C14,'NCMS E ALÍQUOTAS'!B2:C2225,2,FALSE) -> 5407.52.10 | I14: TX CONVERSÃO FISCAL | K14: =C11 -> 5.0579 | M14: (-) ICMS | O14: =K46/$K$12 -> 0 | R14: TX CONVERSÃO FISCAL | T14: =C11 -> 5.0579 | V14: (-) COFINS | X14: =T45/$T$12 -> #DIV/0! | AA14: 3 | AB14: MINAS | AC14: 1 | AN14: 12887.58 | AO14: 13061.56
B15: QUANTIDADE CNTR | C15: 1 | D15: =$C$15/$G$11 -> 1 | G15: =158*65*146/1000000 -> 1.49942 | I15: Total FOB R$ | K15: =K13*K14 -> 333214.45 | M15: CUSTO FINAL | O15: =O9-O10 -> 3.7556928 | P15: =P16-K16 -> 316.11875 | R15: Total FOB R$ | T15: =T13*T14 -> 0 | V15: (-) ICMS | X15: =T46/$T$12 -> #N/A | AB15: CABOTAGEM
A16: =C16 -> 122000 | B16: QUANTIDADE | C16: 122000 | D16: QUANTIDADE 1x40 | E16: 125000 | F16: =C16*0.9*0.26 -> 28548 | G16: =G15*50 -> 74.971 | I16: Frete Internacional | J16: =C19 -> 2500 | K16: =J16*K14 -> 12644.75 | M16: Outros Gastos | O16: =SUM(O17:O23) -> 0.12792745 | P16: =K16*1.025 -> 12960.869 | R16: Frete Internacional | S16: =C34 -> 0 | T16: =S16*T14 -> 0 | V16: CUSTO FINAL | X16: =X10-X11 -> #N/A | AB16: CALCULO TRANSPORTADORA IDA | AE16: CABOTAGEM
A17: =C17 -> 0.54 | B17: VALOR FOB | C17: 0.54 | D17: VALOR FOB TABELA | E17: =VLOOKUP(C14,'TABELA MATRIZ MG'!$A$2:$Y$329,25,FALSE) -> 0.48 | F17: Xx | G17: =VLOOKUP(C14,'TABELA MATRIZ MG'!$A$2:$Y$438,24,FALSE) -> 0.48 | I17: Capatazia | N17: 0 | O17: =N17/K12 -> 0 | R17: Capatazia | T17: 0 | V17: Outros Gastos | X17: =SUM(X18:X33) -> #DIV/0! | AB17: FRETE PESO | AC17: 2966 | AD17: =AC17 -> 2966 | AE17: 15000
A18: 0.54 | B18: TOTAL FOB | C18: =C16*C17 -> 65880 | D18: TOTAL FOB R$ | E18: =C18*C11 -> 333214.45 | F18: 0.2 | G18: =E18*0.2 -> 66642.89 | I18: Valor CIF | K18: =SUM(K15:K17) -> 345859.2 | M18: Comissão de vendas | N18: =E11 -> 0.02 | O18: =N18*G22 -> 0.0910422 | P18: =O18*K12 -> 11107.148 | R18: Valor aduaneiro | T18: =SUM(T15:T17) -> 0 | W18: 0 | X18: =W18/T12 -> #DIV/0! | AB18: PEDÁGIO | AC18: 61.8 | AD18: =AC18 -> 61.8
A19: =A16*A17 -> 65880 | B19: FRETE INTERNAC. USD | C19: =G10*D15 -> 2500 | D19: FRETE INTERNAC. R$ | E19: =C19*C11 -> 12644.75 | F19: 0.8 | G19: =E18*0.8 -> 266571.56 | I19: Imp. Importação | J19: =VLOOKUP($C$14,'NCMS E ALÍQUOTAS'!$B$2:$O$2225,3,FALSE) -> 0.26 | K19: =$K$18*$J$19 -> 89923.393 | O19: =N19/K12 -> 0 | R19: Imp. Importação | S19: =VLOOKUP($C$29,'NCMS E ALÍQUOTAS'!$B$2:$O$2225,3,FALSE) -> #N/A | T19: =S19*T18 -> #N/A | V19: Comissão de vendas | W19: =E11 -> 0.02 | X19: =W19*G37 -> 0 | Y19: =X19*$T$12 -> 0 | AB19: AD. VALOREM | AD19: =AC19*K24 -> 0
A20: =A16*A18 -> 65880 | B20: Total CIF USD | C20: =C19+C18 -> 68380 | D20: Total CIF R$ | E20: =C20*C11 -> 345859.2 | F20: CUSTO EM USD | G20: CUSTO EM REAIS | I20: IPI | J20: =VLOOKUP($C$14,'NCMS E ALÍQUOTAS'!$B$2:$O$2225,4,FALSE) -> 0 | K20: =$K$18*$J$20 -> 0 | M20: Operador Logistico | N20: 3000 | O20: =N20/K12 -> 0.024590164 | R20: IPI | S20: =VLOOKUP($C$29,'NCMS E ALÍQUOTAS'!$B$2:$O$2225,4,FALSE) -> #N/A | T20: =S20*$T$18 -> #N/A | V20: Administração | X20: =W20/T12 -> #DIV/0! | AB20: ADICIONAL 25 TON | AC20: 0.15 | AD20: =AC17*AC20 -> 444.9 | AL20: =2.18*25000 -> 54500
A21: =A19/A20-1 -> 0 | B21: CUSTO PROCESSO | D21: =P24+P28+P29+P31+P36+P37 -> 538162.13 | F21: =G21/$C$11 -> 0.87213369 | G21: =D21/C16 -> 4.411165 | I21: PIS | J21: =VLOOKUP($C$14,'NCMS E ALÍQUOTAS'!$B$2:$O$2225,5,FALSE) -> 0.021 | K21: =$K$18*$J$21 -> 7263.0432 | M21: Contador | N21: 1500 | O21: =N21/K12 -> 0.012295082 | R21: PIS | S21: =VLOOKUP($C$29,'NCMS E ALÍQUOTAS'!$B$2:$O$2225,5,FALSE) -> #N/A | T21: =S21*$T$18 -> #N/A | V21: Operador Logistico | W21: 0 | X21: =W21/T12 -> #DIV/0! | AB21: ICMS | AC21: 0.12 | AD21: =SUM(AD17:AD20)*AC21/0.88 -> 473.55 | AL21: =AL20*C11 -> 275655.55 | AN21: =22 -> 22
A22: =A20-A19 -> 0 | B22: PV em USD | C22: 0.9 | D22: PV TABELA | E22: =C22*C16 -> 109800 | F22: PV em R$ | G22: =$C$22*$C$11 -> 4.55211 | I22: COFINS | J22: =VLOOKUP($C$14,'NCMS E ALÍQUOTAS'!$B$2:$O$2225,6,FALSE) -> 0.1045 | K22: =$K$18*$J$22 -> 36142.287 | O22: =N22/K13 -> 0 | R22: COFINS | S22: =VLOOKUP($C$29,'NCMS E ALÍQUOTAS'!$B$2:$O$2225,6,FALSE) -> #N/A | T22: =S22*$T$18 -> #N/A | V22: Contador | X22: =W22/T12 -> #DIV/0! | AB22: TOTAL | AD22: =SUM(AD17:AD20)/0.88 -> 3946.25 | AN22: =AN21-2.2 -> 19.8 | AP22: 60
A23: =A22*A11 -> 0 | D23: =G22*C16 -> 555357.42 | F23: =G23/C11 -> 32940 | G23: =D23*0.3 -> 166607.23 | I23: Total Valor Aduaneiro | K23: =SUM(K18:K22) -> 479187.92 | O23: 0 | R23: Total Valor Aduaneiro | T23: =SUM(T18:T22) -> #N/A | V23: Salários | X23: =W23/T13 -> #DIV/0! | AB23: IBITINGA | AN23: =G22/AN21 -> 0.20691409 | AP23: 25000
A24: =A23/D23 -> 0 | B24: MARGEM | C24: =E24/D23 -> 0.030962568 | E24: =D23-D21 -> 17195.292 | F24: 0.8 | G24: =D23*0.7 -> 388750.19 | I24: BC ICMS | K24: =(SUM($K$18:$K$22)+$K$26+$K$27)/(1-$J$25) -> 480373.73 | M24: CUSTO TOTAL UNITÁRIO ANTES DA NOTA | O24: =O15+O16 -> 3.8836203 | P24: =O24*K12 -> 473801.67 | R24: BC ICMS | T24: =(SUM($T$18:$T$22)+$T$26+$T$27)/(1-$S$25) -> #N/A | V24: xxx | W24: 0 | X24: =W24/T14 -> 0 | AB24: CALCULO TRANSPORTADORA RETORNO | AP24: =AP23 -> 25000
C25: =C22/C28-1 -> 0.071428571 | F25: =D23*E11 -> 11107.148 | G25: =E24*0.05 -> 859.7646 | I25: ICMS | J25: 0 | K25: =K24*J25 -> 0 | M25: Valor Unitário USD / tx dolar di | O25: =O24/K14 -> 0.76783255 | P25: =O25*K12 -> 93675.571 | R25: ICMS | S25: 0 | T25: =T24*S25 -> #N/A | V25: xxx | X25: 0 | AB25: FRETE PESO | AC25: 2966 | AD25: =AC25/1.3 -> 2281.5385
B26: PV em USD | C26: =(C27+G23)/C16/C11 -> 0.93899353 | D26: =G26*C16 -> 579418.91 | F26: PV em R$ | G26: =$C$26*$C$11 -> 4.7493354 | I26: Siscomex | K26: =115.67+38.56 -> 154.23 | M26: Margem | O26: =O34-O33-O31-O28-O29-O24 -> 0.18545397 | P26: =O26*$K$12 -> 22625.384 | R26: Siscomex | T26: =115.67+38.56 -> 154.23 | V26: xxx | X26: 0 | AB26: PEDÁGIO | AC26: 197 | AD26: =AC26 -> 197 | AG26: =670000 -> 670000
C27: =FV(E12,C12,,G24)*-1 -> 412811.69 | E27: =D26-D21 -> 41256.785 | G27: =E24*0.95 -> 16335.527 | I27: AFRMM | J27: 0.08 | K27: =(K16)*J27+20 -> 1031.58 | M27: Base de Cálculo PIS/COFINS | O27: =G22-O33-O31 -> 4.4838283 | P27: =P24*N29 -> 36008.927 | R27: AFRMM | S27: 0.08 | T27: =(T16+T17)*S27+21.2 -> 21.2 | V27: xxx | X27: 0 | AB27: AD. VALOREM | AC27: 0.001 | AD27: =AC27*K24 -> 480.37373 | AG27: =AG26*0.001 -> 670 | AH27: 570000
C28: 0.84 | I28: S.D.A./Despachante | K28: 2500 | M28: PIS | N28: 0.0165 | O28: =$O$27*N28 -> 0.073983168 | P28: =O28*$K$12 -> 9025.9465 | R28: S.D.A./Despachante | T28: =AD43*$D$30 -> 0 | V28: xxx | X28: 0 | AB28: ADICIONAL 25 TON | AC28: 0.15 | AD28: =AC25*AC28 -> 444.9 | AH28: =AH27*0.001 -> 570
F29: =5.0579/4.5-1 -> 0.12397778 | I29: Diferença frete internacional | J29: =K14*1.025 -> 5.1843475 | K29: =(J16*J29)-K16 -> 316.11875 | M29: COFINS | N29: 0.076 | O29: =$O$27*N29 -> 0.34077095 | P29: =O29*$K$12 -> 41574.056 | R29: Diferença frete internacional | S29: =T14*1.02 -> 5.159058 | T29: =(S16*S29)-T16 -> 0 | V29: xxx | X29: 0 | AB29: ICMS | AC29: 0.12 | AD29: =SUM(AD25:AD28)*AC29/0.88 -> 464.15621
A30: =C30 -> 0 | E30: =E24/18511.7-1 -> -0.07111222 | I30: Valores Agente de cargas | K30: =AD45*$D$15 -> 1800 | M30: Base de Cálculo ICMS | O30: =G22-O33 -> 4.55211 | P30: =P24*N31 -> 7107.0251 | R30: Valores Agente de cargas | T30: =AD45*$D$30 -> 0 | V30: xxx | X30: 0 | AB30: TOTAL | AD30: =SUM(AD25:AD28)/0.88 -> 3867.9684
A31: =C31 -> 0 | I31: Armazenagem PORTO | K31: =AD46*$D$15 -> 2600 | M31: ICMS | N31: 0.015 | O31: =$G$22*$N$31 -> 0.06828165 | P31: =O31*$K$12 -> 8330.3613 | R31: Armazenagem PORTO | T31: =AD46*$D$30 -> 0 | V31: xxx | X31: 0
A32: =C32 -> 0 | I32: Capatazia | K32: =AD47*$D$15 -> 1010 | M32: BC IPI | N32: 0.04 | O32: =G22/(1+N33) -> 4.55211 | R32: Capatazia | T32: =AD47*$D$30 -> 0 | V32: xxx | X32: 0 | AB32: CALCULO TRANSPORTADORA - IBITINGA
A33: =C32 -> 0 | F33: 0.08 | I33: Custo Desembaraço - Santos | K33: =K23+SUM(K25:K32) -> 488599.85 | M33: IPI | N33: =J20 -> 0 | O33: =N33*O32 -> 0 | P33: =O33*$K$12 -> 0 | R33: Custo Desembaraço - Santos | T33: =T23+SUM(T25:T32) -> #N/A | V33: xxx | X33: 0 | AB33: FRETE PESO | AC33: 6316 | AD33: =AC33 -> 6316
A34: =A31*A32 -> 0 | I34: Frete Interno | K34: =AD49*$D$15 -> 13000 | O34: =G22 -> 4.55211 | P34: 0 | R34: Frete Interno - Pouso Alegre | T34: =AD49*$D$30 -> 0 | V34: CUSTO TOTAL UNITÁRIO | X34: =X16+X17+X39+X40+X42+X44+X47+X48+X49 -> #N/A | Y34: =X34*T12 -> #N/A | AB34: PEDÁGIO | AC34: 866.8 | AD34: =AC34 -> 866.8
A35: =A31*A33 -> 0 | M35: Base de Calculo lucro real | O35: =P26 -> 22625.384 | P35: 59999.99 | V35: Valor Unitário USD / tx dolar di | X35: =X34/T14 -> #N/A | AB35: AD. VALOREM | AC35: 0.001 | AD35: =AC35*(K33+T33) -> #N/A
A36: =A35/A34-1 -> #DIV/0! | I36: Operador Logistico | M36: CCSLL | N36: 0.09 | O36: =P36/$K$12 -> 0.016690857 | P36: =O35*N36 -> 2036.2846 | R36: Operador Logistico | T36: 1000 | V36: Margem | W36: =X36/X34 -> #N/A | X36: =X37-X34 -> #N/A | Y36: =W36*Y37 -> #N/A | AB36: ADICIONAL 25 TON | AC36: 0.15 | AD36: =AC33*AC36 -> 947.4
A37: =A34-A35 -> 0 | I37: Operação de carga e descarga | M37: IR | N37: 0.15 | O37: =P37/$K$12 -> 0.027818095 | P37: =N37*O35 -> 3393.8076 | R37: Operação de carga e descarga | V37: PREÇO DE VENDA S/ Impostos | X37: =G37 -> 0 | Y37: =X37*T12 -> 0 | AB37: ICMS | AC37: 0.12 | AD37: =SUM(AD33:AD36)*AC37/0.88 -> #N/A
A38: =A37*A26 -> 0 | I38: coleta vazio | K38: 0 | M38: adicional de IR | N38: 0.1 | O38: =P38/$K$12 -> 0 | P38: =IF(O35>=P35,(O35-P35)*N38,IF(O35<P35,P34*N38)) -> 0 | R38: coleta vazio | V38: Base de Cálculo PIS/COFINS | X38: =G37-X44-X42 -> #N/A | AB38: TOTAL | AD38: =SUM(AD33:AD36)+AD22 -> #N/A
I39: CABOTAGEM | K39: 0 | M39: PREÇO DE VENDA | N39: =O39/5.45 -> 0.83524954 | O39: =G22 -> 4.55211 | P39: =O39*K12 -> 555357.42 | R39: CABOTAGEM | T39: =IF(C10="CABOTAGEM",AE17,IF(C10="IBITINGA",AE32,IF(C10="MINAS",AE22)))*$D$30 -> 0 | V39: PIS | W39: =VLOOKUP($C$29,'NCMS E ALÍQUOTAS'!$B$2:$O$2225,7,FALSE) -> #N/A | X39: =$X$38*W39 -> #N/A | Y39: =X39*$T$12 -> #N/A
I40: Custo Processo | K40: =SUM(K33:K39) -> 501599.85 | M40: Base de Calculo DIFAL | O40: =D23+P33 -> 555357.42 | P40: =O40/0.82 -> 677265.15 | R40: Custo Processo | T40: =SUM(T33:T39) -> #N/A | V40: COFINS | W40: =VLOOKUP($C$29,'NCMS E ALÍQUOTAS'!$B$2:$O$2225,8,FALSE) -> #N/A | X40: =$X$38*W40 -> #N/A | Y40: =X40*$T$12 -> #N/A
I41: Custo Total Unitário | K41: =K40/K12 -> 4.1114742 | M41: icms difal | N41: 0.18 | P41: =P40*N41 -> 121907.73 | R41: Custo Total Unitário | T41: =T40/T12 -> #N/A | V41: Base de Cálculo ICMS | X41: =P21-X44 -> #N/A
I42: (-) CRÉDITOS S/ INSUMOS | K42: =SUM(K43:K46) -> 43405.33 | M42: icms difal mg | N42: 0.04 | P42: =N42*P40 -> 27090.606 | R42: (-) CRÉDITOS S/ INSUMOS | T42: =SUM(T43:T46) -> #N/A | V42: ICMS | W42: =VLOOKUP($E$10,$AD$12:$AE$13,2,FALSE) -> 0.015 | X42: =$G$37*$W$42 -> 0 | Y42: =X42*$T$12 -> 0 | AB42: CUSTOS FIXOS
I43: (-) IPI | J43: =J20 -> 0 | K43: =K20 -> 0 | M43: TOTAL DIFAL | R43: (-) IPI | T43: =T20 -> #N/A | V43: BC IPI | X43: =P21/(1+W44) -> #N/A | AB43: S.D.A./Despachante | AD43: 2500
C44: =280/250 -> 1.12 | D44: =C32*C44 -> 0 | E44: 0.98 | I44: (-) PIS | J44: =J21 -> 0.021 | K44: =$J$44*K18 -> 7263.0432 | R44: (-) PIS | S44: 0 | T44: =$S$44*T18 -> 0 | V44: IPI | W44: =VLOOKUP($C$29,'NCMS E ALÍQUOTAS'!$B$2:$O$2225,4,FALSE) -> #N/A | X44: =W44*X43 -> #N/A | Y44: =X44*$T$12 -> #N/A
I45: (-) COFINS | J45: =J22 -> 0.1045 | K45: =K18*$J$45 -> 36142.287 | M45: =878417.52-872137.52 -> 6280 | R45: (-) COFINS | S45: 0 | T45: =T18*$S$45 -> 0 | X45: =X34+X39+X40+X42 -> #N/A | Y45: 0 | AB45: Valores Agente de cargas | AD45: 1800
A46: =B46*C46 -> 18270 | B46: 0.435 | C46: 42000 | D46: 0.785 | E46: =C46*D46 -> 32970 | G46: =96000*0.32 -> 30720 | I46: (-) ICMS | K46: =K25 -> 0 | R46: (-) ICMS | T46: =T25 -> #N/A | V46: Base de Calculo lucro presumido | W46: 0.08 | X46: =Y37*W46 -> 0 | Y46: 59999.99 | AB46: Armazenagem PORTO | AD46: 2600
A47: =B47*C47 -> 4350 | B47: 0.435 | C47: 10000 | D47: 0.775 | E47: =C47*D47 -> 7750 | I47: CUSTO IMPORTACAO FINAL TOTAL | K47: =K40-K42 -> 458194.52 | L47: VALOR TOTAL DO CUSTO DE ENTRADA NA IMPORTACAO | R47: CUSTO FINAL TOTAL | T47: =T40-T42 -> #N/A | V47: CCSLL | W47: 0.09 | X47: =Y47/$T$12 -> #DIV/0! | Y47: =X46*W47 -> 0 | AB47: Capatazia | AD47: 1010
A48: =B48*C48 -> 12450 | B48: 0.415 | C48: 30000 | D48: 0.735 | E48: =C48*D48 -> 22050 | I48: CUSTO IMPORTACAO FINAL UNITÁRIO | K48: =K47/K12 -> 3.7556928 | M48: =870917.52-K47 -> 412723 | R48: CUSTO FINAL UNITÁRIO | T48: =T47/T12 -> #N/A | V48: IR | W48: 0.15 | X48: =Y48/$T$12 -> #DIV/0! | Y48: =W48*X46 -> 0
A49: =B49*C49 -> 16600 | B49: 0.415 | C49: 40000 | D49: 0.725 | E49: =C49*D49 -> 29000 | V49: adicional de IR | W49: 0.1 | X49: =Y49/$T$12 -> #DIV/0! | Y49: =IF(X46>=Y46,(X46-Y46)*W49,IF(X46<Y46,Y45*W49)) -> 0 | AB49: Frete NACIONAL ALL-IN | AD49: 13000
A50: =B50*C50 -> 53120 | B50: 0.415 | C50: 128000 | D50: 0.725 | E50: =C50*D50 -> 92800
V51: Base de Calculo DIFAL | X51: =D38+Y44 -> #N/A | Y51: =X51/0.82 -> #N/A | AB51: Operador Logistico | AD51: 1000
A52: =SUM(A46:A50) -> 104790 | E52: =SUM(E46:E50) -> 184570 | V52: icms difal | W52: 0.18 | Y52: =Y51*W52 -> #N/A | AB52: Operação de carga e descarga
B53: =A52/C53 -> 0.41916 | C53: =SUM(C46:C51) -> 250000 | D53: =E52/C53 -> 0.73828 | I53: 100000 | J53: =I53*0.021 -> 2100 | K53: =J53+J55 -> 3725 | V53: icms difal mg | W53: 0.04 | Y53: =W53*Y51 -> #N/A | AB53: coleta vazio
I54: 100000 | J54: =I54*0.0965 -> 9650 | K54: =J54+J56 -> 17150 | V54: adicional de IR | Y54: =Y52-Y53 -> #N/A | AB54: CABOTAGEM | AD54: =IF(C10="CABOTAGEM",AE17,IF(C10="IBITINGA",AE32,IF(C10="MINAS",AE22))) -> 0
I55: 250000 | J55: =I55*0.0065 -> 1625
I56: 250000 | J56: =I56*0.03 -> 7500
I57: 100000 | J57: =I57*0.0165 -> 1650
I58: 100000 | J58: =I58*0.0765 -> 7650
I59: 250000 | J59: =I59*0.0165 -> 4125 | K59: =J59-J57 -> 2475
D60: 5150 | I60: 250000 | J60: =I60*0.0765 -> 19125 | K60: =J60-J58 -> 11475
D61: =D60*7 -> 36050
F65: 10.5
F69: =46.8 -> 46.8 | G69: =F69/4 -> 11.7
F70: 62.1 | G70: =F70/4 -> 15.525
C74: =30720 -> 30720 | D74: =C74*4 -> 122880 | E74: =8.97 -> 8.97 | F74: =E74*4 -> 35.88
F77: =68/E74 -> 7.580825
F78: =F77*E74 -> 68 | G78: =C74*F77 -> 232882.94
F187: =F186/E186 -> #DIV/0! | G187: =G186*49.54 -> 0
D189: =0.02*10000 -> 200
C201: 115000 | D201: 68 | E201: =C201/D201 -> 1691.1765
E202: =E201*56 -> 94705.882

Sheet TABELA MATRIZ MG
A1: PRODUTO | B1: NCM | C1: II NCM | D1: IPI | E1: PIS | F1: COFINS | G1: PIS | H1: COFINS | I1: ICMS INTRA | J1: ICMS INTER | K1: Reg Espec INTRA | L1: Reg Espec INTER | M1: ICMS-ST | N1: MOQ | O1: LAI MEI | P1: TONGKHUAN | Q1: AUDREY | R1: DANIELLE | S1: EMMA/heitor | T1: MIIHYUEH | U1: AVANT | V1: KAYBEE | W1: GLOBAL | X1: MENOR VALOR FOB UNITÁRIO | Y1: VALOR FOB UNITÁRIO | Z1: FOB | AA1: FRETE INTERNACIONAL | AB1: TOTAL CIF USD | AC1: TOTAL CIF R$ | AD1: II | AE1: IPI | AF1: PIS | AG1: COFINS | AH1: TX SISCOMEX | AI1: AFRMM | AJ1: CAPATAZIAS | AK1: S.D.A./Despachante | AL1: Diferença frete int | AM1: Valores Agente de cargas | AN1: Armazenagem PORTO | AO1: FRETE RODVIÁRIO | AP1: OPERADOR LOGÍSTICO | AQ1: CREDITO PIS LUCRO REAL | AR1: CREDITO COFINS LUCRO REAL | AS1: CABOTAGEM | AT1: CUSTO DO PROCESSO R$ | AU1: CUSTO TOTAL UNITÁRIO R$ | AV1: COMISSÃO | AW1: CUSTO UNITÁRIO EM USD | AX1: Base de Cálculo PIS/COFINS | AY1: PIS | AZ1: COFINS | BA1: Base de Cálculo ICMS | BB1: ICMS | BC1: BC IPI | BD1: IPI | BE1: Base de Calculo IR | BF1: Base de Calculo csll | BG1: CSLL | BH1: IR | BI1: adicional IR | BJ1: custo VENDA | BK1: Custo total OPERAÇAO R$ | BL1: PERCENTUAL | BM1: PREÇO DE VENDA SUGERIDO USD | BN1: PREÇO DE VENDA TABELA USD | BO1: PREÇO DE VENDA JUROS TABELA USD | BP1: PREÇO DE VENDA SUGERIDO R$ | BQ1: PREÇO DE VENDA JUROS SUGERIDO R$ | BR1: PREÇO DE VENDA TABELA R$ | BS1: TOTAL VENDA SUGERIDA | BU1: TOTAL VENDA PREÇO TABELA | BV1: CUSTO TOTAL | BW1: custo total | BX1: margem | BY1: 59999.99
A2: COLCHA SOLTEIRO 60GSM SOLID | B2: 9404.40.00 | C2: 0.162 | D2: 0 | E2: 0.021 | F2: 0.0965 | G2: 0.0165 | H2: 0.076 | I2: 0.18 | J2: 0.04 | K2: 0.14 | L2: 0.015 | M2: N/A | N2: 9200 | O2: 3.05 | T2: 3.05 | X2: =MIN(O2:W2) -> 3.05 | Y2: =AVERAGE(O2:W2) -> 3.05 | Z2: =Y2*N2 -> 28060 | AA2: ='CALCULO GERAL'!$G$10 -> 6300 | AB2: =Z2+AA2 -> 34360 | AC2: =AB2*'CALCULO GERAL'!$C$11 -> 172452.84 | AD2: =AC2*C2 -> 27937.36 | AE2: =(AC2+AD2)*D2 -> 0 | AF2: =AC2*E2 -> 3621.5096 | AG2: =AC2*F2 -> 16641.699 | AH2: 154.23 | AI2: =((AA2*'CALCULO GERAL'!$C$11))*0.08+20 -> 2549.576 | AJ2: 1010 | AK2: 2500 | AL2: =(AA2*('CALCULO GERAL'!$C$11*1.02))-(AA2*'CALCULO GERAL'!$C$11) -> 632.394 | AM2: 1800 | AN2: 2600 | AO2: 9400 | AP2: 1000 | AQ2: =-AF2 -> -3621.5096 | AR2: =-AG2 -> -16641.699 | AT2: =SUM(AC2:AS2) -> 222036.4 | AU2: =IFERROR((AT2/N2),0) -> 24.134391 | AV2: =IFERROR((BS2*'CALCULO GERAL'!$E$11)/N2,0) -> 0.6615042 | AW2: =AU2/'CALCULO GERAL'!$C$11 -> 4.8086056 | AX2: =BP2-BB2-BD2*'CALCULO GERAL'!$C$11 -> 32.579082 | AY2: =AX2*G2 -> 0.53755485 | AZ2: =AX2*H2 -> 2.4760102 | BA2: =BP2-BD2 -> 33.07521 | BB2: =BA2*L2 -> 0.49612815 | BC2: =BP2/(1+D2) -> 33.07521 | BD2: =BC2*D2 -> 0 | BE2: =BT2 -> 82255.532 | BF2: =BT2 -> 82255.532 | BG2: =(BF2*0.09)/N2 -> 0.80467368 | BH2: =(BE2*0.15)/N2 -> 1.3411228 | BI2: =IF(BE2>=$BY$1,($BY$1-BE2)*0.1,IF(BE2<=$BY$1,($BY$1*0)))/N2 -> -0.24190806 | BJ2: =(AY2+AZ2+BB2+AV2+BD2+BG2+BH2+BI2) -> 6.0750858 | BK2: =BJ2+AU2 -> 30.209477 | BL2: 0.74 | BM2: =ROUND((AW2/BL2)+((AW2*BL2)*'CALCULO GERAL'!$E$11)/BL2,2) -> 6.59 | BN2: =BM2 -> 6.59 | BO2: =ROUND(FV(0.02,8,,BN2)*-1,3) -> 7.721 | BP2: =BM2*'CALCULO GERAL'!$C$11 -> 33.07521 | BQ2: =BO2*'CALCULO GERAL'!$C$11 -> 38.751699 | BR2: =BN2*'CALCULO GERAL'!$C$11 -> 33.07521 | BS2: =BP2*N2 -> 304291.93 | BT2: =BS2-AT2 -> 82255.532 | BU2: =BR2*N2 -> 304291.93 | BV2: =BK2*N2 -> 277927.19 | BW2: =BS2-BV2 -> 26364.742 | BX2: =(((BK2*N2)-BS2)/BS2*-1) -> 0.086642922 | BY2: =ROUND(BL2,2) -> 0.74 | CE2: =CC2/BY2 -> 0 | CF2: =100%-CE2 -> 1 | CG2: =AVERAGE(CF2,CD2) -> 1
A3: COLCHA CASAL 60GSM SOLID | B3: 9404.40.00 | C3: 0.162 | D3: 0 | E3: 0.021 | F3: 0.0965 | G3: 0.0165 | H3: 0.076 | I3: 0.18 | J3: 0.04 | K3: 0.14 | L3: 0.015 | M3: N/A | N3: 9200 | O3: 4.12 | T3: 4.12 | X3: =MIN(O3:W3) -> 4.12 | Y3: =AVERAGE(O3:W3) -> 4.12 | Z3: =Y3*N3 -> 37904 | AA3: ='CALCULO GERAL'!$G$10 -> 6300 | AB3: =Z3+AA3 -> 44204 | AC3: =AB3*'CALCULO GERAL'!$C$11 -> 221859.88 | AD3: =AC3*C3 -> 35941.3 | AE3: =(AC3+AD3)*D3 -> 0 | AF3: =AC3*E3 -> 4659.0574 | AG3: =AC3*F3 -> 21409.478 | AH3: 154.23 | AI3: =((AA3*'CALCULO GERAL'!$C$11))*0.08+20 -> 2549.576 | AJ3: 1010 | AK3: 2500 | AL3: =(AA3*('CALCULO GERAL'!$C$11*1.02))-(AA3*'CALCULO GERAL'!$C$11) -> 632.394 | AM3: 1800 | AN3: 2600 | AO3: 9400 | AP3: 1000 | AQ3: =-AF3 -> -4659.0574 | AR3: =-AG3 -> -21409.478 | AT3: =SUM(AC3:AS3) -> 279447.38 | AU3: =IFERROR((AT3/N3),0) -> 30.374715 | AV3: =IFERROR((BS3*'CALCULO GERAL'!$E$11)/N3,0) -> 0.833154 | AW3: =AU3/'CALCULO GERAL'!$C$11 -> 6.0519456 | AX3: =BP3-BB3-BD3*'CALCULO GERAL'!$C$11 -> 41.032835 | AY3: =AX3*G3 -> 0.67704177 | AZ3: =AX3*H3 -> 3.1184954 | BA3: =BP3-BD3 -> 41.6577 | BB3: =BA3*L3 -> 0.6248655 | BC3: =BP3/(1+D3) -> 41.6577 | BD3: =BC3*D3 -> 0 | BE3: =BU3*0.08 -> 30660.067 | BF3: =BU3*0.12 -> 45990.101 | BG3: =(BF3*0.09)/N3 -> 0.44990316 | BH3: =(BE3*0.15)/N3 -> 0.4998924 | BI3: =IF(BE3>=$BY$1,($BY$1-BE3)*0.1,IF(BE3<=$BY$1,($BY$1*0)))/N3 -> 0 | BJ3: =(AY3+AZ3+BB3+AV3+BD3+BG3+BH3+BI3) -> 6.2033523 | BK3: =BJ3+AU3 -> 36.578067 | BL3: 0.74 | BM3: =ROUND((AW3/BL3)+((AW3*BL3)*'CALCULO GERAL'!$E$11)/BL3,2) -> 8.3 | BN3: =BM3 -> 8.3 | BO3: =ROUND(FV(0.02,8,,BN3)*-1,3) -> 9.725 | BP3: =BM3*'CALCULO GERAL'!$C$11 -> 41.6577 | BQ3: =BO3*'CALCULO GERAL'!$C$11 -> 48.809775 | BR3: =BN3*'CALCULO GERAL'!$C$11 -> 41.6577 | BS3: =BP3*N3 -> 383250.84 | BT3: =BS3-AT3 -> 103803.46 | BU3: =BR3*N3 -> 383250.84 | BV3: =BK3*N3 -> 336518.22 | BW3: =BS3-BV3 -> 46732.623 | BX3: =(((BK3*N3)-BS3)/BS3*-1) -> 0.12193743 | BY3: =ROUND(BL3,2) -> 0.74 | CE3: =CC3/BY3 -> 0 | CF3: =100%-CE3 -> 1 | CG3: =AVERAGE(CF3,CD3) -> 1
A4: COLCHA QUEEN 60GSM SOLID | B4: 9404.40.00 | C4: 0.162 | D4: 0 | E4: 0.021 | F4: 0.0965 | G4: 0.0165 | H4: 0.076 | I4: 0.18 | J4: 0.04 | K4: 0.14 | L4: 0.015 | M4: N/A | N4: 9200 | O4: 4.6 | T4: 4.6 | X4: =MIN(O4:W4) -> 4.6 | Y4: =AVERAGE(O4:W4) -> 4.6 | Z4: =Y4*N4 -> 42320 | AA4: ='CALCULO GERAL'!$G$10 -> 6300 | AB4: =Z4+AA4 -> 48620 | AC4: =AB4*'CALCULO GERAL'!$C$11 -> 244023.78 | AD4: =AC4*C4 -> 39531.852 | AE4: =(AC4+AD4)*D4 -> 0 | AF4: =AC4*E4 -> 5124.4994 | AG4: =AC4*F4 -> 23548.295 | AH4: 154.23 | AI4: =((AA4*'CALCULO GERAL'!$C$11))*0.08+20 -> 2549.576 | AJ4: 1010 | AK4: 2500 | AL4: =(AA4*('CALCULO GERAL'!$C$11*1.02))-(AA4*'CALCULO GERAL'!$C$11) -> 632.394 | AM4: 1800 | AN4: 2600 | AO4: 9400 | AP4: 1000 | AQ4: =-AF4 -> -5124.4994 | AR4: =-AG4 -> -23548.295 | AT4: =SUM(AC4:AS4) -> 305201.83 | AU4: =IFERROR((AT4/N4),0) -> 33.174112 | AV4: =IFERROR((BS4*'CALCULO GERAL'!$E$11)/N4,0) -> 0.9094428 | AW4: =AU4/'CALCULO GERAL'!$C$11 -> 6.6097056 | AX4: =BP4-BB4-BD4*'CALCULO GERAL'!$C$11 -> 44.790058 | AY4: =AX4*G4 -> 0.73903596 | AZ4: =AX4*H4 -> 3.4040444 | BA4: =BP4-BD4 -> 45.47214 | BB4: =BA4*L4 -> 0.6820821 | BC4: =BP4/(1+D4) -> 45.47214 | BD4: =BC4*D4 -> 0 | BE4: =BU4*0.08 -> 33467.495 | BF4: =BU4*0.12 -> 50201.243 | BG4: =(BF4*0.09)/N4 -> 0.49109911 | BH4: =(BE4*0.15)/N4 -> 0.54566568 | BI4: =IF(BE4>=$BY$1,($BY$1-BE4)*0.1,IF(BE4<=$BY$1,($BY$1*0)))/N4 -> 0 | BJ4: =(AY4+AZ4+BB4+AV4+BD4+BG4+BH4+BI4) -> 6.77137 | BK4: =BJ4+AU4 -> 39.945482 | BL4: 0.74 | BM4: =ROUND((AW4/BL4)+((AW4*BL4)*'CALCULO GERAL'!$E$11)/BL4,2) -> 9.06 | BN4: =BM4 -> 9.06 | BO4: =ROUND(FV(0.02,8,,BN4)*-1,3) -> 10.615 | BP4: =BM4*'CALCULO GERAL'!$C$11 -> 45.47214 | BQ4: =BO4*'CALCULO GERAL'!$C$11 -> 53.276685 | BR4: =BN4*'CALCULO GERAL'!$C$11 -> 45.47214 | BS4: =BP4*N4 -> 418343.69 | BT4: =BS4-AT4 -> 113141.86 | BU4: =BR4*N4 -> 418343.69 | BV4: =BK4*N4 -> 367498.44 | BW4: =BS4-BV4 -> 50845.251 | BX4: =(((BK4*N4)-BS4)/BS4*-1) -> 0.12153942 | BY4: =ROUND(BL4,2) -> 0.74 | CE4: =CC4/BY4 -> 0 | CF4: =100%-CE4 -> 1 | CG4: =AVERAGE(CF4,CD4) -> 1
A5: COLCHA KING 60GSM SOLID | B5: 9404.40.00 | C5: 0.162 | D5: 0 | E5: 0.021 | F5: 0.0965 | G5: 0.0165 | H5: 0.076 | I5: 0.18 | J5: 0.04 | K5: 0.14 | L5: 0.015 | M5: N/A | N5: 9200 | O5: 5.1 | T5: 5.1 | X5: =MIN(O5:W5) -> 5.1 | Y5: =AVERAGE(O5:W5) -> 5.1 | Z5: =Y5*N5 -> 46920 | AA5: ='CALCULO GERAL'!$G$10 -> 6300 | AB5: =Z5+AA5 -> 53220 | AC5: =AB5*'CALCULO GERAL'!$C$11 -> 267111.18 | AD5: =AC5*C5 -> 43272.011 | AE5: =(AC5+AD5)*D5 -> 0 | AF5: =AC5*E5 -> 5609.3348 | AG5: =AC5*F5 -> 25776.229 | AH5: 154.23 | AI5: =((AA5*'CALCULO GERAL'!$C$11))*0.08+20 -> 2549.576 | AJ5: 1010 | AK5: 2500 | AL5: =(AA5*('CALCULO GERAL'!$C$11*1.02))-(AA5*'CALCULO GERAL'!$C$11) -> 632.394 | AM5: 1800 | AN5: 2600 | AO5: 9400 | AP5: 1000 | AQ5: =-AF5 -> -5609.3348 | AR5: =-AG5 -> -25776.229 | AT5: =SUM(AC5:AS5) -> 332029.39 | AU5: =IFERROR((AT5/N5),0) -> 36.090151 | AV5: =IFERROR((BS5*'CALCULO GERAL'!$E$11)/N5,0) -> 0.9897468 | AW5: =AU5/'CALCULO GERAL'!$C$11 -> 7.1907056 | AX5: =BP5-BB5-BD5*'CALCULO GERAL'!$C$11 -> 48.74503 | AY5: =AX5*G5 -> 0.80429299 | AZ5: =AX5*H5 -> 3.7046223 | BA5: =BP5-BD5 -> 49.48734 | BB5: =BA5*L5 -> 0.7423101 | BC5: =BP5/(1+D5) -> 49.48734 | BD5: =BC5*D5 -> 0 | BE5: =BU5*0.08 -> 36422.682 | BF5: =BU5*0.12 -> 54634.023 | BG5: =(BF5*0.09)/N5 -> 0.53446327 | BH5: =(BE5*0.15)/N5 -> 0.59384808 | BI5: =IF(BE5>=$BY$1,($BY$1-BE5)*0.1,IF(BE5<=$BY$1,($BY$1*0)))/N5 -> 0 | BJ5: =(AY5+AZ5+BB5+AV5+BD5+BG5+BH5+BI5) -> 7.3692835 | BK5: =BJ5+AU5 -> 43.459435 | BL5: 0.74 | BM5: =ROUND((AW5/BL5)+((AW5*BL5)*'CALCULO GERAL'!$E$11)/BL5,2) -> 9.86 | BN5: =BM5 -> 9.86 | BO5: =ROUND(FV(0.02,8,,BN5)*-1,3) -> 11.553 | BP5: =BM5*'CALCULO GERAL'!$C$11 -> 49.48734 | BQ5: =BO5*'CALCULO GERAL'!$C$11 -> 57.984507 | BR5: =BN5*'CALCULO GERAL'!$C$11 -> 49.48734 | BS5: =BP5*N5 -> 455283.53 | BT5: =BS5-AT5 -> 123254.14 | BU5: =BR5*N5 -> 455283.53 | BV5: =BK5*N5 -> 399826.8 | BW5: =BS5-BV5 -> 55456.728 | BX5: =(((BK5*N5)-BS5)/BS5*-1) -> 0.12180702 | BY5: =ROUND(BL5,2) -> 0.74 | CE5: =CC5/BY5 -> 0 | CF5: =100%-CE5 -> 1 | CG5: =AVERAGE(CF5,CD5) -> 1
A6: COLCHA SOLTEIRO 65GSM ESTAMPADA | B6: 9404.40.00 | C6: 0.162 | D6: 0 | E6: 0.021 | F6: 0.0965 | G6: 0.0165 | H6: 0.076 | I6: 0.18 | J6: 0.04 | K6: 0.14 | L6: 0.015 | M6: N/A | N6: 9200 | O6: 3.06 | T6: 3.06 | X6: =MIN(O6:W6) -> 3.06 | Y6: =AVERAGE(O6:W6) -> 3.06 | Z6: =Y6*N6 -> 28152 | AA6: ='CALCULO GERAL'!$G$10 -> 6300 | AB6: =Z6+AA6 -> 34452 | AC6: =AB6*'CALCULO GERAL'!$C$11 -> 172914.59 | AD6: =AC6*C6 -> 28012.163 | AE6: =(AC6+AD6)*D6 -> 0 | AF6: =AC6*E6 -> 3631.2063 | AG6: =AC6*F6 -> 16686.258 | AH6: 154.23 | AI6: =((AA6*'CALCULO GERAL'!$C$11))*0.08+20 -> 2549.576 | AJ6: 1010 | AK6: 2500 | AL6: =(AA6*('CALCULO GERAL'!$C$11*1.02))-(AA6*'CALCULO GERAL'!$C$11) -> 632.394 | AM6: 1800 | AN6: 2600 | AO6: 9400 | AP6: 1000 | AQ6: =-AF6 -> -3631.2063 | AR6: =-AG6 -> -16686.258 | AT6: =SUM(AC6:AS6) -> 222572.95 | AU6: =IFERROR((AT6/N6),0) -> 24.192712 | AV6: =IFERROR((BS6*'CALCULO GERAL'!$E$11)/N6,0) -> 0.6635118 | AW6: =AU6/'CALCULO GERAL'!$C$11 -> 4.8202256 | AX6: =BP6-BB6-BD6*'CALCULO GERAL'!$C$11 -> 32.677956 | AY6: =AX6*G6 -> 0.53918628 | AZ6: =AX6*H6 -> 2.4835247 | BA6: =BP6-BD6 -> 33.17559 | BB6: =BA6*L6 -> 0.49763385 | BC6: =BP6/(1+D6) -> 33.17559 | BD6: =BC6*D6 -> 0 | BE6: =BU6*0.08 -> 24417.234 | BF6: =BU6*0.12 -> 36625.851 | BG6: =(BF6*0.09)/N6 -> 0.35829637 | BH6: =(BE6*0.15)/N6 -> 0.39810708 | BI6: =IF(BE6>=$BY$1,($BY$1-BE6)*0.1,IF(BE6<=$BY$1,($BY$1*0)))/N6 -> 0 | BJ6: =(AY6+AZ6+BB6+AV6+BD6+BG6+BH6+BI6) -> 4.94026 | BK6: =BJ6+AU6 -> 29.132972 | BL6: 0.74 | BM6: =ROUND((AW6/BL6)+((AW6*BL6)*'CALCULO GERAL'!$E$11)/BL6,2) -> 6.61 | BN6: =BM6 -> 6.61 | BO6: =ROUND(FV(0.02,8,,BN6)*-1,3) -> 7.745 | BP6: =BM6*'CALCULO GERAL'!$C$11 -> 33.17559 | BQ6: =BO6*'CALCULO GERAL'!$C$11 -> 38.872155 | BR6: =BN6*'CALCULO GERAL'!$C$11 -> 33.17559 | BS6: =BP6*N6 -> 305215.43 | BT6: =BS6-AT6 -> 82642.477 | BU6: =BR6*N6 -> 305215.43 | BV6: =BK6*N6 -> 268023.34 | BW6: =BS6-BV6 -> 37192.084 | BX6: =(((BK6*N6)-BS6)/BS6*-1) -> 0.12185519 | BY6: =ROUND(BL6,2) -> 0.74 | CE6: =CC6/BY6 -> 0 | CF6: =100%-CE6 -> 1 | CG6: =AVERAGE(CF6,CD6) -> 1
A7: COLCHA CASAL 65GSM ESTAMPADA | B7: 9404.40.00 | C7: 0.162 | D7: 0 | E7: 0.021 | F7: 0.0965 | G7: 0.0165 | H7: 0.076 | I7: 0.18 | J7: 0.04 | K7: 0.14 | L7: 0.015 | M7: N/A | N7: 9200 | O7: 4.13 | T7: 4.13 | X7: =MIN(O7:W7) -> 4.13 | Y7: =AVERAGE(O7:W7) -> 4.13 | Z7: =Y7*N7 -> 37996 | AA7: ='CALCULO GERAL'!$G$10 -> 6300 | AB7: =Z7+AA7 -> 44296 | AC7: =AB7*'CALCULO GERAL'!$C$11 -> 222321.62 | AD7: =AC7*C7 -> 36016.103 | AE7: =(AC7+AD7)*D7 -> 0 | AF7: =AC7*E7 -> 4668.7541 | AG7: =AC7*F7 -> 21454.037 | AH7: 154.23 | AI7: =((AA7*'CALCULO GERAL'!$C$11))*0.08+20 -> 2549.576 | AJ7: 1010 | AK7: 2500 | AL7: =(AA7*('CALCULO GERAL'!$C$11*1.02))-(AA7*'CALCULO GERAL'!$C$11) -> 632.394 | AM7: 1800 | AN7: 2600 | AO7: 9400 | AP7: 1000 | AQ7: =-AF7 -> -4668.7541 | AR7: =-AG7 -> -21454.037 | AT7: =SUM(AC7:AS7) -> 279983.93 | AU7: =IFERROR((AT7/N7),0) -> 30.433036 | AV7: =IFERROR((BS7*'CALCULO GERAL'!$E$11)/N7,0) -> 0.8351616 | AW7: =AU7/'CALCULO GERAL'!$C$11 -> 6.0635656 | AX7: =BP7-BB7-BD7*'CALCULO GERAL'!$C$11 -> 41.131709 | AY7: =AX7*G7 -> 0.6786732 | AZ7: =AX7*H7 -> 3.1260099 | BA7: =BP7-BD7 -> 41.75808 | BB7: =BA7*L7 -> 0.6263712 | BC7: =BP7/(1+D7) -> 41.75808 | BD7: =BC7*D7 -> 0 | BE7: =BU7*0.08 -> 30733.947 | BF7: =BU7*0.12 -> 46100.92 | BG7: =(BF7*0.09)/N7 -> 0.45098726 | BH7: =(BE7*0.15)/N7 -> 0.50109696 | BI7: =IF(BE7>=$BY$1,($BY$1-BE7)*0.1,IF(BE7<=$BY$1,($BY$1*0)))/N7 -> 0 | BJ7: =(AY7+AZ7+BB7+AV7+BD7+BG7+BH7+BI7) -> 6.2183001 | BK7: =BJ7+AU7 -> 36.651336 | BL7: 0.74 | BM7: =ROUND((AW7/BL7)+((AW7*BL7)*'CALCULO GERAL'!$E$11)/BL7,2) -> 8.32 | BN7: =BM7 -> 8.32 | BO7: =ROUND(FV(0.02,8,,BN7)*-1,3) -> 9.748 | BP7: =BM7*'CALCULO GERAL'!$C$11 -> 41.75808 | BQ7: =BO7*'CALCULO GERAL'!$C$11 -> 48.925212 | BR7: =BN7*'CALCULO GERAL'!$C$11 -> 41.75808 | BS7: =BP7*N7 -> 384174.34 | BT7: =BS7-AT7 -> 104190.41 | BU7: =BR7*N7 -> 384174.34 | BV7: =BK7*N7 -> 337192.29 | BW7: =BS7-BV7 -> 46982.048 | BX7: =(((BK7*N7)-BS7)/BS7*-1) -> 0.12229356 | BY7: =ROUND(BL7,2) -> 0.74 | CE7: =CC7/BY7 -> 0 | CF7: =100%-CE7 -> 1 | CG7: =AVERAGE(CF7,CD7) -> 1
A8: COLCHA QUEEN 65GSM ESTAMPADA | B8: 9404.40.00 | C8: 0.162 | D8: 0 | E8: 0.021 | F8: 0.0965 | G8: 0.0165 | H8: 0.076 | I8: 0.18 | J8: 0.04 | K8: 0.14 | L8: 0.015 | M8: N/A | N8: 9200 | O8: 4.62 | T8: 4.62 | X8: =MIN(O8:W8) -> 4.62 | Y8: =AVERAGE(O8:W8) -> 4.62 | Z8: =Y8*N8 -> 42504 | AA8: ='CALCULO GERAL'!$G$10 -> 6300 | AB8: =Z8+AA8 -> 48804 | AC8: =AB8*'CALCULO GERAL'!$C$11 -> 244947.28 | AD8: =AC8*C8 -> 39681.459 | AE8: =(AC8+AD8)*D8 -> 0 | AF8: =AC8*E8 -> 5143.8928 | AG8: =AC8*F8 -> 23637.412 | AH8: 154.23 | AI8: =((AA8*'CALCULO GERAL'!$C$11))*0.08+20 -> 2549.576 | AJ8: 1010 | AK8: 2500 | AL8: =(AA8*('CALCULO GERAL'!$C$11*1.02))-(AA8*'CALCULO GERAL'!$C$11) -> 632.394 | AM8: 1800 | AN8: 2600 | AO8: 9400 | AP8: 1000 | AQ8: =-AF8 -> -5143.8928 | AR8: =-AG8 -> -23637.412 | AT8: =SUM(AC8:AS8) -> 306274.93 | AU8: =IFERROR((AT8/N8),0) -> 33.290754 | AV8: =IFERROR((BS8*'CALCULO GERAL'!$E$11)/N8,0) -> 0.913458 | AW8: =AU8/'CALCULO GERAL'!$C$11 -> 6.6329456 | AX8: =BP8-BB8-BD8*'CALCULO GERAL'!$C$11 -> 44.987806 | AY8: =AX8*G8 -> 0.74229881 | AZ8: =AX8*H8 -> 3.4190733 | BA8: =BP8-BD8 -> 45.6729 | BB8: =BA8*L8 -> 0.6850935 | BC8: =BP8/(1+D8) -> 45.6729 | BD8: =BC8*D8 -> 0 | BE8: =BU8*0.08 -> 33615.254 | BF8: =BU8*0.12 -> 50422.882 | BG8: =(BF8*0.09)/N8 -> 0.49326732 | BH8: =(BE8*0.15)/N8 -> 0.5480748 | BI8: =IF(BE8>=$BY$1,($BY$1-BE8)*0.1,IF(BE8<=$BY$1,($BY$1*0)))/N8 -> 0 | BJ8: =(AY8+AZ8+BB8+AV8+BD8+BG8+BH8+BI8) -> 6.8012657 | BK8: =BJ8+AU8 -> 40.092019 | BL8: 0.74 | BM8: =ROUND((AW8/BL8)+((AW8*BL8)*'CALCULO GERAL'!$E$11)/BL8,2) -> 9.1 | BN8: =BM8 -> 9.1 | BO8: =ROUND(FV(0.02,8,,BN8)*-1,3) -> 10.662 | BP8: =BM8*'CALCULO GERAL'!$C$11 -> 45.6729 | BQ8: =BO8*'CALCULO GERAL'!$C$11 -> 53.512578 | BR8: =BN8*'CALCULO GERAL'!$C$11 -> 45.6729 | BS8: =BP8*N8 -> 420190.68 | BT8: =BS8-AT8 -> 113915.75 | BU8: =BR8*N8 -> 420190.68 | BV8: =BK8*N8 -> 368846.58 | BW8: =BS8-BV8 -> 51344.101 | BX8: =(((BK8*N8)-BS8)/BS8*-1) -> 0.12219238 | BY8: =ROUND(BL8,2) -> 0.74 | CE8: =CC8/BY8 -> 0 | CF8: =100%-CE8 -> 1 | CG8: =AVERAGE(CF8,CD8) -> 1
A9: COLCHA KING 65GSM ESTAMPADA | B9: 9404.40.00 | C9: 0.162 | D9: 0 | E9: 0.021 | F9: 0.0965 | G9: 0.0165 | H9: 0.076 | I9: 0.18 | J9: 0.04 | K9: 0.14 | L9: 0.015 | M9: N/A | N9: 9200 | O9: 5.13 | T9: 5.13 | X9: =MIN(O9:W9) -> 5.13 | Y9: =AVERAGE(O9:W9) -> 5.13 | Z9: =Y9*N9 -> 47196 | AA9: ='CALCULO GERAL'!$G$10 -> 6300 | AB9: =Z9+AA9 -> 53496 | AC9: =AB9*'CALCULO GERAL'!$C$11 -> 268496.42 | AD9: =AC9*C9 -> 43496.421 | AE9: =(AC9+AD9)*D9 -> 0 | AF9: =AC9*E9 -> 5638.4249 | AG9: =AC9*F9 -> 25909.905 | AH9: 154.23 | AI9: =((AA9*'CALCULO GERAL'!$C$11))*0.08+20 -> 2549.576 | AJ9: 1010 | AK9: 2500 | AL9: =(AA9*('CALCULO GERAL'!$C$11*1.02))-(AA9*'CALCULO GERAL'!$C$11) -> 632.394 | AM9: 1800 | AN9: 2600 | AO9: 9400 | AP9: 1000 | AQ9: =-AF9 -> -5638.4249 | AR9: =-AG9 -> -25909.905 | AT9: =SUM(AC9:AS9) -> 333639.04 | AU9: =IFERROR((AT9/N9),0) -> 36.265114 | AV9: =IFERROR((BS9*'CALCULO GERAL'!$E$11)/N9,0) -> 0.9947658 | AW9: =AU9/'CALCULO GERAL'!$C$11 -> 7.2255656 | AX9: =BP9-BB9-BD9*'CALCULO GERAL'!$C$11 -> 48.992216 | AY9: =AX9*G9 -> 0.80837156 | AZ9: =AX9*H9 -> 3.7234084 | BA9: =BP9-BD9 -> 49.73829 | BB9: =BA9*L9 -> 0.74607435 | BC9: =BP9/(1+D9) -> 49.73829 | BD9: =BC9*D9 -> 0 | BE9: =BU9*0.08 -> 36607.381 | BF9: =BU9*0.12 -> 54911.072 | BG9: =(BF9*0.09)/N9 -> 0.53717353 | BH9: =(BE9*0.15)/N9 -> 0.59685948 | BI9: =IF(BE9>=$BY$1,($BY$1-BE9)*0.1,IF(BE9<=$BY$1,($BY$1*0)))/N9 -> 0 | BJ9: =(AY9+AZ9+BB9+AV9+BD9+BG9+BH9+BI9) -> 7.4066531 | BK9: =BJ9+AU9 -> 43.671767 | BL9: 0.74 | BM9: =ROUND((AW9/BL9)+((AW9*BL9)*'CALCULO GERAL'!$E$11)/BL9,2) -> 9.91 | BN9: =BM9 -> 9.91 | BO9: =ROUND(FV(0.02,8,,BN9)*-1,3) -> 11.611 | BP9: =BM9*'CALCULO GERAL'!$C$11 -> 49.73829 | BQ9: =BO9*'CALCULO GERAL'!$C$11 -> 58.275609 | BR9: =BN9*'CALCULO GERAL'!$C$11 -> 49.73829 | BS9: =BP9*N9 -> 457592.27 | BT9: =BS9-AT9 -> 123953.22 | BU9: =BR9*N9 -> 457592.27 | BV9: =BK9*N9 -> 401780.25 | BW9: =BS9-BV9 -> 55812.015 | BX9: =(((BK9*N9)-BS9)/BS9*-1) -> 0.12196888 | BY9: =ROUND(BL9,2) -> 0.74 | CE9: =CC9/BY9 -> 0 | CF9: =100%-CE9 -> 1 | CG9: =AVERAGE(CF9,CD9) -> 1
A10: COLCHA SOLTEIRO 70GSM SOLID 3D | B10: 9404.40.00 | C10: 0.162 | D10: 0 | E10: 0.021 | F10: 0.0965 | G10: 0.0165 | H10: 0.076 | I10: 0.18 | J10: 0.04 | K10: 0.14 | L10: 0.015 | M10: N/A | N10: 6000 | O10: 4.71 | T10: 4.71 | X10: =MIN(O10:W10) -> 4.71 | Y10: =AVERAGE(O10:W10) -> 4.71 | Z10: =Y10*N10 -> 28260 | AA10: ='CALCULO GERAL'!$G$10 -> 6300 | AB10: =Z10+AA10 -> 34560 | AC10: =AB10*'CALCULO GERAL'!$C$11 -> 173456.64 | AD10: =AC10*C10 -> 28099.976 | AE10: =(AC10+AD10)*D10 -> 0 | AF10: =AC10*E10 -> 3642.5894 | AG10: =AC10*F10 -> 16738.566 | AH10: 154.23 | AI10: =((AA10*'CALCULO GERAL'!$C$11))*0.08+20 -> 2549.576 | AJ10: 1010 | AK10: 2500 | AL10: =(AA10*('CALCULO GERAL'!$C$11*1.02))-(AA10*'CALCULO GERAL'!$C$11) -> 632.394 | AM10: 1800 | AN10: 2600 | AO10: 9400 | AP10: 1000 | AQ10: =-AF10 -> -3642.5894 | AR10: =-AG10 -> -16738.566 | AT10: =SUM(AC10:AS10) -> 223202.82 | AU10: =IFERROR((AT10/N10),0) -> 37.200469 | AV10: =IFERROR((BS10*'CALCULO GERAL'!$E$11)/N10,0) -> 1.0198608 | AW10: =AU10/'CALCULO GERAL'!$C$11 -> 7.4119285 | AX10: =BP10-BB10-BD10*'CALCULO GERAL'!$C$11 -> 50.228144 | AY10: =AX10*G10 -> 0.82876438 | AZ10: =AX10*H10 -> 3.817339 | BA10: =BP10-BD10 -> 50.99304 | BB10: =BA10*L10 -> 0.7648956 | BC10: =BP10/(1+D10) -> 50.99304 | BD10: =BC10*D10 -> 0 | BE10: =BU10*0.08 -> 24476.659 | BF10: =BU10*0.12 -> 36714.989 | BG10: =(BF10*0.09)/N10 -> 0.55072483 | BH10: =(BE10*0.15)/N10 -> 0.61191648 | BI10: =IF(BE10>=$BY$1,($BY$1-BE10)*0.1,IF(BE10<=$BY$1,($BY$1*0)))/N10 -> 0 | BJ10: =(AY10+AZ10+BB10+AV10+BD10+BG10+BH10+BI10) -> 7.5935011 | BK10: =BJ10+AU10 -> 44.79397 | BL10: 0.74 | BM10: =ROUND((AW10/BL10)+((AW10*BL10)*'CALCULO GERAL'!$E$11)/BL10,2) -> 10.16 | BN10: =BM10 -> 10.16 | BO10: =ROUND(FV(0.02,8,,BN10)*-1,3) -> 11.904 | BP10: =BM10*'CALCULO GERAL'!$C$11 -> 50.99304 | BQ10: =BO10*'CALCULO GERAL'!$C$11 -> 59.746176 | BR10: =BN10*'CALCULO GERAL'!$C$11 -> 50.99304 | BS10: =BP10*N10 -> 305958.24 | BT10: =BS10-AT10 -> 82755.424 | BU10: =BR10*N10 -> 305958.24 | BV10: =BK10*N10 -> 268763.82 | BW10: =BS10-BV10 -> 37194.418 | BX10: =(((BK10*N10)-BS10)/BS10*-1) -> 0.12156698 | BY10: =ROUND(BL10,2) -> 0.74 | CE10: =CC10/BY10 -> 0 | CF10: =100%-CE10 -> 1 | CG10: =AVERAGE(CF10,CD10) -> 1
A11: COLCHA CASAL 70GSM SOLID 3D | B11: 9404.40.00 | C11: 0.162 | D11: 0 | E11: 0.021 | F11: 0.0965 | G11: 0.0165 | H11: 0.076 | I11: 0.18 | J11: 0.04 | K11: 0.14 | L11: 0.015 | M11: N/A | N11: 6000 | O11: 6.22 | T11: 6.22 | X11: =MIN(O11:W11) -> 6.22 | Y11: =AVERAGE(O11:W11) -> 6.22 | Z11: =Y11*N11 -> 37320 | AA11: ='CALCULO GERAL'!$G$10 -> 6300 | AB11: =Z11+AA11 -> 43620 | AC11: =AB11*'CALCULO GERAL'!$C$11 -> 218928.78 | AD11: =AC11*C11 -> 35466.462 | AE11: =(AC11+AD11)*D11 -> 0 | AF11: =AC11*E11 -> 4597.5044 | AG11: =AC11*F11 -> 21126.627 | AH11: 154.23 | AI11: =((AA11*'CALCULO GERAL'!$C$11))*0.08+20 -> 2549.576 | AJ11: 1010 | AK11: 2500 | AL11: =(AA11*('CALCULO GERAL'!$C$11*1.02))-(AA11*'CALCULO GERAL'!$C$11) -> 632.394 | AM11: 1800 | AN11: 2600 | AO11: 9400 | AP11: 1000 | AQ11: =-AF11 -> -4597.5044 | AR11: =-AG11 -> -21126.627 | AT11: =SUM(AC11:AS11) -> 276041.44 | AU11: =IFERROR((AT11/N11),0) -> 46.006907 | AV11: =IFERROR((BS11*'CALCULO GERAL'!$E$11)/N11,0) -> 1.2617766 | AW11: =AU11/'CALCULO GERAL'!$C$11 -> 9.1665485 | AX11: =BP11-BB11-BD11*'CALCULO GERAL'!$C$11 -> 62.142498 | AY11: =AX11*G11 -> 1.0253512 | AZ11: =AX11*H11 -> 4.7228298 | BA11: =BP11-BD11 -> 63.08883 | BB11: =BA11*L11 -> 0.94633245 | BC11: =BP11/(1+D11) -> 63.08883 | BD11: =BC11*D11 -> 0 | BE11: =BU11*0.08 -> 30282.638 | BF11: =BU11*0.12 -> 45423.958 | BG11: =(BF11*0.09)/N11 -> 0.68135936 | BH11: =(BE11*0.15)/N11 -> 0.75706596 | BI11: =IF(BE11>=$BY$1,($BY$1-BE11)*0.1,IF(BE11<=$BY$1,($BY$1*0)))/N11 -> 0 | BJ11: =(AY11+AZ11+BB11+AV11+BD11+BG11+BH11+BI11) -> 9.3947154 | BK11: =BJ11+AU11 -> 55.401622 | BL11: 0.74 | BM11: =ROUND((AW11/BL11)+((AW11*BL11)*'CALCULO GERAL'!$E$11)/BL11,2) -> 12.57 | BN11: =BM11 -> 12.57 | BO11: =ROUND(FV(0.02,8,,BN11)*-1,3) -> 14.728 | BP11: =BM11*'CALCULO GERAL'!$C$11 -> 63.08883 | BQ11: =BO11*'CALCULO GERAL'!$C$11 -> 73.919832 | BR11: =BN11*'CALCULO GERAL'!$C$11 -> 63.08883 | BS11: =BP11*N11 -> 378532.98 | BT11: =BS11-AT11 -> 102491.54 | BU11: =BR11*N11 -> 378532.98 | BV11: =BK11*N11 -> 332409.73 | BW11: =BS11-BV11 -> 46123.245 | BX11: =(((BK11*N11)-BS11)/BS11*-1) -> 0.12184736 | BY11: =ROUND(BL11,2) -> 0.74 | CE11: =CC11/BY11 -> 0 | CF11: =100%-CE11 -> 1 | CG11: =AVERAGE(CF11,CD11) -> 1
A12: COLCHA QUEEN 70GSM SOLID 3D | B12: 9404.40.00 | C12: 0.162 | D12: 0 | E12: 0.021 | F12: 0.0965 | G12: 0.0165 | H12: 0.076 | I12: 0.18 | J12: 0.04 | K12: 0.14 | L12: 0.015 | M12: N/A | N12: 6000 | O12: 6.74 | T12: 6.74 | X12: =MIN(O12:W12) -> 6.74 | Y12: =AVERAGE(O12:W12) -> 6.74 | Z12: =Y12*N12 -> 40440 | AA12: ='CALCULO GERAL'!$G$10 -> 6300 | AB12: =Z12+AA12 -> 46740 | AC12: =AB12*'CALCULO GERAL'!$C$11 -> 234588.06 | AD12: =AC12*C12 -> 38003.266 | AE12: =(AC12+AD12)*D12 -> 0 | AF12: =AC12*E12 -> 4926.3493 | AG12: =AC12*F12 -> 22637.748 | AH12: 154.23 | AI12: =((AA12*'CALCULO GERAL'!$C$11))*0.08+20 -> 2549.576 | AJ12: 1010 | AK12: 2500 | AL12: =(AA12*('CALCULO GERAL'!$C$11*1.02))-(AA12*'CALCULO GERAL'!$C$11) -> 632.394 | AM12: 1800 | AN12: 2600 | AO12: 9400 | AP12: 1000 | AQ12: =-AF12 -> -4926.3493 | AR12: =-AG12 -> -22637.748 | AT12: =SUM(AC12:AS12) -> 294237.53 | AU12: =IFERROR((AT12/N12),0) -> 49.039588 | AV12: =IFERROR((BS12*'CALCULO GERAL'!$E$11)/N12,0) -> 1.345092 | AW12: =AU12/'CALCULO GERAL'!$C$11 -> 9.7707885 | AX12: =BP12-BB12-BD12*'CALCULO GERAL'!$C$11 -> 66.245781 | AY12: =AX12*G12 -> 1.0930554 | AZ12: =AX12*H12 -> 5.0346794 | BA12: =BP12-BD12 -> 67.2546 | BB12: =BA12*L12 -> 1.008819 | BC12: =BP12/(1+D12) -> 67.2546 | BD12: =BC12*D12 -> 0 | BE12: =BU12*0.08 -> 32282.208 | BF12: =BU12*0.12 -> 48423.312 | BG12: =(BF12*0.09)/N12 -> 0.72634968 | BH12: =(BE12*0.15)/N12 -> 0.8070552 | BI12: =IF(BE12>=$BY$1,($BY$1-BE12)*0.1,IF(BE12<=$BY$1,($BY$1*0)))/N12 -> 0 | BJ12: =(AY12+AZ12+BB12+AV12+BD12+BG12+BH12+BI12) -> 10.015051 | BK12: =BJ12+AU12 -> 59.054638 | BL12: 0.74 | BM12: =ROUND((AW12/BL12)+((AW12*BL12)*'CALCULO GERAL'!$E$11)/BL12,2) -> 13.4 | BN12: =BM12 -> 13.4 | BO12: =ROUND(FV(0.02,8,,BN12)*-1,3) -> 15.7 | BP12: =BM12*'CALCULO GERAL'!$C$11 -> 67.2546 | BQ12: =BO12*'CALCULO GERAL'!$C$11 -> 78.7983 | BR12: =BN12*'CALCULO GERAL'!$C$11 -> 67.2546 | BS12: =BP12*N12 -> 403527.6 | BT12: =BS12-AT12 -> 109290.07 | BU12: =BR12*N12 -> 403527.6 | BV12: =BK12*N12 -> 354327.83 | BW12: =BS12-BV12 -> 49199.771 | BX12: =(((BK12*N12)-BS12)/BS12*-1) -> 0.12192418 | BY12: =ROUND(BL12,2) -> 0.74 | CE12: =CC12/BY12 -> 0 | CF12: =100%-CE12 -> 1 | CG12: =AVERAGE(CF12,CD12) -> 1
A13: COLCHA KING 70GSM SOLID 3D | B13: 9404.40.00 | C13: 0.162 | D13: 0 | E13: 0.021 | F13: 0.0965 | G13: 0.0165 | H13: 0.076 | I13: 0.18 | J13: 0.04 | K13: 0.14 | L13: 0.015 | M13: N/A | N13: 6000 | O13: 7.57 | T13: 7.57 | X13: =MIN(O13:W13) -> 7.57 | Y13: =AVERAGE(O13:W13) -> 7.57 | Z13: =Y13*N13 -> 45420 | AA13: ='CALCULO GERAL'!$G$10 -> 6300 | AB13: =Z13+AA13 -> 51720 | AC13: =AB13*'CALCULO GERAL'!$C$11 -> 259582.68 | AD13: =AC13*C13 -> 42052.394 | AE13: =(AC13+AD13)*D13 -> 0 | AF13: =AC13*E13 -> 5451.2363 | AG13: =AC13*F13 -> 25049.729 | AH13: 154.23 | AI13: =((AA13*'CALCULO GERAL'!$C$11))*0.08+20 -> 2549.576 | AJ13: 1010 | AK13: 2500 | AL13: =(AA13*('CALCULO GERAL'!$C$11*1.02))-(AA13*'CALCULO GERAL'!$C$11) -> 632.394 | AM13: 1800 | AN13: 2600 | AO13: 9400 | AP13: 1000 | AQ13: =-AF13 -> -5451.2363 | AR13: =-AG13 -> -25049.729 | AT13: =SUM(AC13:AS13) -> 323281.27 | AU13: =IFERROR((AT13/N13),0) -> 53.880212 | AV13: =IFERROR((BS13*'CALCULO GERAL'!$E$11)/N13,0) -> 1.4775936 | AW13: =AU13/'CALCULO GERAL'!$C$11 -> 10.735249 | AX13: =BP13-BB13-BD13*'CALCULO GERAL'!$C$11 -> 72.771485 | AY13: =AX13*G13 -> 1.2007295 | AZ13: =AX13*H13 -> 5.5306328 | BA13: =BP13-BD13 -> 73.87968 | BB13: =BA13*L13 -> 1.1081952 | BC13: =BP13/(1+D13) -> 73.87968 | BD13: =BC13*D13 -> 0 | BE13: =BU13*0.08 -> 35462.246 | BF13: =BU13*0.12 -> 53193.37 | BG13: =(BF13*0.09)/N13 -> 0.79790054 | BH13: =(BE13*0.15)/N13 -> 0.88655616 | BI13: =IF(BE13>=$BY$1,($BY$1-BE13)*0.1,IF(BE13<=$BY$1,($BY$1*0)))/N13 -> 0 | BJ13: =(AY13+AZ13+BB13+AV13+BD13+BG13+BH13+BI13) -> 11.001608 | BK13: =BJ13+AU13 -> 64.88182 | BL13: 0.74 | BM13: =ROUND((AW13/BL13)+((AW13*BL13)*'CALCULO GERAL'!$E$11)/BL13,2) -> 14.72 | BN13: =BM13 -> 14.72 | BO13: =ROUND(FV(0.02,8,,BN13)*-1,3) -> 17.247 | BP13: =BM13*'CALCULO GERAL'!$C$11 -> 73.87968 | BQ13: =BO13*'CALCULO GERAL'!$C$11 -> 86.562693 | BR13: =BN13*'CALCULO GERAL'!$C$11 -> 73.87968 | BS13: =BP13*N13 -> 443278.08 | BT13: =BS13-AT13 -> 119996.81 | BU13: =BR13*N13 -> 443278.08 | BV13: =BK13*N13 -> 389290.92 | BW13: =BS13-BV13 -> 53987.159 | BX13: =(((BK13*N13)-BS13)/BS13*-1) -> 0.12179073 | BY13: =ROUND(BL13,2) -> 0.74 | CE13: =CC13/BY13 -> 0 | CF13: =100%-CE13 -> 1 | CG13: =AVERAGE(CF13,CD13) -> 1
A14: COLCHA SOLTEIRO 70GSM SOLID BULLET | B14: 9404.40.00 | C14: 0.162 | D14: 0 | E14: 0.021 | F14: 0.0965 | G14: 0.0165 | H14: 0.076 | I14: 0.18 | J14: 0.04 | K14: 0.14 | L14: 0.015 | M14: N/A | N14: 8000 | O14: 3.28 | T14: 3.28 | X14: =MIN(O14:W14) -> 3.28 | Y14: =AVERAGE(O14:W14) -> 3.28 | Z14: =Y14*N14 -> 26240 | AA14: ='CALCULO GERAL'!$G$10 -> 6300 | AB14: =Z14+AA14 -> 32540 | AC14: =AB14*'CALCULO GERAL'!$C$11 -> 163318.26 | AD14: =AC14*C14 -> 26457.558 | AE14: =(AC14+AD14)*D14 -> 0 | AF14: =AC14*E14 -> 3429.6835 | AG14: =AC14*F14 -> 15760.212 | AH14: 154.23 | AI14: =((AA14*'CALCULO GERAL'!$C$11))*0.08+20 -> 2549.576 | AJ14: 1010 | AK14: 2500 | AL14: =(AA14*('CALCULO GERAL'!$C$11*1.02))-(AA14*'CALCULO GERAL'!$C$11) -> 632.394 | AM14: 1800 | AN14: 2600 | AO14: 9400 | AP14: 1000 | AQ14: =-AF14 -> -3429.6835 | AR14: =-AG14 -> -15760.212 | AT14: =SUM(AC14:AS14) -> 211422.02 | AU14: =IFERROR((AT14/N14),0) -> 26.427752 | AV14: =IFERROR((BS14*'CALCULO GERAL'!$E$11)/N14,0) -> 0.7247436 | AW14: =AU14/'CALCULO GERAL'!$C$11 -> 5.2655414 | AX14: =BP14-BB14-BD14*'CALCULO GERAL'!$C$11 -> 35.693622 | AY14: =AX14*G14 -> 0.58894477 | AZ14: =AX14*H14 -> 2.7127153 | BA14: =BP14-BD14 -> 36.23718 | BB14: =BA14*L14 -> 0.5435577 | BC14: =BP14/(1+D14) -> 36.23718 | BD14: =BC14*D14 -> 0 | BE14: =BU14*0.08 -> 23191.795 | BF14: =BU14*0.12 -> 34787.693 | BG14: =(BF14*0.09)/N14 -> 0.39136154 | BH14: =(BE14*0.15)/N14 -> 0.43484616 | BI14: =IF(BE14>=$BY$1,($BY$1-BE14)*0.1,IF(BE14<=$BY$1,($BY$1*0)))/N14 -> 0 | BJ14: =(AY14+AZ14+BB14+AV14+BD14+BG14+BH14+BI14) -> 5.3961691 | BK14: =BJ14+AU14 -> 31.823921 | BL14: 0.74 | BM14: =ROUND((AW14/BL14)+((AW14*BL14)*'CALCULO GERAL'!$E$11)/BL14,2) -> 7.22 | BN14: =BM14 -> 7.22 | BO14: =ROUND(FV(0.02,8,,BN14)*-1,3) -> 8.459 | BP14: =BM14*'CALCULO GERAL'!$C$11 -> 36.23718 | BQ14: =BO14*'CALCULO GERAL'!$C$11 -> 42.455721 | BR14: =BN14*'CALCULO GERAL'!$C$11 -> 36.23718 | BS14: =BP14*N14 -> 289897.44 | BT14: =BS14-AT14 -> 78475.422 | BU14: =BR14*N14 -> 289897.44 | BV14: =BK14*N14 -> 254591.37 | BW14: =BS14-BV14 -> 35306.069 | BX14: =(((BK14*N14)-BS14)/BS14*-1) -> 0.12178814 | BY14: =ROUND(BL14,2) -> 0.74 | CE14: =CC14/BY14 -> 0 | CF14: =100%-CE14 -> 1 | CG14: =AVERAGE(CF14,CD14) -> 1
... A25: COLCHA KING 85GSM SOLID | B25: 9404.40.00 | C25: 0.162 | D25: 0 | E25: 0.021 | F25: 0.0965 | G25: 0.0165 | H25: 0.076 | I25: 0.18 | J25: 0.04 | K25: 0.14 | L25: 0.015 | M25: N/A | N25: 6000 | O25: 6.15 | T25: 6.15 | X25: =MIN(O25:W25) -> 6.15 | Y25: =AVERAGE(O25:W25) -> 6.15 | Z25: =Y25*N25 -> 36900 | AA25: ='CALCULO GERAL'!$G$10 -> 6300 | AB25: =Z25+AA25 -> 43200 | AC25: =AB25*'CALCULO GERAL'!$C$11 -> 216820.8 | AD25: =AC25*C25 -> 35124.97 | AE25: =(AC25+AD25)*D25 -> 0 | AF25: =AC25*E25 -> 4553.2368 | AG25: =AC25*F25 -> 20923.207 | AH25: 154.23 | AI25: =((AA25*'CALCULO GERAL'!$C$11))*0.08+20 -> 2549.576 | AJ25: 1010 | AK25: 2500 | AL25: =(AA25*('CALCULO GERAL'!$C$11*1.02))-(AA25*'CALCULO GERAL'!$C$11) -> 632.394 | AM25: 1800 | AN25: 2600 | AO25: 9400 | AP25: 1000 | AQ25: =-AF25 -> -4553.2368 | AR25: =-AG25 -> -20923.207 | AT25: =SUM(AC25:AS25) -> 273591.97 | AU25: =IFERROR((AT25/N25),0) -> 45.598662 | AV25: =IFERROR((BS25*'CALCULO GERAL'!$E$11)/N25,0) -> 1.2507348 | AW25: =AU25/'CALCULO GERAL'!$C$11 -> 9.0852085 | AX25: =BP25-BB25-BD25*'CALCULO GERAL'!$C$11 -> 61.598689 | AY25: =AX25*G25 -> 1.0163784 | AZ25: =AX25*H25 -> 4.6815004 | BA25: =BP25-BD25 -> 62.53674 | BB25: =BA25*L25 -> 0.9380511 | BC25: =BP25/(1+D25) -> 62.53674 | BD25: =BC25*D25 -> 0 | BE25: =BU25*0.08 -> 30017.635 | BF25: =BU25*0.12 -> 45026.453 | BG25: =(BF25*0.09)/N25 -> 0.67539679 | BH25: =(BE25*0.15)/N25 -> 0.75044088 | BI25: =IF(BE25>=$BY$1,($BY$1-BE25)*0.1,IF(BE25<=$BY$1,($BY$1*0)))/N25 -> 0 | BJ25: =(AY25+AZ25+BB25+AV25+BD25+BG25+BH25+BI25) -> 9.3125023 | BK25: =BJ25+AU25 -> 54.911164 | BL25: 0.74 | BM25: =ROUND((AW25/BL25)+((AW25*BL25)*'CALCULO GERAL'!$E$11)/BL25,2) -> 12.46 | BN25: =BM25 -> 12.46 | BO25: =ROUND(FV(0.02,8,,BN25)*-1,3) -> 14.599 | BP25: =BM25*'CALCULO GERAL'!$C$11 -> 62.53674 | BQ25: =BO25*'CALCULO GERAL'!$C$11 -> 73.272381 | BR25: =BN25*'CALCULO GERAL'!$C$11 -> 62.53674 | BS25: =BP25*N25 -> 375220.44 | BT25: =BS25-AT25 -> 101628.47 | BU25: =BR25*N25 -> 375220.44 | BV25: =BK25*N25 -> 329466.98 | BW25: =BS25-BV25 -> 45753.457 | BX25: =(((BK25*N25)-BS25)/BS25*-1) -> 0.12193754 | BY25: =ROUND(BL25,2) -> 0.74 | CE25: =CC25/BY25 -> 0 | CF25: =100%-CE25 -> 1 | CG25: =AVERAGE(CF25,CD25) -> 1
A26: COLCHA SOLTEIRO 80gsm SOLID COSTURADO - 180x240cm | B26: 9404.40.00 | C26: 0.162 | D26: 0 | E26: 0.021 | F26: 0.0965 | G26: 0.0165 | H26: 0.076 | I26: 0.18 | J26: 0.04 | K26: 0.14 | L26: 0.015 | M26: N/A | N26: 6700 | O26: 5.6 | X26: =MIN(O26:W26) -> 5.6 | Y26: =AVERAGE(O26:W26) -> 5.6 | Z26: =Y26*N26 -> 37520 | AA26: ='CALCULO GERAL'!$G$10 -> 6300 | AB26: =Z26+AA26 -> 43820 | AC26: =AB26*'CALCULO GERAL'!$C$11 -> 219932.58 | AD26: =AC26*C26 -> 35629.078 | AE26: =(AC26+AD26)*D26 -> 0 | AF26: =AC26*E26 -> 4618.5842 | AG26: =AC26*F26 -> 21223.494 | AH26: 154.23 | AI26: =((AA26*'CALCULO GERAL'!$C$11))*0.08+20 -> 2549.576 | AJ26: 1010 | AK26: 2500 | AL26: =(AA26*('CALCULO GERAL'!$C$11*1.02))-(AA26*'CALCULO GERAL'!$C$11) -> 632.394 | AM26: 1800 | AN26: 2600 | AO26: 9400 | AP26: 1000 | AQ26: =-AF26 -> -4618.5842 | AR26: =-AG26 -> -21223.494 | AT26: =SUM(AC26:AS26) -> 277207.86 | AU26: =IFERROR((AT26/N26),0) -> 41.374307 | AV26: =IFERROR((BS26*'CALCULO GERAL'!$E$11)/N26,0) -> 1.134294 | AW26: =AU26/'CALCULO GERAL'!$C$11 -> 8.243536 | AX26: =BP26-BB26-BD26*'CALCULO GERAL'!$C$11 -> 55.86398 | AY26: =AX26*G26 -> 0.92175566 | AZ26: =AX26*H26 -> 4.2456624 | BA26: =BP26-BD26 -> 56.7147 | BB26: =BA26*L26 -> 0.8507205 | BC26: =BP26/(1+D26) -> 56.7147 | BD26: =BC26*D26 -> 0 | BE26: =BU26*0.08 -> 30399.079 | BF26: =BU26*0.12 -> 45598.619 | BG26: =(BF26*0.09)/N26 -> 0.61251876 | BH26: =(BE26*0.15)/N26 -> 0.6805764 | BI26: =IF(BE26>=$BY$1,($BY$1-BE26)*0.1,IF(BE26<=$BY$1,($BY$1*0)))/N26 -> 0 | BJ26: =(AY26+AZ26+BB26+AV26+BD26+BG26+BH26+BI26) -> 8.4455278 | BK26: =BJ26+AU26 -> 49.819835 | BL26: 0.74 | BM26: =ROUND((AW26/BL26)+((AW26*BL26)*'CALCULO GERAL'!$E$11)/BL26,2) -> 11.3 | BN26: =BM26 -> 11.3 | BO26: =ROUND(FV(0.02,8,,BN26)*-1,3) -> 13.24 | BP26: =BM26*'CALCULO GERAL'!$C$11 -> 56.7147 | BQ26: =BO26*'CALCULO GERAL'!$C$11 -> 66.45156 | BR26: =BN26*'CALCULO GERAL'!$C$11 -> 56.7147 | BS26: =BP26*N26 -> 379988.49 | BT26: =BS26-AT26 -> 102780.63 | BU26: =BR26*N26 -> 379988.49 | BV26: =BK26*N26 -> 333792.89 | BW26: =BS26-BV26 -> 46195.596 | BX26: =(((BK26*N26)-BS26)/BS26*-1) -> 0.12157104 | BY26: =ROUND(BL26,2) -> 0.74 | CE26: =CC26/BY26 -> 0 | CF26: =100%-CE26 -> 1 | CG26: =AVERAGE(CF26,CD26) -> 1
A27: COLCHA CASAL 80gsm SOLID COSTURADO - 220x240cm | B27: 9404.40.00 | C27: 0.162 | D27: 0 | E27: 0.021 | F27: 0.0965 | G27: 0.0165 | H27: 0.076 | I27: 0.18 | J27: 0.04 | K27: 0.14 | L27: 0.015 | M27: N/A | N27: 6700 | O27: 7.5 | X27: =MIN(O27:W27) -> 7.5 | Y27: =AVERAGE(O27:W27) -> 7.5 | Z27: =Y27*N27 -> 50250 | AA27: ='CALCULO GERAL'!$G$10 -> 6300 | AB27: =Z27+AA27 -> 56550 | AC27: =AB27*'CALCULO GERAL'!$C$11 -> 283824.45 | AD27: =AC27*C27 -> 45979.561 | AE27: =(AC27+AD27)*D27 -> 0 | AF27: =AC27*E27 -> 5960.3135 | AG27: =AC27*F27 -> 27389.059 | AH27: 154.23 | AI27: =((AA27*'CALCULO GERAL'!$C$11))*0.08+20 -> 2549.576 | AJ27: 1010 | AK27: 2500 | AL27: =(AA27*('CALCULO GERAL'!$C$11*1.02))-(AA27*'CALCULO GERAL'!$C$11) -> 632.394 | AM27: 1800 | AN27: 2600 | AO27: 9400 | AP27: 1000 | AQ27: =-AF27 -> -5960.3135 | AR27: =-AG27 -> -27389.059 | AT27: =SUM(AC27:AS27) -> 351450.21 | AU27: =IFERROR((AT27/N27),0) -> 52.455255 | AV27: =IFERROR((BS27*'CALCULO GERAL'!$E$11)/N27,0) -> 1.4384454 | AW27: =AU27/'CALCULO GERAL'!$C$11 -> 10.451336 | AX27: =BP27-BB27-BD27*'CALCULO GERAL'!$C$11 -> 70.843436 | AY27: =AX27*G27 -> 1.1689167 | AZ27: =AX27*H27 -> 5.3841011 | BA27: =BP27-BD27 -> 71.92227 | BB27: =BA27*L27 -> 1.078834 | BC27: =BP27/(1+D27) -> 71.92227 | BD27: =BC27*D27 -> 0 | BE27: =BU27*0.08 -> 38550.337 | BF27: =BU27*0.12 -> 57825.505 | BG27: =(BF27*0.09)/N27 -> 0.77676052 | BH27: =(BE27*0.15)/N27 -> 0.86306724 | BI27: =IF(BE27>=$BY$1,($BY$1-BE27)*0.1,IF(BE27<=$BY$1,($BY$1*0)))/N27 -> 0 | BJ27: =(AY27+AZ27+BB27+AV27+BD27+BG27+BH27+BI27) -> 10.710125 | BK27: =BJ27+AU27 -> 63.16538 | BL27: 0.74 | BM27: =ROUND((AW27/BL27)+((AW27*BL27)*'CALCULO GERAL'!$E$11)/BL27,2) -> 14.33 | BN27: =BM27 -> 14.33 | BO27: =ROUND(FV(0.02,8,,BN27)*-1,3) -> 16.79 | BP27: =BM27*'CALCULO GERAL'!$C$11 -> 71.92227 | BQ27: =BO27*'CALCULO GERAL'!$C$11 -> 84.26901 | BR27: =BN27*'CALCULO GERAL'!$C$11 -> 71.92227 | BS27: =BP27*N27 -> 481879.21 | BT27: =BS27-AT27 -> 130429 | BU27: =BR27*N27 -> 481879.21 | BV27: =BK27*N27 -> 423208.05 | BW27: =BS27-BV27 -> 58671.16 | BX27: =(((BK27*N27)-BS27)/BS27*-1) -> 0.12175491 | BY27: =ROUND(BL27,2) -> 0.74 | CE27: =CC27/BY27 -> 0 | CF27: =100%-CE27 -> 1 | CG27: =AVERAGE(CF27,CD27) -> 1
A28: COLCHA QUEEN 80gsm SOLID COSTURADO - 240x260cm | B28: 9404.40.00 | C28: 0.162 | D28: 0 | E28: 0.021 | F28: 0.0965 | G28: 0.0165 | H28: 0.076 | I28: 0.18 | J28: 0.04 | K28: 0.14 | L28: 0.015 | M28: N/A | N28: 6700 | O28: 8.4 | X28: =MIN(O28:W28) -> 8.4 | Y28: =AVERAGE(O28:W28) -> 8.4 | Z28: =Y28*N28 -> 56280 | AA28: ='CALCULO GERAL'!$G$10 -> 6300 | AB28: =Z28+AA28 -> 62580 | AC28: =AB28*'CALCULO GERAL'!$C$11 -> 314089.02 | AD28: =AC28*C28 -> 50882.421 | AE28: =(AC28+AD28)*D28 -> 0 | AF28: =AC28*E28 -> 6595.8694 | AG28: =AC28*F28 -> 30309.59 | AH28: 154.23 | AI28: =((AA28*'CALCULO GERAL'!$C$11))*0.08+20 -> 2549.576 | AJ28: 1010 | AK28: 2500 | AL28: =(AA28*('CALCULO GERAL'!$C$11*1.02))-(AA28*'CALCULO GERAL'!$C$11) -> 632.394 | AM28: 1800 | AN28: 2600 | AO28: 9400 | AP28: 1000 | AQ28: =-AF28 -> -6595.8694 | AR28: =-AG28 -> -30309.59 | AT28: =SUM(AC28:AS28) -> 386617.64 | AU28: =IFERROR((AT28/N28),0) -> 57.704126 | AV28: =IFERROR((BS28*'CALCULO GERAL'!$E$11)/N28,0) -> 1.5829926 | AW28: =AU28/'CALCULO GERAL'!$C$11 -> 11.497136 | AX28: =BP28-BB28-BD28*'CALCULO GERAL'!$C$11 -> 77.962386 | AY28: =AX28*G28 -> 1.2863794 | AZ28: =AX28*H28 -> 5.9251413 | BA28: =BP28-BD28 -> 79.14963 | BB28: =BA28*L28 -> 1.1872444 | BC28: =BP28/(1+D28) -> 79.14963 | BD28: =BC28*D28 -> 0 | BE28: =BU28*0.08 -> 42424.202 | BF28: =BU28*0.12 -> 63636.303 | BG28: =(BF28*0.09)/N28 -> 0.854816 | BH28: =(BE28*0.15)/N28 -> 0.94979556 | BI28: =IF(BE28>=$BY$1,($BY$1-BE28)*0.1,IF(BE28<=$BY$1,($BY$1*0)))/N28 -> 0 | BJ28: =(AY28+AZ28+BB28+AV28+BD28+BG28+BH28+BI28) -> 11.786369 | BK28: =BJ28+AU28 -> 69.490495 | BL28: 0.74 | BM28: =ROUND((AW28/BL28)+((AW28*BL28)*'CALCULO GERAL'!$E$11)/BL28,2) -> 15.77 | BN28: =BM28 -> 15.77 | BO28: =ROUND(FV(0.02,8,,BN28)*-1,3) -> 18.477 | BP28: =BM28*'CALCULO GERAL'!$C$11 -> 79.14963 | BQ28: =BO28*'CALCULO GERAL'!$C$11 -> 92.736063 | BR28: =BN28*'CALCULO GERAL'!$C$11 -> 79.14963 | BS28: =BP28*N28 -> 530302.52 | BT28: =BS28-AT28 -> 143684.88 | BU28: =BR28*N28 -> 530302.52 | BV28: =BK28*N28 -> 465586.32 | BW28: =BS28-BV28 -> 64716.206 | BX28: =(((BK28*N28)-BS28)/BS28*-1) -> 0.12203639 | BY28: =ROUND(BL28,2) -> 0.74 | CE28: =CC28/BY28 -> 0 | CF28: =100%-CE28 -> 1 | CG28: =AVERAGE(CF28,CD28) -> 1
A29: COLCHA KING 80gsm SOLID COSTURADO - 280x260cm | B29: 9404.40.00 | C29: 0.162 | D29: 0 | E29: 0.021 | F29: 0.0965 | G29: 0.0165 | H29: 0.076 | I29: 0.18 | J29: 0.04 | K29: 0.14 | L29: 0.015 | M29: N/A | N29: 6700 | O29: 9.54 | X29: =MIN(O29:W29) -> 9.54 | Y29: =AVERAGE(O29:W29) -> 9.54 | Z29: =Y29*N29 -> 63918 | AA29: ='CALCULO GERAL'!$G$10 -> 6300 | AB29: =Z29+AA29 -> 70218 | AC29: =AB29*'CALCULO GERAL'!$C$11 -> 352424.14 | AD29: =AC29*C29 -> 57092.711 | AE29: =(AC29+AD29)*D29 -> 0 | AF29: =AC29*E29 -> 7400.907 | AG29: =AC29*F29 -> 34008.93 | AH29: 154.23 | AI29: =((AA29*'CALCULO GERAL'!$C$11))*0.08+20 -> 2549.576 | AJ29: 1010 | AK29: 2500 | AL29: =(AA29*('CALCULO GERAL'!$C$11*1.02))-(AA29*'CALCULO GERAL'!$C$11) -> 632.394 | AM29: 1800 | AN29: 2600 | AO29: 9400 | AP29: 1000 | AQ29: =-AF29 -> -7400.907 | AR29: =-AG29 -> -34008.93 | AT29: =SUM(AC29:AS29) -> 431163.05 | AU29: =IFERROR((AT29/N29),0) -> 64.352694 | AV29: =IFERROR((BS29*'CALCULO GERAL'!$E$11)/N29,0) -> 1.7646804 | AW29: =AU29/'CALCULO GERAL'!$C$11 -> 12.821816 | AX29: =BP29-BB29-BD29*'CALCULO GERAL'!$C$11 -> 86.91051 | AY29: =AX29*G29 -> 1.4340234 | AZ29: =AX29*H29 -> 6.6051987 | BA29: =BP29-BD29 -> 88.23402 | BB29: =BA29*L29 -> 1.3235103 | BC29: =BP29/(1+D29) -> 88.23402 | BD29: =BC29*D29 -> 0 | BE29: =BU29*0.08 -> 47293.435 | BF29: =BU29*0.12 -> 70940.152 | BG29: =(BF29*0.09)/N29 -> 0.95292742 | BH29: =(BE29*0.15)/N29 -> 1.0588082 | BI29: =IF(BE29>=$BY$1,($BY$1-BE29)*0.1,IF(BE29<=$BY$1,($BY$1*0)))/N29 -> 0 | BJ29: =(AY29+AZ29+BB29+AV29+BD29+BG29+BH29+BI29) -> 13.139149 | BK29: =BJ29+AU29 -> 77.491843 | BL29: 0.74 | BM29: =ROUND((AW29/BL29)+((AW29*BL29)*'CALCULO GERAL'!$E$11)/BL29,2) -> 17.58 | BN29: =BM29 -> 17.58 | BO29: =ROUND(FV(0.02,8,,BN29)*-1,3) -> 20.598 | BP29: =BM29*'CALCULO GERAL'!$C$11 -> 88.23402 | BQ29: =BO29*'CALCULO GERAL'!$C$11 -> 103.38136 | BR29: =BN29*'CALCULO GERAL'!$C$11 -> 88.23402 | BS29: =BP29*N29 -> 591167.93 | BT29: =BS29-AT29 -> 160004.88 | BU29: =BR29*N29 -> 591167.93 | BV29: =BK29*N29 -> 519195.35 | BW29: =BS29-BV29 -> 71972.586 | BX29: =(((BK29*N29)-BS29)/BS29*-1) -> 0.12174643 | BY29: =ROUND(BL29,2) -> 0.74 | CE29: =CC29/BY29 -> 0 | CF29: =100%-CE29 -> 1 | CG29: =AVERAGE(CF29,CD29) -> 1
A30: COLCHA SUPER KING 80gsm SOLID COSTURADO - 310x280cm | B30: 9404.40.00 | C30: 0.162 | D30: 0 | E30: 0.021 | F30: 0.0965 | G30: 0.0165 | H30: 0.076 | I30: 0.18 | J30: 0.04 | K30: 0.14 | L30: 0.015 | M30: N/A | N30: 6700 | O30: 10.95 | X30: =MIN(O30:W30) -> 10.95 | Y30: =AVERAGE(O30:W30) -> 10.95 | Z30: =Y30*N30 -> 73365 | AA30: ='CALCULO GERAL'!$G$10 -> 6300 | AB30: =Z30+AA30 -> 79665 | AC30: =AB30*'CALCULO GERAL'!$C$11 -> 399838.64 | AD30: =AC30*C30 -> 64773.859 | AE30: =(AC30+AD30)*D30 -> 0 | AF30: =AC30*E30 -> 8396.6113 | AG30: =AC30*F30 -> 38584.428 | AH30: 154.23 | AI30: =((AA30*'CALCULO GERAL'!$C$11))*0.08+20 -> 2549.576 | AJ30: 1010 | AK30: 2500 | AL30: =(AA30*('CALCULO GERAL'!$C$11*1.02))-(AA30*'CALCULO GERAL'!$C$11) -> 632.394 | AM30: 1800 | AN30: 2600 | AO30: 9400 | AP30: 1000 | AQ30: =-AF30 -> -8396.6113 | AR30: =-AG30 -> -38584.428 | AT30: =SUM(AC30:AS30) -> 486258.69 | AU30: =IFERROR((AT30/N30),0) -> 72.575924 | AV30: =IFERROR((BS30*'CALCULO GERAL'!$E$11)/N30,0) -> 1.9905354 | AW30: =AU30/'CALCULO GERAL'!$C$11 -> 14.460236 | AX30: =BP30-BB30-BD30*'CALCULO GERAL'!$C$11 -> 98.033868 | AY30: =AX30*G30 -> 1.6175588 | AZ30: =AX30*H30 -> 7.450574 | BA30: =BP30-BD30 -> 99.52677 | BB30: =BA30*L30 -> 1.4929016 | BC30: =BP30/(1+D30) -> 99.52677 | BD30: =BC30*D30 -> 0 | BE30: =BU30*0.08 -> 53346.349 | BF30: =BU30*0.12 -> 80019.523 | BG30: =(BF30*0.09)/N30 -> 1.0748891 | BH30: =(BE30*0.15)/N30 -> 1.1943212 | BI30: =IF(BE30>=$BY$1,($BY$1-BE30)*0.1,IF(BE30<=$BY$1,($BY$1*0)))/N30 -> 0 | BJ30: =(AY30+AZ30+BB30+AV30+BD30+BG30+BH30+BI30) -> 14.82078 | BK30: =BJ30+AU30 -> 87.396705 | BL30: 0.74 | BM30: =ROUND((AW30/BL30)+((AW30*BL30)*'CALCULO GERAL'!$E$11)/BL30,2) -> 19.83 | BN30: =BM30 -> 19.83 | BO30: =ROUND(FV(0.02,8,,BN30)*-1,3) -> 23.234 | BP30: =BM30*'CALCULO GERAL'!$C$11 -> 99.52677 | BQ30: =BO30*'CALCULO GERAL'!$C$11 -> 116.61145 | BR30: =BN30*'CALCULO GERAL'!$C$11 -> 99.52677 | BS30: =BP30*N30 -> 666829.36 | BT30: =BS30-AT30 -> 180570.67 | BU30: =BR30*N30 -> 666829.36 | BV30: =BK30*N30 -> 585557.92 | BW30: =BS30-BV30 -> 81271.438 | BX30: =(((BK30*N30)-BS30)/BS30*-1) -> 0.12187741 | BY30: =ROUND(BL30,2) -> 0.74 | CE30: =CC30/BY30 -> 0 | CF30: =100%-CE30 -> 1 | CG30: =AVERAGE(CF30,CD30) -> 1
A31: COLCHA SOLTEIRO 90GSM SOLID COSTURADO - 180x240cm | B31: 9404.40.00 | C31: 0.162 | D31: 0 | E31: 0.021 | F31: 0.0965 | G31: 0.0165 | H31: 0.076 | I31: 0.18 | J31: 0.04 | K31: 0.14 | L31: 0.015 | M31: N/A | N31: 6700 | O31: 5.6 | X31: =MIN(O31:W31) -> 5.6 | Y31: =AVERAGE(O31:W31) -> 5.6 | Z31: =Y31*N31 -> 37520 | AA31: ='CALCULO GERAL'!$G$10 -> 6300 | AB31: =Z31+AA31 -> 43820 | AC31: =AB31*'CALCULO GERAL'!$C$11 -> 219932.58 | AD31: =AC31*C31 -> 35629.078 | AE31: =(AC31+AD31)*D31 -> 0 | AF31: =AC31*E31 -> 4618.5842 | AG31: =AC31*F31 -> 21223.494 | AH31: 154.23 | AI31: =((AA31*'CALCULO GERAL'!$C$11))*0.08+20 -> 2549.576 | AJ31: 1010 | AK31: 2500 | AL31: =(AA31*('CALCULO GERAL'!$C$11*1.02))-(AA31*'CALCULO GERAL'!$C$11) -> 632.394 | AM31: 1800 | AN31: 2600 | AO31: 9400 | AP31: 1000 | AQ31: =-AF31 -> -4618.5842 | AR31: =-AG31 -> -21223.494 | AT31: =SUM(AC31:AS31) -> 277207.86 | AU31: =IFERROR((AT31/N31),0) -> 41.374307 | AV31: =IFERROR((BS31*'CALCULO GERAL'!$E$11)/N31,0) -> 1.134294 | AW31: =AU31/'CALCULO GERAL'!$C$11 -> 8.243536 | AX31: =BP31-BB31-BD31*'CALCULO GERAL'!$C$11 -> 55.86398 | AY31: =AX31*G31 -> 0.92175566 | AZ31: =AX31*H31 -> 4.2456624 | BA31: =BP31-BD31 -> 56.7147 | BB31: =BA31*L31 -> 0.8507205 | BC31: =BP31/(1+D31) -> 56.7147 | BD31: =BC31*D31 -> 0 | BE31: =BU31*0.08 -> 30399.079 | BF31: =BU31*0.12 -> 45598.619 | BG31: =(BF31*0.09)/N31 -> 0.61251876 | BH31: =(BE31*0.15)/N31 -> 0.6805764 | BI31: =IF(BE31>=$BY$1,($BY$1-BE31)*0.1,IF(BE31<=$BY$1,($BY$1*0)))/N31 -> 0 | BJ31: =(AY31+AZ31+BB31+AV31+BD31+BG31+BH31+BI31) -> 8.4455278 | BK31: =BJ31+AU31 -> 49.819835 | BL31: 0.74 | BM31: =ROUND((AW31/BL31)+((AW31*BL31)*'CALCULO GERAL'!$E$11)/BL31,2) -> 11.3 | BN31: =BM31 -> 11.3 | BO31: =ROUND(FV(0.02,8,,BN31)*-1,3) -> 13.24 | BP31: =BM31*'CALCULO GERAL'!$C$11 -> 56.7147 | BQ31: =BO31*'CALCULO GERAL'!$C$11 -> 66.45156 | BR31: =BN31*'CALCULO GERAL'!$C$11 -> 56.7147 | BS31: =BP31*N31 -> 379988.49 | BT31: =BS31-AT31 -> 102780.63 | BU31: =BR31*N31 -> 379988.49 | BV31: =BK31*N31 -> 333792.89 | BW31: =BS31-BV31 -> 46195.596 | BX31: =(((BK31*N31)-BS31)/BS31*-1) -> 0.12157104 | BY31: =ROUND(BL31,2) -> 0.74 | CE31: =CC31/BY31 -> 0 | CF31: =100%-CE31 -> 1 | CG31: =AVERAGE(CF31,CD31) -> 1
A32: COLCHA CASAL 90gsm SEERSUCKER COSTURADO - 220x240cm A | B32: 9404.40.00 | C32: 0.162 | D32: 0 | E32: 0.021 | F32: 0.0965 | G32: 0.0165 | H32: 0.076 | I32: 0.18 | J32: 0.04 | K32: 0.14 | L32: 0.015 | M32: N/A | N32: 6700 | O32: 7.5 | X32: =MIN(O32:W32) -> 7.5 | Y32: =AVERAGE(O32:W32) -> 7.5 | Z32: =Y32*N32 -> 50250 | AA32: ='CALCULO GERAL'!$G$10 -> 6300 | AB32: =Z32+AA32 -> 56550 | AC32: =AB32*'CALCULO GERAL'!$C$11 -> 283824.45 | AD32: =AC32*C32 -> 45979.561 | AE32: =(AC32+AD32)*D32 -> 0 | AF32: =AC32*E32 -> 5960.3135 | AG32: =AC32*F32 -> 27389.059 | AH32: 154.23 | AI32: =((AA32*'CALCULO GERAL'!$C$11))*0.08+20 -> 2549.576 | AJ32: 1010 | AK32: 2500 | AL32: =(AA32*('CALCULO GERAL'!$C$11*1.02))-(AA32*'CALCULO GERAL'!$C$11) -> 632.394 | AM32: 1800 | AN32: 2600 | AO32: 9400 | AP32: 1000 | AQ32: =-AF32 -> -5960.3135 | AR32: =-AG32 -> -27389.059 | AT32: =SUM(AC32:AS32) -> 351450.21 | AU32: =IFERROR((AT32/N32),0) -> 52.455255 | AV32: =IFERROR((BS32*'CALCULO GERAL'!$E$11)/N32,0) -> 1.4384454 | AW32: =AU32/'CALCULO GERAL'!$C$11 -> 10.451336 | AX32: =BP32-BB32-BD32*'CALCULO GERAL'!$C$11 -> 70.843436 | AY32: =AX32*G32 -> 1.1689167 | AZ32: =AX32*H32 -> 5.3841011 | BA32: =BP32-BD32 -> 71.92227 | BB32: =BA32*L32 -> 1.078834 | BC32: =BP32/(1+D32) -> 71.92227 | BD32: =BC32*D32 -> 0 | BE32: =BU32*0.08 -> 38550.337 | BF32: =BU32*0.12 -> 57825.505 | BG32: =(BF32*0.09)/N32 -> 0.77676052 | BH32: =(BE32*0.15)/N32 -> 0.86306724 | BI32: =IF(BE32>=$BY$1,($BY$1-BE32)*0.1,IF(BE32<=$BY$1,($BY$1*0)))/N32 -> 0 | BJ32: =(AY32+AZ32+BB32+AV32+BD32+BG32+BH32+BI32) -> 10.710125 | BK32: =BJ32+AU32 -> 63.16538 | BL32: 0.74 | BM32: =ROUND((AW32/BL32)+((AW32*BL32)*'CALCULO GERAL'!$E$11)/BL32,2) -> 14.33 | BN32: =BM32 -> 14.33 | BO32: =ROUND(FV(0.02,8,,BN32)*-1,3) -> 16.79 | BP32: =BM32*'CALCULO GERAL'!$C$11 -> 71.92227 | BQ32: =BO32*'CALCULO GERAL'!$C$11 -> 84.26901 | BR32: =BN32*'CALCULO GERAL'!$C$11 -> 71.92227 | BS32: =BP32*N32 -> 481879.21 | BT32: =BS32-AT32 -> 130429 | BU32: =BR32*N32 -> 481879.21 | BV32: =BK32*N32 -> 423208.05 | BW32: =BS32-BV32 -> 58671.16 | BX32: =(((BK32*N32)-BS32)/BS32*-1) -> 0.12175491 | BY32: =ROUND(BL32,2) -> 0.74 | CE32: =CC32/BY32 -> 0 | CF32: =100%-CE32 -> 1 | CG32: =AVERAGE(CF32,CD32) -> 1
A33: COLCHA QUEEN 90GSM SEERSUCKER COSTURADO - 240x260cm A | B33: 9404.40.00 | C33: 0.162 | D33: 0 | E33: 0.021 | F33: 0.0965 | G33: 0.0165 | H33: 0.076 | I33: 0.18 | J33: 0.04 | K33: 0.14 | L33: 0.015 | M33: N/A | N33: 6700 | O33: 8.4 | X33: =MIN(O33:W33) -> 8.4 | Y33: =AVERAGE(O33:W33) -> 8.4 | Z33: =Y33*N33 -> 56280 | AA33: ='CALCULO GERAL'!$G$10 -> 6300 | AB33: =Z33+AA33 -> 62580 | AC33: =AB33*'CALCULO GERAL'!$C$11 -> 314089.02 | AD33: =AC33*C33 -> 50882.421 | AE33: =(AC33+AD33)*D33 -> 0 | AF33: =AC33*E33 -> 6595.8694 | AG33: =AC33*F33 -> 30309.59 | AH33: 154.23 | AI33: =((AA33*'CALCULO GERAL'!$C$11))*0.08+20 -> 2549.576 | AJ33: 1010 | AK33: 2500 | AL33: =(AA33*('CALCULO GERAL'!$C$11*1.02))-(AA33*'CALCULO GERAL'!$C$11) -> 632.394 | AM33: 1800 | AN33: 2600 | AO33: 9400 | AP33: 1000 | AQ33: =-AF33 -> -6595.8694 | AR33: =-AG33 -> -30309.59 | AT33: =SUM(AC33:AS33) -> 386617.64 | AU33: =IFERROR((AT33/N33),0) -> 57.704126 | AV33: =IFERROR((BS33*'CALCULO GERAL'!$E$11)/N33,0) -> 1.5829926 | AW33: =AU33/'CALCULO GERAL'!$C$11 -> 11.497136 | AX33: =BP33-BB33-BD33*'CALCULO GERAL'!$C$11 -> 77.962386 | AY33: =AX33*G33 -> 1.2863794 | AZ33: =AX33*H33 -> 5.9251413 | BA33: =BP33-BD33 -> 79.14963 | BB33: =BA33*L33 -> 1.1872444 | BC33: =BP33/(1+D33) -> 79.14963 | BD33: =BC33*D33 -> 0 | BE33: =BU33*0.08 -> 42424.202 | BF33: =BU33*0.12 -> 63636.303 | BG33: =(BF33*0.09)/N33 -> 0.854816 | BH33: =(BE33*0.15)/N33 -> 0.94979556 | BI33: =IF(BE33>=$BY$1,($BY$1-BE33)*0.1,IF(BE33<=$BY$1,($BY$1*0)))/N33 -> 0 | BJ33: =(AY33+AZ33+BB33+AV33+BD33+BG33+BH33+BI33) -> 11.786369 | BK33: =BJ33+AU33 -> 69.490495 | BL33: 0.74 | BM33: =ROUND((AW33/BL33)+((AW33*BL33)*'CALCULO GERAL'!$E$11)/BL33,2) -> 15.77 | BN33: =BM33 -> 15.77 | BO33: =ROUND(FV(0.02,8,,BN33)*-1,3) -> 18.477 | BP33: =BM33*'CALCULO GERAL'!$C$11 -> 79.14963 | BQ33: =BO33*'CALCULO GERAL'!$C$11 -> 92.736063 | BR33: =BN33*'CALCULO GERAL'!$C$11 -> 79.14963 | BS33: =BP33*N33 -> 530302.52 | BT33: =BS33-AT33 -> 143684.88 | BU33: =BR33*N33 -> 530302.52 | BV33: =BK33*N33 -> 465586.32 | BW33: =BS33-BV33 -> 64716.206 | BX33: =(((BK33*N33)-BS33)/BS33*-1) -> 0.12203639 | BY33: =ROUND(BL33,2) -> 0.74 | CE33: =CC33/BY33 -> 0 | CF33: =100%-CE33 -> 1 | CG33: =AVERAGE(CF33,CD33) -> 1
A34: COLCHA KING 90gsm SEERSUCKER COSTURADO - 280x260cm A | B34: 9404.40.00 | C34: 0.162 | D34: 0 | E34: 0.021 | F34: 0.0965 | G34: 0.0165 | H34: 0.076 | I34: 0.18 | J34: 0.04 | K34: 0.14 | L34: 0.015 | M34: N/A | N34: 6700 | O34: 9.54 | X34: =MIN(O34:W34) -> 9.54 | Y34: =AVERAGE(O34:W34) -> 9.54 | Z34: =Y34*N34 -> 63918 | AA34: ='CALCULO GERAL'!$G$10 -> 6300 | AB34: =Z34+AA34 -> 70218 | AC34: =AB34*'CALCULO GERAL'!$C$11 -> 352424.14 | AD34: =AC34*C34 -> 57092.711 | AE34: =(AC34+AD34)*D34 -> 0 | AF34: =AC34*E34 -> 7400.907 | AG34: =AC34*F34 -> 34008.93 | AH34: 154.23 | AI34: =((AA34*'CALCULO GERAL'!$C$11))*0.08+20 -> 2549.576 | AJ34: 1010 | AK34: 2500 | AL34: =(AA34*('CALCULO GERAL'!$C$11*1.02))-(AA34*'CALCULO GERAL'!$C$11) -> 632.394 | AM34: 1800 | AN34: 2600 | AO34: 9400 | AP34: 1000 | AQ34: =-AF34 -> -7400.907 | AR34: =-AG34 -> -34008.93 | AT34: =SUM(AC34:AS34) -> 431163.05 | AU34: =IFERROR((AT34/N34),0) -> 64.352694 | AV34: =IFERROR((BS34*'CALCULO GERAL'!$E$11)/N34,0) -> 1.7646804 | AW34: =AU34/'CALCULO GERAL'!$C$11 -> 12.821816 | AX34: =BP34-BB34-BD34*'CALCULO GERAL'!$C$11 -> 86.91051 | AY34: =AX34*G34 -> 1.4340234 | AZ34: =AX34*H34 -> 6.6051987 | BA34: =BP34-BD34 -> 88.23402 | BB34: =BA34*L34 -> 1.3235103 | BC34: =BP34/(1+D34) -> 88.23402 | BD34: =BC34*D34 -> 0 | BE34: =BU34*0.08 -> 47293.435 | BF34: =BU34*0.12 -> 70940.152 | BG34: =(BF34*0.09)/N34 -> 0.95292742 | BH34: =(BE34*0.15)/N34 -> 1.0588082 | BI34: =IF(BE34>=$BY$1,($BY$1-BE34)*0.1,IF(BE34<=$BY$1,($BY$1*0)))/N34 -> 0 | BJ34: =(AY34+AZ34+BB34+AV34+BD34+BG34+BH34+BI34) -> 13.139149 | BK34: =BJ34+AU34 -> 77.491843 | BL34: 0.74 | BM34: =ROUND((AW34/BL34)+((AW34*BL34)*'CALCULO GERAL'!$E$11)/BL34,2) -> 17.58 | BN34: =BM34 -> 17.58 | BO34: =ROUND(FV(0.02,8,,BN34)*-1,3) -> 20.598 | BP34: =BM34*'CALCULO GERAL'!$C$11 -> 88.23402 | BQ34: =BO34*'CALCULO GERAL'!$C$11 -> 103.38136 | BR34: =BN34*'CALCULO GERAL'!$C$11 -> 88.23402 | BS34: =BP34*N34 -> 591167.93 | BT34: =BS34-AT34 -> 160004.88 | BU34: =BR34*N34 -> 591167.93 | BV34: =BK34*N34 -> 519195.35 | BW34: =BS34-BV34 -> 71972.586 | BX34: =(((BK34*N34)-BS34)/BS34*-1) -> 0.12174643 | BY34: =ROUND(BL34,2) -> 0.74 | CE34: =CC34/BY34 -> 0 | CF34: =100%-CE34 -> 1 | CG34: =AVERAGE(CF34,CD34) -> 1
A35: COLCHA CASAL 90gsm SEERSUCKER COSTURADO - 220x240cm B | B35: 9404.40.00 | C35: 0.162 | D35: 0 | E35: 0.021 | F35: 0.0965 | G35: 0.0165 | H35: 0.076 | I35: 0.18 | J35: 0.04 | K35: 0.14 | L35: 0.015 | M35: N/A | N35: 6700 | O35: 10.95 | X35: =MIN(O35:W35) -> 10.95 | Y35: =AVERAGE(O35:W35) -> 10.95 | Z35: =Y35*N35 -> 73365 | AA35: ='CALCULO GERAL'!$G$10 -> 6300 | AB35: =Z35+AA35 -> 79665 | AC35: =AB35*'CALCULO GERAL'!$C$11 -> 399838.64 | AD35: =AC35*C35 -> 64773.859 | AE35: =(AC35+AD35)*D35 -> 0 | AF35: =AC35*E35 -> 8396.6113 | AG35: =AC35*F35 -> 38584.428 | AH35: 154.23 | AI35: =((AA35*'CALCULO GERAL'!$C$11))*0.08+20 -> 2549.576 | AJ35: 1010 | AK35: 2500 | AL35: =(AA35*('CALCULO GERAL'!$C$11*1.02))-(AA35*'CALCULO GERAL'!$C$11) -> 632.394 | AM35: 1800 | AN35: 2600 | AO35: 9400 | AP35: 1000 | AQ35: =-AF35 -> -8396.6113 | AR35: =-AG35 -> -38584.428 | AT35: =SUM(AC35:AS35) -> 486258.69 | AU35: =IFERROR((AT35/N35),0) -> 72.575924 | AV35: =IFERROR((BS35*'CALCULO GERAL'!$E$11)/N35,0) -> 1.9905354 | AW35: =AU35/'CALCULO GERAL'!$C$11 -> 14.460236 | AX35: =BP35-BB35-BD35*'CALCULO GERAL'!$C$11 -> 98.033868 | AY35: =AX35*G35 -> 1.6175588 | AZ35: =AX35*H35 -> 7.450574 | BA35: =BP35-BD35 -> 99.52677 | BB35: =BA35*L35 -> 1.4929016 | BC35: =BP35/(1+D35) -> 99.52677 | BD35: =BC35*D35 -> 0 | BE35: =BU35*0.08 -> 53346.349 | BF35: =BU35*0.12 -> 80019.523 | BG35: =(BF35*0.09)/N35 -> 1.0748891 | BH35: =(BE35*0.15)/N35 -> 1.1943212 | BI35: =IF(BE35>=$BY$1,($BY$1-BE35)*0.1,IF(BE35<=$BY$1,($BY$1*0)))/N35 -> 0 | BJ35: =(AY35+AZ35+BB35+AV35+BD35+BG35+BH35+BI35) -> 14.82078 | BK35: =BJ35+AU35 -> 87.396705 | BL35: 0.74 | BM35: =ROUND((AW35/BL35)+((AW35*BL35)*'CALCULO GERAL'!$E$11)/BL35,2) -> 19.83 | BN35: =BM35 -> 19.83 | BO35: =ROUND(FV(0.02,8,,BN35)*-1,3) -> 23.234 | BP35: =BM35*'CALCULO GERAL'!$C$11 -> 99.52677 | BQ35: =BO35*'CALCULO GERAL'!$C$11 -> 116.61145 | BR35: =BN35*'CALCULO GERAL'!$C$11 -> 99.52677 | BS35: =BP35*N35 -> 666829.36 | BT35: =BS35-AT35 -> 180570.67 | BU35: =BR35*N35 -> 666829.36 | BV35: =BK35*N35 -> 585557.92 | BW35: =BS35-BV35 -> 81271.438 | BX35: =(((BK35*N35)-BS35)/BS35*-1) -> 0.12187741 | BY35: =ROUND(BL35,2) -> 0.74 | CE35: =CC35/BY35 -> 0 | CF35: =100%-CE35 -> 1 | CG35: =AVERAGE(CF35,CD35) -> 1
A36: COLCHA QUEEN 90GSM SEERSUCKER COSTURADO - 240x260cm B | B36: 9404.40.00 | C36: 0.162 | D36: 0 | E36: 0.021 | F36: 0.0965 | G36: 0.0165 | H36: 0.076 | I36: 0.18 | J36: 0.04 | K36: 0.14 | L36: 0.015 | M36: N/A | N36: 6700 | O36: 10.2 | X36: =MIN(O36:W36) -> 10.2 | Y36: =AVERAGE(O36:W36) -> 10.2 | Z36: =Y36*N36 -> 68340 | AA36: ='CALCULO GERAL'!$G$10 -> 6300 | AB36: =Z36+AA36 -> 74640 | AC36: =AB36*'CALCULO GERAL'!$C$11 -> 374618.16 | AD36: =AC36*C36 -> 60688.142 | AE36: =(AC36+AD36)*D36 -> 0 | AF36: =AC36*E36 -> 7866.9814 | AG36: =AC36*F36 -> 36150.652 | AH36: 154.23 | AI36: =((AA36*'CALCULO GERAL'!$C$11))*0.08+20 -> 2549.576 | AJ36: 1010 | AK36: 2500 | AL36: =(AA36*('CALCULO GERAL'!$C$11*1.02))-(AA36*'CALCULO GERAL'!$C$11) -> 632.394 | AM36: 1800 | AN36: 2600 | AO36: 9400 | AP36: 1000 | AQ36: =-AF36 -> -7866.9814 | AR36: =-AG36 -> -36150.652 | AT36: =SUM(AC36:AS36) -> 456952.5 | AU36: =IFERROR((AT36/N36),0) -> 68.201866 | AV36: =IFERROR((BS36*'CALCULO GERAL'!$E$11)/N36,0) -> 1.8700794 | AW36: =AU36/'CALCULO GERAL'!$C$11 -> 13.588736 | AX36: =BP36-BB36-BD36*'CALCULO GERAL'!$C$11 -> 92.10141 | AY36: =AX36*G36 -> 1.5196733 | AZ36: =AX36*H36 -> 6.9997072 | BA36: =BP36-BD36 -> 93.50397 | BB36: =BA36*L36 -> 1.4025595 | BC36: =BP36/(1+D36) -> 93.50397 | BD36: =BC36*D36 -> 0 | BE36: =BU36*0.08 -> 50118.128 | BF36: =BU36*0.12 -> 75177.192 | BG36: =(BF36*0.09)/N36 -> 1.0098429 | BH36: =(BE36*0.15)/N36 -> 1.1220476 | BI36: =IF(BE36>=$BY$1,($BY$1-BE36)*0.1,IF(BE36<=$BY$1,($BY$1*0)))/N36 -> 0 | BJ36: =(AY36+AZ36+BB36+AV36+BD36+BG36+BH36+BI36) -> 13.92391 | BK36: =BJ36+AU36 -> 82.125776 | BL36: 0.74 | BM36: =ROUND((AW36/BL36)+((AW36*BL36)*'CALCULO GERAL'!$E$11)/BL36,2) -> 18.63 | BN36: =BM36 -> 18.63 | BO36: =ROUND(FV(0.02,8,,BN36)*-1,3) -> 21.828 | BP36: =BM36*'CALCULO GERAL'!$C$11 -> 93.50397 | BQ36: =BO36*'CALCULO GERAL'!$C$11 -> 109.55473 | BR36: =BN36*'CALCULO GERAL'!$C$11 -> 93.50397 | BS36: =BP36*N36 -> 626476.6 | BT36: =BS36-AT36 -> 169524.1 | BU36: =BR36*N36 -> 626476.6 | BV36: =BK36*N36 -> 550242.7 | BW36: =BS36-BV36 -> 76233.901 | BX36: =(((BK36*N36)-BS36)/BS36*-1) -> 0.12168675 | BY36: =ROUND(BL36,2) -> 0.74 | CE36: =CC36/BY36 -> 0 | CF36: =100%-CE36 -> 1 | CG36: =AVERAGE(CF36,CD36) -> 1
A37: COLCHA KING 90gsm SEERSUCKER COSTURADO - 280x260cm B | B37: 9404.40.00 | C37: 0.162 | D37: 0 | E37: 0.021 | F37: 0.0965 | G37: 0.0165 | H37: 0.076 | I37: 0.18 | J37: 0.04 | K37: 0.14 | L37: 0.015 | M37: N/A | N37: 6700 | O37: 13.25 | X37: =MIN(O37:W37) -> 13.25 | Y37: =AVERAGE(O37:W37) -> 13.25 | Z37: =Y37*N37 -> 88775 | AA37: ='CALCULO GERAL'!$G$10 -> 6300 | AB37: =Z37+AA37 -> 95075 | AC37: =AB37*'CALCULO GERAL'!$C$11 -> 477181.42 | AD37: =AC37*C37 -> 77303.391 | AE37: =(AC37+AD37)*D37 -> 0 | AF37: =AC37*E37 -> 10020.81 | AG37: =AC37*F37 -> 46048.008 | AH37: 154.23 | AI37: =((AA37*'CALCULO GERAL'!$C$11))*0.08+20 -> 2549.576 | AJ37: 1010 | AK37: 2500 | AL37: =(AA37*('CALCULO GERAL'!$C$11*1.02))-(AA37*'CALCULO GERAL'!$C$11) -> 632.394 | AM37: 1800 | AN37: 2600 | AO37: 9400 | AP37: 1000 | AQ37: =-AF37 -> -10020.81 | AR37: =-AG37 -> -46048.008 | AT37: =SUM(AC37:AS37) -> 576131.02 | AU37: =IFERROR((AT37/N37),0) -> 85.989704 | AV37: =IFERROR((BS37*'CALCULO GERAL'!$E$11)/N37,0) -> 2.35893 | AW37: =AU37/'CALCULO GERAL'!$C$11 -> 17.132836 | AX37: =BP37-BB37-BD37*'CALCULO GERAL'!$C$11 -> 116.1773 | AY37: =AX37*G37 -> 1.9169255 | AZ37: =AX37*H37 -> 8.829475 | BA37: =BP37-BD37 -> 117.9465 | BB37: =BA37*L37 -> 1.7691975 | BC37: =BP37/(1+D37) -> 117.9465 | BD37: =BC37*D37 -> 0 | BE37: =BU37*0.08 -> 63219.324 | BF37: =BU37*0.12 -> 94828.986 | BG37: =(BF37*0.09)/N37 -> 1.2738222 | BH37: =(BE37*0.15)/N37 -> 1.415358 | BI37: =IF(BE37>=$BY$1,($BY$1-BE37)*0.1,IF(BE37<=$BY$1,($BY$1*0)))/N37 -> -0.048049761 | BJ37: =(AY37+AZ37+BB37+AV37+BD37+BG37+BH37+BI37) -> 17.515658 | BK37: =BJ37+AU37 -> 103.50536 | BL37: 0.74 | BM37: =ROUND((AW37/BL37)+((AW37*BL37)*'CALCULO GERAL'!$E$11)/BL37,2) -> 23.5 | BN37: =BM37 -> 23.5 | BO37: =ROUND(FV(0.02,8,,BN37)*-1,3) -> 27.534 | BP37: =BM37*'CALCULO GERAL'!$C$11 -> 117.9465 | BQ37: =BO37*'CALCULO GERAL'!$C$11 -> 138.19315 | BR37: =BN37*'CALCULO GERAL'!$C$11 -> 117.9465 | BS37: =BP37*N37 -> 790241.55 | BT37: =BS37-AT37 -> 214110.53 | BU37: =BR37*N37 -> 790241.55 | BV37: =BK37*N37 -> 693485.93 | BW37: =BS37-BV37 -> 96755.623 | BX37: =(((BK37*N37)-BS37)/BS37*-1) -> 0.12243804 | BY37: =ROUND(BL37,2) -> 0.74 | CE37: =CC37/BY37 -> 0 | CF37: =100%-CE37 -> 1 | CG37: =AVERAGE(CF37,CD37) -> 1
... A41: COLCHA SUPER KING 90GSM SOLID COSTURADO - 310x280cm | B41: 9404.40.00 | C41: 0.162 | D41: 0 | E41: 0.021 | F41: 0.0965 | G41: 0.0165 | H41: 0.076 | I41: 0.18 | J41: 0.04 | K41: 0.14 | L41: 0.015 | M41: N/A | N41: 6700 | O41: 10.95 | X41: =MIN(O41:W41) -> 10.95 | Y41: =AVERAGE(O41:W41) -> 10.95 | Z41: =Y41*N41 -> 73365 | AA41: ='CALCULO GERAL'!$G$10 -> 6300 | AB41: =Z41+AA41 -> 79665 | AC41: =AB41*'CALCULO GERAL'!$C$11 -> 399838.64 | AD41: =AC41*C41 -> 64773.859 | AE41: =(AC41+AD41)*D41 -> 0 | AF41: =AC41*E41 -> 8396.6113 | AG41: =AC41*F41 -> 38584.428 | AH41: 154.23 | AI41: =((AA41*'CALCULO GERAL'!$C$11))*0.08+20 -> 2549.576 | AJ41: 1010 | AK41: 2500 | AL41: =(AA41*('CALCULO GERAL'!$C$11*1.02))-(AA41*'CALCULO GERAL'!$C$11) -> 632.394 | AM41: 1800 | AN41: 2600 | AO41: 9400 | AP41: 1000 | AQ41: =-AF41 -> -8396.6113 | AR41: =-AG41 -> -38584.428 | AT41: =SUM(AC41:AS41) -> 486258.69 | AU41: =IFERROR((AT41/N41),0) -> 72.575924 | AV41: =IFERROR((BS41*'CALCULO GERAL'!$E$11)/N41,0) -> 1.9905354 | AW41: =AU41/'CALCULO GERAL'!$C$11 -> 14.460236 | AX41: =BP41-BB41-BD41*'CALCULO GERAL'!$C$11 -> 98.033868 | AY41: =AX41*G41 -> 1.6175588 | AZ41: =AX41*H41 -> 7.450574 | BA41: =BP41-BD41 -> 99.52677 | BB41: =BA41*L41 -> 1.4929016 | BC41: =BP41/(1+D41) -> 99.52677 | BD41: =BC41*D41 -> 0 | BE41: =BU41*0.08 -> 53346.349 | BF41: =BU41*0.12 -> 80019.523 | BG41: =(BF41*0.09)/N41 -> 1.0748891 | BH41: =(BE41*0.15)/N41 -> 1.1943212 | BI41: =IF(BE41>=$BY$1,($BY$1-BE41)*0.1,IF(BE41<=$BY$1,($BY$1*0)))/N41 -> 0 | BJ41: =(AY41+AZ41+BB41+AV41+BD41+BG41+BH41+BI41) -> 14.82078 | BK41: =BJ41+AU41 -> 87.396705 | BL41: 0.74 | BM41: =ROUND((AW41/BL41)+((AW41*BL41)*'CALCULO GERAL'!$E$11)/BL41,2) -> 19.83 | BN41: =BM41 -> 19.83 | BO41: =ROUND(FV(0.02,8,,BN41)*-1,3) -> 23.234 | BP41: =BM41*'CALCULO GERAL'!$C$11 -> 99.52677 | BQ41: =BO41*'CALCULO GERAL'!$C$11 -> 116.61145 | BR41: =BN41*'CALCULO GERAL'!$C$11 -> 99.52677 | BS41: =BP41*N41 -> 666829.36 | BT41: =BS41-AT41 -> 180570.67 | BU41: =BR41*N41 -> 666829.36 | BV41: =BK41*N41 -> 585557.92 | BW41: =BS41-BV41 -> 81271.438 | BX41: =(((BK41*N41)-BS41)/BS41*-1) -> 0.12187741 | BY41: =ROUND(BL41,2) -> 0.74 | CE41: =CC41/BY41 -> 0 | CF41: =100%-CE41 -> 1 | CG41: =AVERAGE(CF41,CD41) -> 1
A42: CORTINA | B42: 6303.92.00 | C42: 0.35 | D42: 0 | E42: 0.021 | F42: 0.1065 | G42: 0.0165 | H42: 0.076 | I42: 0.18 | J42: 0.04 | K42: 0.14 | L42: 0.015 | M42: N/A | N42: 24000 | U42: 6.75 | X42: =MIN(O42:W42) -> 6.75 | Y42: =AVERAGE(O42:W42) -> 6.75 | Z42: =Y42*N42 -> 162000 | AA42: ='CALCULO GERAL'!$G$10 -> 6300 | AB42: =Z42+AA42 -> 168300 | AC42: =AB42*'CALCULO GERAL'!$C$11 -> 844697.7 | AD42: =AC42*C42 -> 295644.2 | AE42: =(AC42+AD42)*D42 -> 0 | AF42: =AC42*E42 -> 17738.652 | AG42: =AC42*F42 -> 89960.305 | AH42: 154.23 | AI42: =((AA42*'CALCULO GERAL'!$C$11))*0.08+20 -> 2549.576 | AJ42: 1010 | AK42: 2500 | AL42: =(AA42*('CALCULO GERAL'!$C$11*1.02))-(AA42*'CALCULO GERAL'!$C$11) -> 632.394 | AM42: 1800 | AN42: 2600 | AO42: 9400 | AP42: 1000 | AQ42: =-AF42 -> -17738.652 | AR42: =-AG42 -> -89960.305 | AT42: =SUM(AC42:AS42) -> 1161988.1 | AU42: =IFERROR((AT42/N42),0) -> 48.416171 | AV42: =IFERROR((BS42*'CALCULO GERAL'!$E$11)/N42,0) -> 1.3280274 | AW42: =AU42/'CALCULO GERAL'!$C$11 -> 9.6465771 | AX42: =BP42-BB42-BD42*'CALCULO GERAL'!$C$11 -> 65.405349 | AY42: =AX42*G42 -> 1.0791883 | AZ42: =AX42*H42 -> 4.9708066 | BA42: =BP42-BD42 -> 66.40137 | BB42: =BA42*L42 -> 0.99602055 | BC42: =BP42/(1+D42) -> 66.40137 | BD42: =BC42*D42 -> 0 | BE42: =BU42*0.08 -> 127490.63 | BF42: =BU42*0.12 -> 191235.95 | BG42: =(BF42*0.09)/N42 -> 0.7171348 | BH42: =(BE42*0.15)/N42 -> 0.79681644 | BI42: =IF(BE42>=$BY$1,($BY$1-BE42)*0.1,IF(BE42<=$BY$1,($BY$1*0)))/N42 -> -0.281211 | BJ42: =(AY42+AZ42+BB42+AV42+BD42+BG42+BH42+BI42) -> 9.606783 | BK42: =BJ42+AU42 -> 58.022954 | BL42: 0.74 | BM42: =ROUND((AW42/BL42)+((AW42*BL42)*'CALCULO GERAL'!$E$11)/BL42,2) -> 13.23 | BN42: =BM42 -> 13.23 | BO42: =ROUND(FV(0.02,8,,BN42)*-1,3) -> 15.501 | BP42: =BM42*'CALCULO GERAL'!$C$11 -> 66.40137 | BQ42: =BO42*'CALCULO GERAL'!$C$11 -> 77.799519 | BR42: =BN42*'CALCULO GERAL'!$C$11 -> 66.40137 | BS42: =BP42*N42 -> 1593632.9 | BT42: =BS42-AT42 -> 431644.78 | BU42: =BR42*N42 -> 1593632.9 | BV42: =BK42*N42 -> 1392550.9 | BW42: =BS42-BV42 -> 201081.99 | BX42: =(((BK42*N42)-BS42)/BS42*-1) -> 0.12617837 | BY42: =ROUND(BL42,2) -> 0.74 | CE42: =CC42/BY42 -> 0 | CF42: =100%-CE42 -> 1 | CG42: =AVERAGE(CF42,CD42) -> 1
A43: FIBRA DE POLIÉSTER | B43: 5503.20.90 | C43: 0.125 | D43: 0 | E43: 0.021 | F43: 0.1065 | G43: 0.0165 | H43: 0.076 | I43: 0.18 | J43: 0.04 | K43: 0.14 | L43: 0.015 | M43: N/A | N43: 24000 | V43: 0.92 | X43: =MIN(O43:W43) -> 0.92 | Y43: =AVERAGE(O43:W43) -> 0.92 | Z43: =Y43*N43 -> 22080 | AA43: ='CALCULO GERAL'!$G$10 -> 6300 | AB43: =Z43+AA43 -> 28380 | AC43: =AB43*'CALCULO GERAL'!$C$11 -> 142439.22 | AD43: =AC43*C43 -> 17804.903 | AE43: =(AC43+AD43)*D43 -> 0 | AF43: =AC43*E43 -> 2991.2236 | AG43: =AC43*F43 -> 15169.777 | AH43: 154.23 | AI43: =((AA43*'CALCULO GERAL'!$C$11))*0.08+20 -> 2549.576 | AJ43: 1010 | AK43: 2500 | AL43: =(AA43*('CALCULO GERAL'!$C$11*1.02))-(AA43*'CALCULO GERAL'!$C$11) -> 632.394 | AM43: 1800 | AN43: 2600 | AO43: 9400 | AP43: 1000 | AQ43: =-AF43 -> -2991.2236 | AR43: =-AG43 -> -15169.777 | AT43: =SUM(AC43:AS43) -> 181890.32 | AU43: =IFERROR((AT43/N43),0) -> 7.5787634 | AV43: =IFERROR((BS43*'CALCULO GERAL'!$E$11)/N43,0) -> 0.2077866 | AW43: =AU43/'CALCULO GERAL'!$C$11 -> 1.5100146 | AX43: =BP43-BB43-BD43*'CALCULO GERAL'!$C$11 -> 10.23349 | AY43: =AX43*G43 -> 0.16885259 | AZ43: =AX43*H43 -> 0.77774524 | BA43: =BP43-BD43 -> 10.38933 | BB43: =BA43*L43 -> 0.15583995 | BC43: =BP43/(1+D43) -> 10.38933 | BD43: =BC43*D43 -> 0 | BE43: =BU43*0.08 -> 19947.514 | BF43: =BU43*0.12 -> 29921.27 | BG43: =(BF43*0.09)/N43 -> 0.11220476 | BH43: =(BE43*0.15)/N43 -> 0.12467196 | BI43: =IF(BE43>=$BY$1,($BY$1-BE43)*0.1,IF(BE43<=$BY$1,($BY$1*0)))/N43 -> 0 | BJ43: =(AY43+AZ43+BB43+AV43+BD43+BG43+BH43+BI43) -> 1.5471011 | BK43: =BJ43+AU43 -> 9.1258645 | BL43: 0.74 | BM43: =ROUND((AW43/BL43)+((AW43*BL43)*'CALCULO GERAL'!$E$11)/BL43,2) -> 2.07 | BN43: =BM43 -> 2.07 | BO43: =ROUND(FV(0.02,8,,BN43)*-1,3) -> 2.425 | BP43: =BM43*'CALCULO GERAL'!$C$11 -> 10.38933 | BQ43: =BO43*'CALCULO GERAL'!$C$11 -> 12.171075 | BR43: =BN43*'CALCULO GERAL'!$C$11 -> 10.38933 | BS43: =BP43*N43 -> 249343.92 | BT43: =BS43-AT43 -> 67453.597 | BU43: =BR43*N43 -> 249343.92 | BV43: =BK43*N43 -> 219020.75 | BW43: =BS43-BV43 -> 30323.171 | BX43: =(((BK43*N43)-BS43)/BS43*-1) -> 0.12161183 | BY43: =ROUND(BL43,2) -> 0.74 | CE43: =CC43/BY43 -> 0 | CF43: =100%-CE43 -> 1 | CG43: =AVERAGE(CF43,CD43) -> 1
A44: FIBRA DE POLIÉSTER BI-COMPONENTE | B44: 5503.20.10 | C44: 0.02 | D44: 0 | E44: 0.021 | F44: 0.1065 | G44: 0.0165 | H44: 0.076 | I44: 0.18 | J44: 0.04 | K44: 0.14 | L44: 0.015 | M44: N/A | N44: 24000 | V44: 0.92 | X44: =MIN(O44:W44) -> 0.92 | Y44: =AVERAGE(O44:W44) -> 0.92 | Z44: =Y44*N44 -> 22080 | AA44: ='CALCULO GERAL'!$G$10 -> 6300 | AB44: =Z44+AA44 -> 28380 | AC44: =AB44*'CALCULO GERAL'!$C$11 -> 142439.22 | AD44: =AC44*C44 -> 2848.7844 | AE44: =(AC44+AD44)*D44 -> 0 | AF44: =AC44*E44 -> 2991.2236 | AG44: =AC44*F44 -> 15169.777 | AH44: 154.23 | AI44: =((AA44*'CALCULO GERAL'!$C$11))*0.08+20 -> 2549.576 | AJ44: 1010 | AK44: 2500 | AL44: =(AA44*('CALCULO GERAL'!$C$11*1.02))-(AA44*'CALCULO GERAL'!$C$11) -> 632.394 | AM44: 1800 | AN44: 2600 | AO44: 9400 | AP44: 1000 | AQ44: =-AF44 -> -2991.2236 | AR44: =-AG44 -> -15169.777 | AT44: =SUM(AC44:AS44) -> 166934.2 | AU44: =IFERROR((AT44/N44),0) -> 6.9555919 | AV44: =IFERROR((BS44*'CALCULO GERAL'!$E$11)/N44,0) -> 0.190722 | AW44: =AU44/'CALCULO GERAL'!$C$11 -> 1.3858521 | AX44: =BP44-BB44-BD44*'CALCULO GERAL'!$C$11 -> 9.3930585 | AY44: =AX44*G44 -> 0.15498547 | AZ44: =AX44*H44 -> 0.71387245 | BA44: =BP44-BD44 -> 9.5361 | BB44: =BA44*L44 -> 0.1430415 | BC44: =BP44/(1+D44) -> 9.5361 | BD44: =BC44*D44 -> 0 | BE44: =BU44*0.08 -> 18309.312 | BF44: =BU44*0.12 -> 27463.968 | BG44: =(BF44*0.09)/N44 -> 0.10298988 | BH44: =(BE44*0.15)/N44 -> 0.1144332 | BI44: =IF(BE44>=$BY$1,($BY$1-BE44)*0.1,IF(BE44<=$BY$1,($BY$1*0)))/N44 -> 0 | BJ44: =(AY44+AZ44+BB44+AV44+BD44+BG44+BH44+BI44) -> 1.4200445 | BK44: =BJ44+AU44 -> 8.3756363 | BL44: 0.74 | BM44: =ROUND((AW44/BL44)+((AW44*BL44)*'CALCULO GERAL'!$E$11)/BL44,2) -> 1.9 | BN44: =BM44 -> 1.9 | BO44: =ROUND(FV(0.02,8,,BN44)*-1,3) -> 2.226 | BP44: =BM44*'CALCULO GERAL'!$C$11 -> 9.5361 | BQ44: =BO44*'CALCULO GERAL'!$C$11 -> 11.172294 | BR44: =BN44*'CALCULO GERAL'!$C$11 -> 9.5361 | BS44: =BP44*N44 -> 228866.4 | BT44: =BS44-AT44 -> 61932.196 | BU44: =BR44*N44 -> 228866.4 | BV44: =BK44*N44 -> 201015.27 | BW44: =BS44-BV44 -> 27851.128 | BX44: =(((BK44*N44)-BS44)/BS44*-1) -> 0.12169164 | BY44: =ROUND(BL44,2) -> 0.74 | CE44: =CC44/BY44 -> 0 | CF44: =100%-CE44 -> 1 | CG44: =AVERAGE(CF44,CD44) -> 1
A45: FIO DE POLIÉSTER | B45: 5402.33.10 | C45: 0.18 | D45: 0 | E45: 0.021 | F45: 0.0965 | G45: 0.0165 | H45: 0.076 | I45: 0.18 | J45: 0.04 | K45: 0.14 | L45: 0.015 | M45: N/A | N45: 22000 | S45: 1.34 | X45: =MIN(O45:W45) -> 1.34 | Y45: =AVERAGE(O45:W45) -> 1.34 | Z45: =Y45*N45 -> 29480 | AA45: ='CALCULO GERAL'!$G$10 -> 6300 | AB45: =Z45+AA45 -> 35780 | AC45: =AB45*'CALCULO GERAL'!$C$11 -> 179579.82 | AD45: =AC45*C45 -> 32324.368 | AE45: =(AC45+AD45)*D45 -> 0 | AF45: =AC45*E45 -> 3771.1762 | AG45: =AC45*F45 -> 17329.453 | AH45: 154.23 | AI45: =((AA45*'CALCULO GERAL'!$C$11))*0.08+20 -> 2549.576 | AJ45: 1010 | AK45: 2500 | AL45: =(AA45*('CALCULO GERAL'!$C$11*1.02))-(AA45*'CALCULO GERAL'!$C$11) -> 632.394 | AM45: 1800 | AN45: 2600 | AO45: 9400 | AP45: 1000 | AQ45: =-AF45 -> -3771.1762 | AR45: =-AG45 -> -17329.453 | AT45: =SUM(AC45:AS45) -> 233550.39 | AU45: =IFERROR((AT45/N45),0) -> 10.615927 | AV45: =IFERROR((BS45*'CALCULO GERAL'!$E$11)/N45,0) -> 0.2730336 | AW45: =AU45/'CALCULO GERAL'!$C$11 -> 2.1151478 | AX45: =BP45-BB45-BD45*'CALCULO GERAL'!$C$11 -> 13.446905 | AY45: =AX45*G45 -> 0.22187393 | AZ45: =AX45*H45 -> 1.0219648 | BA45: =BP45-BD45 -> 13.65168 | BB45: =BA45*L45 -> 0.2047752 | BC45: =BP45/(1+D45) -> 13.65168 | BD45: =BC45*D45 -> 0 | BE45: =BU45*0.08 -> 24026.957 | BF45: =BU45*0.12 -> 36040.435 | BG45: =(BF45*0.09)/N45 -> 0.14743814 | BH45: =(BE45*0.15)/N45 -> 0.16382016 | BI45: =IF(BE45>=$BY$1,($BY$1-BE45)*0.1,IF(BE45<=$BY$1,($BY$1*0)))/N45 -> 0 | BJ45: =(AY45+AZ45+BB45+AV45+BD45+BG45+BH45+BI45) -> 2.0329058 | BK45: =BJ45+AU45 -> 12.648833 | BL45: 0.79 | BM45: =ROUND((AW45/BL45)+((AW45*BL45)*'CALCULO GERAL'!$E$11)/BL45,2) -> 2.72 | BN45: =BM45 -> 2.72 | BO45: =ROUND(FV(0.02,8,,BN45)*-1,3) -> 3.187 | BP45: =BM45*'CALCULO GERAL'!$C$11 -> 13.65168 | BQ45: =BO45*'CALCULO GERAL'!$C$11 -> 15.995553 | BR45: =BN45*'CALCULO GERAL'!$C$11 -> 13.65168 | BS45: =BP45*N45 -> 300336.96 | BT45: =BS45-AT45 -> 66786.572 | BU45: =BR45*N45 -> 300336.96 | BV45: =BK45*N45 -> 278274.32 | BW45: =BS45-BV45 -> 22062.645 | BX45: =(((BK45*N45)-BS45)/BS45*-1) -> 0.07345964 | BY45: =ROUND(BL45,2) -> 0.79 | CE45: =CC45/BY45 -> 0 | CF45: =100%-CE45 -> 1 | CG45: =AVERAGE(CF45,CD45) -> 1
A46: PROTETOR DE COLCHÃO SOLTEIRO | B46: 6302.32.00 | C46: 0.35 | D46: 0 | E46: 0.021 | F46: 0.1065 | G46: 0.0165 | H46: 0.076 | I46: 0.18 | J46: 0.04 | K46: 0.14 | L46: 0.015 | M46: N/A | N46: 9000 | T46: 3.28 | X46: =MIN(O46:W46) -> 3.28 | Y46: =AVERAGE(O46:W46) -> 3.28 | Z46: =Y46*N46 -> 29520 | AA46: ='CALCULO GERAL'!$G$10 -> 6300 | AB46: =Z46+AA46 -> 35820 | AC46: =AB46*'CALCULO GERAL'!$C$11 -> 179780.58 | AD46: =AC46*C46 -> 62923.203 | AE46: =(AC46+AD46)*D46 -> 0 | AF46: =AC46*E46 -> 3775.3922 | AG46: =AC46*F46 -> 19146.632 | AH46: 154.23 | AI46: =((AA46*'CALCULO GERAL'!$C$11))*0.08+20 -> 2549.576 | AJ46: 1010 | AK46: 2500 | AL46: =(AA46*('CALCULO GERAL'!$C$11*1.02))-(AA46*'CALCULO GERAL'!$C$11) -> 632.394 | AM46: 1800 | AN46: 2600 | AO46: 9400 | AP46: 1000 | AQ46: =-AF46 -> -3775.3922 | AR46: =-AG46 -> -19146.632 | AT46: =SUM(AC46:AS46) -> 264349.98 | AU46: =IFERROR((AT46/N46),0) -> 29.37222 | AV46: =IFERROR((BS46*'CALCULO GERAL'!$E$11)/N46,0) -> 0.8060514 | AW46: =AU46/'CALCULO GERAL'!$C$11 -> 5.8522057 | AX46: =BP46-BB46-BD46*'CALCULO GERAL'!$C$11 -> 39.698031 | AY46: =AX46*G46 -> 0.65501752 | AZ46: =AX46*H46 -> 3.0170504 | BA46: =BP46-BD46 -> 40.30257 | BB46: =BA46*L46 -> 0.60453855 | BC46: =BP46/(1+D46) -> 40.30257 | BD46: =BC46*D46 -> 0 | BE46: =BU46*0.08 -> 29017.85 | BF46: =BU46*0.12 -> 43526.776 | BG46: =(BF46*0.09)/N46 -> 0.43526776 | BH46: =(BE46*0.15)/N46 -> 0.48363084 | BI46: =IF(BE46>=$BY$1,($BY$1-BE46)*0.1,IF(BE46<=$BY$1,($BY$1*0)))/N46 -> 0 | BJ46: =(AY46+AZ46+BB46+AV46+BD46+BG46+BH46+BI46) -> 6.0015565 | BK46: =BJ46+AU46 -> 35.373777 | BL46: 0.74 | BM46: =ROUND((AW46/BL46)+((AW46*BL46)*'CALCULO GERAL'!$E$11)/BL46,2) -> 8.03 | BN46: =BM46 -> 8.03 | BO46: =ROUND(FV(0.02,8,,BN46)*-1,3) -> 9.408 | BP46: =BM46*'CALCULO GERAL'!$C$11 -> 40.30257 | BQ46: =BO46*'CALCULO GERAL'!$C$11 -> 47.218752 | BR46: =BN46*'CALCULO GERAL'!$C$11 -> 40.30257 | BS46: =BP46*N46 -> 362723.13 | BT46: =BS46-AT46 -> 98373.147 | BU46: =BR46*N46 -> 362723.13 | BV46: =BK46*N46 -> 318363.99 | BW46: =BS46-BV46 -> 44359.139 | BX46: =(((BK46*N46)-BS46)/BS46*-1) -> 0.12229476 | BY46: =ROUND(BL46,2) -> 0.74 | CE46: =CC46/BY46 -> 0 | CF46: =100%-CE46 -> 1 | CG46: =AVERAGE(CF46,CD46) -> 1
A47: PROTETOR DE COLCHÃO CASAL | B47: 6302.32.00 | C47: 0.35 | D47: 0 | E47: 0.021 | F47: 0.1065 | G47: 0.0165 | H47: 0.076 | I47: 0.18 | J47: 0.04 | K47: 0.14 | L47: 0.015 | M47: N/A | N47: 9000 | T47: 4.04 | X47: =MIN(O47:W47) -> 4.04 | Y47: =AVERAGE(O47:W47) -> 4.04 | Z47: =Y47*N47 -> 36360 | AA47: ='CALCULO GERAL'!$G$10 -> 6300 | AB47: =Z47+AA47 -> 42660 | AC47: =AB47*'CALCULO GERAL'!$C$11 -> 214110.54 | AD47: =AC47*C47 -> 74938.689 | AE47: =(AC47+AD47)*D47 -> 0 | AF47: =AC47*E47 -> 4496.3213 | AG47: =AC47*F47 -> 22802.773 | AH47: 154.23 | AI47: =((AA47*'CALCULO GERAL'!$C$11))*0.08+20 -> 2549.576 | AJ47: 1010 | AK47: 2500 | AL47: =(AA47*('CALCULO GERAL'!$C$11*1.02))-(AA47*'CALCULO GERAL'!$C$11) -> 632.394 | AM47: 1800 | AN47: 2600 | AO47: 9400 | AP47: 1000 | AQ47: =-AF47 -> -4496.3213 | AR47: =-AG47 -> -22802.773 | AT47: =SUM(AC47:AS47) -> 310695.43 | AU47: =IFERROR((AT47/N47),0) -> 34.521714 | AV47: =IFERROR((BS47*'CALCULO GERAL'!$E$11)/N47,0) -> 0.9465834 | AW47: =AU47/'CALCULO GERAL'!$C$11 -> 6.8782057 | AX47: =BP47-BB47-BD47*'CALCULO GERAL'!$C$11 -> 46.619232 | AY47: =AX47*G47 -> 0.76921734 | AZ47: =AX47*H47 -> 3.5430617 | BA47: =BP47-BD47 -> 47.32917 | BB47: =BA47*L47 -> 0.70993755 | BC47: =BP47/(1+D47) -> 47.32917 | BD47: =BC47*D47 -> 0 | BE47: =BU47*0.08 -> 34077.002 | BF47: =BU47*0.12 -> 51115.504 | BG47: =(BF47*0.09)/N47 -> 0.51115504 | BH47: =(BE47*0.15)/N47 -> 0.56795004 | BI47: =IF(BE47>=$BY$1,($BY$1-BE47)*0.1,IF(BE47<=$BY$1,($BY$1*0)))/N47 -> 0 | BJ47: =(AY47+AZ47+BB47+AV47+BD47+BG47+BH47+BI47) -> 7.047905 | BK47: =BJ47+AU47 -> 41.569619 | BL47: 0.74 | BM47: =ROUND((AW47/BL47)+((AW47*BL47)*'CALCULO GERAL'!$E$11)/BL47,2) -> 9.43 | BN47: =BM47 -> 9.43 | BO47: =ROUND(FV(0.02,8,,BN47)*-1,3) -> 11.049 | BP47: =BM47*'CALCULO GERAL'!$C$11 -> 47.32917 | BQ47: =BO47*'CALCULO GERAL'!$C$11 -> 55.454931 | BR47: =BN47*'CALCULO GERAL'!$C$11 -> 47.32917 | BS47: =BP47*N47 -> 425962.53 | BT47: =BS47-AT47 -> 115267.1 | BU47: =BR47*N47 -> 425962.53 | BV47: =BK47*N47 -> 374126.57 | BW47: =BS47-BV47 -> 51835.956 | BX47: =(((BK47*N47)-BS47)/BS47*-1) -> 0.12169135 | BY47: =ROUND(BL47,2) -> 0.74 | CE47: =CC47/BY47 -> 0 | CF47: =100%-CE47 -> 1 | CG47: =AVERAGE(CF47,CD47) -> 1
A48: PROTETOR DE COLCHÃO QUEEN | B48: 6302.32.00 | C48: 0.35 | D48: 0 | E48: 0.021 | F48: 0.1065 | G48: 0.0165 | H48: 0.076 | I48: 0.18 | J48: 0.04 | K48: 0.14 | L48: 0.015 | M48: N/A | N48: 9000 | T48: 4.4 | X48: =MIN(O48:W48) -> 4.4 | Y48: =AVERAGE(O48:W48) -> 4.4 | Z48: =Y48*N48 -> 39600 | AA48: ='CALCULO GERAL'!$G$10 -> 6300 | AB48: =Z48+AA48 -> 45900 | AC48: =AB48*'CALCULO GERAL'!$C$11 -> 230372.1 | AD48: =AC48*C48 -> 80630.235 | AE48: =(AC48+AD48)*D48 -> 0 | AF48: =AC48*E48 -> 4837.8141 | AG48: =AC48*F48 -> 24534.629 | AH48: 154.23 | AI48: =((AA48*'CALCULO GERAL'!$C$11))*0.08+20 -> 2549.576 | AJ48: 1010 | AK48: 2500 | AL48: =(AA48*('CALCULO GERAL'!$C$11*1.02))-(AA48*'CALCULO GERAL'!$C$11) -> 632.394 | AM48: 1800 | AN48: 2600 | AO48: 9400 | AP48: 1000 | AQ48: =-AF48 -> -4837.8141 | AR48: =-AG48 -> -24534.629 | AT48: =SUM(AC48:AS48) -> 332648.54 | AU48: =IFERROR((AT48/N48),0) -> 36.960948 | AV48: =IFERROR((BS48*'CALCULO GERAL'!$E$11)/N48,0) -> 1.013838 | AW48: =AU48/'CALCULO GERAL'!$C$11 -> 7.3642057 | AX48: =BP48-BB48-BD48*'CALCULO GERAL'!$C$11 -> 49.931521 | AY48: =AX48*G48 -> 0.8238701 | AZ48: =AX48*H48 -> 3.7947956 | BA48: =BP48-BD48 -> 50.6919 | BB48: =BA48*L48 -> 0.7603785 | BC48: =BP48/(1+D48) -> 50.6919 | BD48: =BC48*D48 -> 0 | BE48: =BU48*0.08 -> 36498.168 | BF48: =BU48*0.12 -> 54747.252 | BG48: =(BF48*0.09)/N48 -> 0.54747252 | BH48: =(BE48*0.15)/N48 -> 0.6083028 | BI48: =IF(BE48>=$BY$1,($BY$1-BE48)*0.1,IF(BE48<=$BY$1,($BY$1*0)))/N48 -> 0 | BJ48: =(AY48+AZ48+BB48+AV48+BD48+BG48+BH48+BI48) -> 7.5486576 | BK48: =BJ48+AU48 -> 44.509606 | BL48: 0.74 | BM48: =ROUND((AW48/BL48)+((AW48*BL48)*'CALCULO GERAL'!$E$11)/BL48,2) -> 10.1 | BN48: =BM48 -> 10.1 | BO48: =ROUND(FV(0.02,8,,BN48)*-1,3) -> 11.834 | BP48: =BM48*'CALCULO GERAL'!$C$11 -> 50.6919 | BQ48: =BO48*'CALCULO GERAL'!$C$11 -> 59.394846 | BR48: =BN48*'CALCULO GERAL'!$C$11 -> 50.6919 | BS48: =BP48*N48 -> 456227.1 | BT48: =BS48-AT48 -> 123578.56 | BU48: =BR48*N48 -> 456227.1 | BV48: =BK48*N48 -> 400586.45 | BW48: =BS48-BV48 -> 55640.647 | BX48: =(((BK48*N48)-BS48)/BS48*-1) -> 0.12195822 | BY48: =ROUND(BL48,2) -> 0.74 | CE48: =CC48/BY48 -> 0 | CF48: =100%-CE48 -> 1 | CG48: =AVERAGE(CF48,CD48) -> 1
A49: PROTETOR DE COLCHÃO KING | B49: 6302.32.00 | C49: 0.35 | D49: 0 | E49: 0.021 | F49: 0.1065 | G49: 0.0165 | H49: 0.076 | I49: 0.18 | J49: 0.04 | K49: 0.14 | L49: 0.015 | M49: N/A | N49: 9000 | T49: 5.34 | X49: =MIN(O49:W49) -> 5.34 | Y49: =AVERAGE(O49:W49) -> 5.34 | Z49: =Y49*N49 -> 48060 | AA49: ='CALCULO GERAL'!$G$10 -> 6300 | AB49: =Z49+AA49 -> 54360 | AC49: =AB49*'CALCULO GERAL'!$C$11 -> 272832.84 | AD49: =AC49*C49 -> 95491.494 | AE49: =(AC49+AD49)*D49 -> 0 | AF49: =AC49*E49 -> 5729.4896 | AG49: =AC49*F49 -> 29056.697 | AH49: 154.23 | AI49: =((AA49*'CALCULO GERAL'!$C$11))*0.08+20 -> 2549.576 | AJ49: 1010 | AK49: 2500 | AL49: =(AA49*('CALCULO GERAL'!$C$11*1.02))-(AA49*'CALCULO GERAL'!$C$11) -> 632.394 | AM49: 1800 | AN49: 2600 | AO49: 9400 | AP49: 1000 | AQ49: =-AF49 -> -5729.4896 | AR49: =-AG49 -> -29056.697 | AT49: =SUM(AC49:AS49) -> 389970.53 | AU49: =IFERROR((AT49/N49),0) -> 43.330059 | AV49: =IFERROR((BS49*'CALCULO GERAL'!$E$11)/N49,0) -> 1.1884992 | AW49: =AU49/'CALCULO GERAL'!$C$11 -> 8.6332057 | AX49: =BP49-BB49-BD49*'CALCULO GERAL'!$C$11 -> 58.533586 | AY49: =AX49*G49 -> 0.96580416 | AZ49: =AX49*H49 -> 4.4485525 | BA49: =BP49-BD49 -> 59.42496 | BB49: =BA49*L49 -> 0.8913744 | BC49: =BP49/(1+D49) -> 59.42496 | BD49: =BC49*D49 -> 0 | BE49: =BU49*0.08 -> 42785.971 | BF49: =BU49*0.12 -> 64178.957 | BG49: =(BF49*0.09)/N49 -> 0.64178957 | BH49: =(BE49*0.15)/N49 -> 0.71309952 | BI49: =IF(BE49>=$BY$1,($BY$1-BE49)*0.1,IF(BE49<=$BY$1,($BY$1*0)))/N49 -> 0 | BJ49: =(AY49+AZ49+BB49+AV49+BD49+BG49+BH49+BI49) -> 8.8491194 | BK49: =BJ49+AU49 -> 52.179179 | BL49: 0.74 | BM49: =ROUND((AW49/BL49)+((AW49*BL49)*'CALCULO GERAL'!$E$11)/BL49,2) -> 11.84 | BN49: =BM49 -> 11.84 | BO49: =ROUND(FV(0.02,8,,BN49)*-1,3) -> 13.872 | BP49: =BM49*'CALCULO GERAL'!$C$11 -> 59.42496 | BQ49: =BO49*'CALCULO GERAL'!$C$11 -> 69.623568 | BR49: =BN49*'CALCULO GERAL'!$C$11 -> 59.42496 | BS49: =BP49*N49 -> 534824.64 | BT49: =BS49-AT49 -> 144854.11 | BU49: =BR49*N49 -> 534824.64 | BV49: =BK49*N49 -> 469612.61 | BW49: =BS49-BV49 -> 65212.032 | BX49: =(((BK49*N49)-BS49)/BS49*-1) -> 0.12193161 | BY49: =ROUND(BL49,2) -> 0.74 | CE49: =CC49/BY49 -> 0 | CF49: =100%-CE49 -> 1 | CG49: =AVERAGE(CF49,CD49) -> 1
A50: JOGO DE CAMA POLIESTER 85GSM - PONTO PALITO SOLTEIRO | B50: 6302.32.00 | C50: 0.35 | D50: 0 | E50: 0.021 | F50: 0.1065 | G50: 0.0165 | H50: 0.076 | I50: 0.18 | J50: 0.04 | K50: 0.14 | L50: 0.015 | M50: N/A | N50: 16000 | T50: 3.5 | X50: =MIN(O50:W50) -> 3.5 | Y50: =AVERAGE(O50:W50) -> 3.5 | Z50: =Y50*N50 -> 56000 | AA50: ='CALCULO GERAL'!$G$10 -> 6300 | AB50: =Z50+AA50 -> 62300 | AC50: =AB50*'CALCULO GERAL'!$C$11 -> 312683.7 | AD50: =AC50*C50 -> 109439.29 | AE50: =(AC50+AD50)*D50 -> 0 | AF50: =AC50*E50 -> 6566.3577 | AG50: =AC50*F50 -> 33300.814 | AH50: 154.23 | AI50: =((AA50*'CALCULO GERAL'!$C$11))*0.08+20 -> 2549.576 | AJ50: 1010 | AK50: 2500 | AL50: =(AA50*('CALCULO GERAL'!$C$11*1.02))-(AA50*'CALCULO GERAL'!$C$11) -> 632.394 | AM50: 1800 | AN50: 2600 | AO50: 9400 | AP50: 1000 | AQ50: =-AF50 -> -6566.3577 | AR50: =-AG50 -> -33300.814 | AT50: =SUM(AC50:AS50) -> 443769.2 | AU50: =IFERROR((AT50/N50),0) -> 27.735575 | AV50: =IFERROR((BS50*'CALCULO GERAL'!$E$11)/N50,0) -> 0.7608804 | AW50: =AU50/'CALCULO GERAL'!$C$11 -> 5.5261157 | AX50: =BP50-BB50-BD50*'CALCULO GERAL'!$C$11 -> 37.47336 | AY50: =AX50*G50 -> 0.61831044 | AZ50: =AX50*H50 -> 2.8479753 | BA50: =BP50-BD50 -> 38.04402 | BB50: =BA50*L50 -> 0.5706603 | BC50: =BP50/(1+D50) -> 38.04402 | BD50: =BC50*D50 -> 0 | BE50: =BU50*0.08 -> 48696.346 | BF50: =BU50*0.12 -> 73044.518 | BG50: =(BF50*0.09)/N50 -> 0.41087542 | BH50: =(BE50*0.15)/N50 -> 0.45652824 | BI50: =IF(BE50>=$BY$1,($BY$1-BE50)*0.1,IF(BE50<=$BY$1,($BY$1*0)))/N50 -> 0 | BJ50: =(AY50+AZ50+BB50+AV50+BD50+BG50+BH50+BI50) -> 5.6652301 | BK50: =BJ50+AU50 -> 33.400805 | BL50: 0.74 | BM50: =ROUND((AW50/BL50)+((AW50*BL50)*'CALCULO GERAL'!$E$11)/BL50,2) -> 7.58 | BN50: =BM50 -> 7.58 | BO50: =ROUND(FV(0.02,8,,BN50)*-1,3) -> 8.881 | BP50: =BM50*'CALCULO GERAL'!$C$11 -> 38.04402 | BQ50: =BO50*'CALCULO GERAL'!$C$11 -> 44.573739 | BR50: =BN50*'CALCULO GERAL'!$C$11 -> 38.04402 | BS50: =BP50*N50 -> 608704.32 | BT50: =BS50-AT50 -> 164935.13 | BU50: =BR50*N50 -> 608704.32 | BV50: =BK50*N50 -> 534412.88 | BW50: =BS50-BV50 -> 74291.443 | BX50: =(((BK50*N50)-BS50)/BS50*-1) -> 0.12204849 | BY50: =ROUND(BL50,2) -> 0.74 | CE50: =CC50/BY50 -> 0 | CF50: =100%-CE50 -> 1 | CG50: =AVERAGE(CF50,CD50) -> 1
A51: JOGO DE CAMA POLIESTER 85GSM - PONTO PALITO CASAL | B51: 6302.32.00 | C51: 0.35 | D51: 0 | E51: 0.021 | F51: 0.1065 | G51: 0.0165 | H51: 0.076 | I51: 0.18 | J51: 0.04 | K51: 0.14 | L51: 0.015 | M51: N/A | N51: 16000 | T51: 3.95 | X51: =MIN(O51:W51) -> 3.95 | Y51: =AVERAGE(O51:W51) -> 3.95 | Z51: =Y51*N51 -> 63200 | AA51: ='CALCULO GERAL'!$G$10 -> 6300 | AB51: =Z51+AA51 -> 69500 | AC51: =AB51*'CALCULO GERAL'!$C$11 -> 348820.5 | AD51: =AC51*C51 -> 122087.17 | AE51: =(AC51+AD51)*D51 -> 0 | AF51: =AC51*E51 -> 7325.2305 | AG51: =AC51*F51 -> 37149.383 | AH51: 154.23 | AI51: =((AA51*'CALCULO GERAL'!$C$11))*0.08+20 -> 2549.576 | AJ51: 1010 | AK51: 2500 | AL51: =(AA51*('CALCULO GERAL'!$C$11*1.02))-(AA51*'CALCULO GERAL'!$C$11) -> 632.394 | AM51: 1800 | AN51: 2600 | AO51: 9400 | AP51: 1000 | AQ51: =-AF51 -> -7325.2305 | AR51: =-AG51 -> -37149.383 | AT51: =SUM(AC51:AS51) -> 492553.88 | AU51: =IFERROR((AT51/N51),0) -> 30.784617 | AV51: =IFERROR((BS51*'CALCULO GERAL'!$E$11)/N51,0) -> 0.8441958 | AW51: =AU51/'CALCULO GERAL'!$C$11 -> 6.1336157 | AX51: =BP51-BB51-BD51*'CALCULO GERAL'!$C$11 -> 41.576643 | AY51: =AX51*G51 -> 0.68601461 | AZ51: =AX51*H51 -> 3.1598249 | BA51: =BP51-BD51 -> 42.20979 | BB51: =BA51*L51 -> 0.63314685 | BC51: =BP51/(1+D51) -> 42.20979 | BD51: =BC51*D51 -> 0 | BE51: =BU51*0.08 -> 54028.531 | BF51: =BU51*0.12 -> 81042.797 | BG51: =(BF51*0.09)/N51 -> 0.45586573 | BH51: =(BE51*0.15)/N51 -> 0.50651748 | BI51: =IF(BE51>=$BY$1,($BY$1-BE51)*0.1,IF(BE51<=$BY$1,($BY$1*0)))/N51 -> 0 | BJ51: =(AY51+AZ51+BB51+AV51+BD51+BG51+BH51+BI51) -> 6.2855654 | BK51: =BJ51+AU51 -> 37.070183 | BL51: 0.74 | BM51: =ROUND((AW51/BL51)+((AW51*BL51)*'CALCULO GERAL'!$E$11)/BL51,2) -> 8.41 | BN51: =BM51 -> 8.41 | BO51: =ROUND(FV(0.02,8,,BN51)*-1,3) -> 9.854 | BP51: =BM51*'CALCULO GERAL'!$C$11 -> 42.20979 | BQ51: =BO51*'CALCULO GERAL'!$C$11 -> 49.457226 | BR51: =BN51*'CALCULO GERAL'!$C$11 -> 42.20979 | BS51: =BP51*N51 -> 675356.64 | BT51: =BS51-AT51 -> 182802.77 | BU51: =BR51*N51 -> 675356.64 | BV51: =BK51*N51 -> 593122.92 | BW51: =BS51-BV51 -> 82233.719 | BX51: =(((BK51*N51)-BS51)/BS51*-1) -> 0.1217634 | BY51: =ROUND(BL51,2) -> 0.74 | CE51: =CC51/BY51 -> 0 | CF51: =100%-CE51 -> 1 | CG51: =AVERAGE(CF51,CD51) -> 1
A52: JOGO DE CAMA POLIESTER 85GSM - PONTO PALITO QUEEN | B52: 6302.32.00 | C52: 0.35 | D52: 0 | E52: 0.021 | F52: 0.1065 | G52: 0.0165 | H52: 0.076 | I52: 0.18 | J52: 0.04 | K52: 0.14 | L52: 0.015 | M52: N/A | N52: 16000 | T52: 4.42 | X52: =MIN(O52:W52) -> 4.42 | Y52: =AVERAGE(O52:W52) -> 4.42 | Z52: =Y52*N52 -> 70720 | AA52: ='CALCULO GERAL'!$G$10 -> 6300 | AB52: =Z52+AA52 -> 77020 | AC52: =AB52*'CALCULO GERAL'!$C$11 -> 386563.38 | AD52: =AC52*C52 -> 135297.18 | AE52: =(AC52+AD52)*D52 -> 0 | AF52: =AC52*E52 -> 8117.831 | AG52: =AC52*F52 -> 41169 | AH52: 154.23 | AI52: =((AA52*'CALCULO GERAL'!$C$11))*0.08+20 -> 2549.576 | AJ52: 1010 | AK52: 2500 | AL52: =(AA52*('CALCULO GERAL'!$C$11*1.02))-(AA52*'CALCULO GERAL'!$C$11) -> 632.394 | AM52: 1800 | AN52: 2600 | AO52: 9400 | AP52: 1000 | AQ52: =-AF52 -> -8117.831 | AR52: =-AG52 -> -41169 | AT52: =SUM(AC52:AS52) -> 543506.76 | AU52: =IFERROR((AT52/N52),0) -> 33.969173 | AV52: =IFERROR((BS52*'CALCULO GERAL'!$E$11)/N52,0) -> 0.9315264 | AW52: =AU52/'CALCULO GERAL'!$C$11 -> 6.7681157 | AX52: =BP52-BB52-BD52*'CALCULO GERAL'!$C$11 -> 45.877675 | AY52: =AX52*G52 -> 0.75698164 | AZ52: =AX52*H52 -> 3.4867033 | BA52: =BP52-BD52 -> 46.57632 | BB52: =BA52*L52 -> 0.6986448 | BC52: =BP52/(1+D52) -> 46.57632 | BD52: =BC52*D52 -> 0 | BE52: =BU52*0.08 -> 59617.69 | BF52: =BU52*0.12 -> 89426.534 | BG52: =(BF52*0.09)/N52 -> 0.50302426 | BH52: =(BE52*0.15)/N52 -> 0.55891584 | BI52: =IF(BE52>=$BY$1,($BY$1-BE52)*0.1,IF(BE52<=$BY$1,($BY$1*0)))/N52 -> 0 | BJ52: =(AY52+AZ52+BB52+AV52+BD52+BG52+BH52+BI52) -> 6.9357963 | BK52: =BJ52+AU52 -> 40.904969 | BL52: 0.74 | BM52: =ROUND((AW52/BL52)+((AW52*BL52)*'CALCULO GERAL'!$E$11)/BL52,2) -> 9.28 | BN52: =BM52 -> 9.28 | BO52: =ROUND(FV(0.02,8,,BN52)*-1,3) -> 10.873 | BP52: =BM52*'CALCULO GERAL'!$C$11 -> 46.57632 | BQ52: =BO52*'CALCULO GERAL'!$C$11 -> 54.571587 | BR52: =BN52*'CALCULO GERAL'!$C$11 -> 46.57632 | BS52: =BP52*N52 -> 745221.12 | BT52: =BS52-AT52 -> 201714.36 | BU52: =BR52*N52 -> 745221.12 | BV52: =BK52*N52 -> 654479.5 | BW52: =BS52-BV52 -> 90741.617 | BX52: =(((BK52*N52)-BS52)/BS52*-1) -> 0.12176469 | BY52: =ROUND(BL52,2) -> 0.74 | CE52: =CC52/BY52 -> 0 | CF52: =100%-CE52 -> 1 | CG52: =AVERAGE(CF52,CD52) -> 1
A53: JOGO DE CAMA POLIESTER 85GSM - PONTO PALITO KING | B53: 6302.32.00 | C53: 0.35 | D53: 0 | E53: 0.021 | F53: 0.1065 | G53: 0.0165 | H53: 0.076 | I53: 0.18 | J53: 0.04 | K53: 0.14 | L53: 0.015 | M53: N/A | N53: 16000 | T53: 5.06 | X53: =MIN(O53:W53) -> 5.06 | Y53: =AVERAGE(O53:W53) -> 5.06 | Z53: =Y53*N53 -> 80960 | AA53: ='CALCULO GERAL'!$G$10 -> 6300 | AB53: =Z53+AA53 -> 87260 | AC53: =AB53*'CALCULO GERAL'!$C$11 -> 437957.94 | AD53: =AC53*C53 -> 153285.28 | AE53: =(AC53+AD53)*D53 -> 0 | AF53: =AC53*E53 -> 9197.1167 | AG53: =AC53*F53 -> 46642.521 | AH53: 154.23 | AI53: =((AA53*'CALCULO GERAL'!$C$11))*0.08+20 -> 2549.576 | AJ53: 1010 | AK53: 2500 | AL53: =(AA53*('CALCULO GERAL'!$C$11*1.02))-(AA53*'CALCULO GERAL'!$C$11) -> 632.394 | AM53: 1800 | AN53: 2600 | AO53: 9400 | AP53: 1000 | AQ53: =-AF53 -> -9197.1167 | AR53: =-AG53 -> -46642.521 | AT53: =SUM(AC53:AS53) -> 612889.42 | AU53: =IFERROR((AT53/N53),0) -> 38.305589 | AV53: =IFERROR((BS53*'CALCULO GERAL'!$E$11)/N53,0) -> 1.0509786 | AW53: =AU53/'CALCULO GERAL'!$C$11 -> 7.6321157 | AX53: =BP53-BB53-BD53*'CALCULO GERAL'!$C$11 -> 51.760696 | AY53: =AX53*G53 -> 0.85405148 | AZ53: =AX53*H53 -> 3.9338129 | BA53: =BP53-BD53 -> 52.54893 | BB53: =BA53*L53 -> 0.78823395 | BC53: =BP53/(1+D53) -> 52.54893 | BD53: =BC53*D53 -> 0 | BE53: =BU53*0.08 -> 67262.63 | BF53: =BU53*0.12 -> 100893.95 | BG53: =(BF53*0.09)/N53 -> 0.56752844 | BH53: =(BE53*0.15)/N53 -> 0.63058716 | BI53: =IF(BE53>=$BY$1,($BY$1-BE53)*0.1,IF(BE53<=$BY$1,($BY$1*0)))/N53 -> -0.045391503 | BJ53: =(AY53+AZ53+BB53+AV53+BD53+BG53+BH53+BI53) -> 7.779801 | BK53: =BJ53+AU53 -> 46.08539 | BL53: 0.74 | BM53: =ROUND((AW53/BL53)+((AW53*BL53)*'CALCULO GERAL'!$E$11)/BL53,2) -> 10.47 | BN53: =BM53 -> 10.47 | BO53: =ROUND(FV(0.02,8,,BN53)*-1,3) -> 12.267 | BP53: =BM53*'CALCULO GERAL'!$C$11 -> 52.54893 | BQ53: =BO53*'CALCULO GERAL'!$C$11 -> 61.568073 | BR53: =BN53*'CALCULO GERAL'!$C$11 -> 52.54893 | BS53: =BP53*N53 -> 840782.88 | BT53: =BS53-AT53 -> 227893.46 | BU53: =BR53*N53 -> 840782.88 | BV53: =BK53*N53 -> 737366.24 | BW53: =BS53-BV53 -> 103416.64 | BX53: =(((BK53*N53)-BS53)/BS53*-1) -> 0.12300042 | BY53: =ROUND(BL53,2) -> 0.74 | CE53: =CC53/BY53 -> 0 | CF53: =100%-CE53 -> 1 | CG53: =AVERAGE(CF53,CD53) -> 1
A54: JOGO DE CAMA POLIESTER 85GSM - BORDADO SOLTEIRO | B54: 6302.32.00 | C54: 0.35 | D54: 0 | E54: 0.021 | F54: 0.1065 | G54: 0.0165 | H54: 0.076 | I54: 0.18 | J54: 0.04 | K54: 0.14 | L54: 0.015 | M54: N/A | N54: 16000 | T54: 5.01 | X54: =MIN(O54:W54) -> 5.01 | Y54: =AVERAGE(O54:W54) -> 5.01 | Z54: =Y54*N54 -> 80160 | AA54: ='CALCULO GERAL'!$G$10 -> 6300 | AB54: =Z54+AA54 -> 86460 | AC54: =AB54*'CALCULO GERAL'!$C$11 -> 433942.74 | AD54: =AC54*C54 -> 151879.96 | AE54: =(AC54+AD54)*D54 -> 0 | AF54: =AC54*E54 -> 9112.7975 | AG54: =AC54*F54 -> 46214.902 | AH54: 154.23 | AI54: =((AA54*'CALCULO GERAL'!$C$11))*0.08+20 -> 2549.576 | AJ54: 1010 | AK54: 2500 | AL54: =(AA54*('CALCULO GERAL'!$C$11*1.02))-(AA54*'CALCULO GERAL'!$C$11) -> 632.394 | AM54: 1800 | AN54: 2600 | AO54: 9400 | AP54: 1000 | AQ54: =-AF54 -> -9112.7975 | AR54: =-AG54 -> -46214.902 | AT54: =SUM(AC54:AS54) -> 607468.9 | AU54: =IFERROR((AT54/N54),0) -> 37.966806 | AV54: =IFERROR((BS54*'CALCULO GERAL'!$E$11)/N54,0) -> 1.0409406 | AW54: =AU54/'CALCULO GERAL'!$C$11 -> 7.5646157 | AX54: =BP54-BB54-BD54*'CALCULO GERAL'!$C$11 -> 51.266325 | AY54: =AX54*G54 -> 0.84589436 | AZ54: =AX54*H54 -> 3.8962407 | BA54: =BP54-BD54 -> 52.04703 | BB54: =BA54*L54 -> 0.78070545 | BC54: =BP54/(1+D54) -> 52.04703 | BD54: =BC54*D54 -> 0 | BE54: =BU54*0.08 -> 66620.198 | BF54: =BU54*0.12 -> 99930.298 | BG54: =(BF54*0.09)/N54 -> 0.56210792 | BH54: =(BE54*0.15)/N54 -> 0.62456436 | BI54: =IF(BE54>=$BY$1,($BY$1-BE54)*0.1,IF(BE54<=$BY$1,($BY$1*0)))/N54 -> -0.041376302 | BJ54: =(AY54+AZ54+BB54+AV54+BD54+BG54+BH54+BI54) -> 7.7090771 | BK54: =BJ54+AU54 -> 45.675883 | BL54: 0.74 | BM54: =ROUND((AW54/BL54)+((AW54*BL54)*'CALCULO GERAL'!$E$11)/BL54,2) -> 10.37 | BN54: =BM54 -> 10.37 | BO54: =ROUND(FV(0.02,8,,BN54)*-1,3) -> 12.15 | BP54: =BM54*'CALCULO GERAL'!$C$11 -> 52.04703 | BQ54: =BO54*'CALCULO GERAL'!$C$11 -> 60.98085 | BR54: =BN54*'CALCULO GERAL'!$C$11 -> 52.04703 | BS54: =BP54*N54 -> 832752.48 | BT54: =BS54-AT54 -> 225283.58 | BU54: =BR54*N54 -> 832752.48 | BV54: =BK54*N54 -> 730814.13 | BW54: =BS54-BV54 -> 101938.35 | BX54: =(((BK54*N54)-BS54)/BS54*-1) -> 0.12241134 | BY54: =ROUND(BL54,2) -> 0.74 | CE54: =CC54/BY54 -> 0 | CF54: =100%-CE54 -> 1 | CG54: =AVERAGE(CF54,CD54) -> 1
A55: JOGO DE CAMA POLIESTER 85GSM - BORDADO CASAL | B55: 6302.32.00 | C55: 0.35 | D55: 0 | E55: 0.021 | F55: 0.1065 | G55: 0.0165 | H55: 0.076 | I55: 0.18 | J55: 0.04 | K55: 0.14 | L55: 0.015 | M55: N/A | N55: 16000 | T55: 5.58 | X55: =MIN(O55:W55) -> 5.58 | Y55: =AVERAGE(O55:W55) -> 5.58 | Z55: =Y55*N55 -> 89280 | AA55: ='CALCULO GERAL'!$G$10 -> 6300 | AB55: =Z55+AA55 -> 95580 | AC55: =AB55*'CALCULO GERAL'!$C$11 -> 479716.02 | AD55: =AC55*C55 -> 167900.61 | AE55: =(AC55+AD55)*D55 -> 0 | AF55: =AC55*E55 -> 10074.036 | AG55: =AC55*F55 -> 51089.756 | AH55: 154.23 | AI55: =((AA55*'CALCULO GERAL'!$C$11))*0.08+20 -> 2549.576 | AJ55: 1010 | AK55: 2500 | AL55: =(AA55*('CALCULO GERAL'!$C$11*1.02))-(AA55*'CALCULO GERAL'!$C$11) -> 632.394 | AM55: 1800 | AN55: 2600 | AO55: 9400 | AP55: 1000 | AQ55: =-AF55 -> -10074.036 | AR55: =-AG55 -> -51089.756 | AT55: =SUM(AC55:AS55) -> 669262.83 | AU55: =IFERROR((AT55/N55),0) -> 41.828927 | AV55: =IFERROR((BS55*'CALCULO GERAL'!$E$11)/N55,0) -> 1.1473434 | AW55: =AU55/'CALCULO GERAL'!$C$11 -> 8.3341157 | AX55: =BP55-BB55-BD55*'CALCULO GERAL'!$C$11 -> 56.506662 | AY55: =AX55*G55 -> 0.93235993 | AZ55: =AX55*H55 -> 4.2945063 | BA55: =BP55-BD55 -> 57.36717 | BB55: =BA55*L55 -> 0.86050755 | BC55: =BP55/(1+D55) -> 57.36717 | BD55: =BC55*D55 -> 0 | BE55: =BU55*0.08 -> 73429.978 | BF55: =BU55*0.12 -> 110144.97 | BG55: =(BF55*0.09)/N55 -> 0.61956544 | BH55: =(BE55*0.15)/N55 -> 0.68840604 | BI55: =IF(BE55>=$BY$1,($BY$1-BE55)*0.1,IF(BE55<=$BY$1,($BY$1*0)))/N55 -> -0.083937423 | BJ55: =(AY55+AZ55+BB55+AV55+BD55+BG55+BH55+BI55) -> 8.4587513 | BK55: =BJ55+AU55 -> 50.287678 | BL55: 0.74 | BM55: =ROUND((AW55/BL55)+((AW55*BL55)*'CALCULO GERAL'!$E$11)/BL55,2) -> 11.43 | BN55: =BM55 -> 11.43 | BO55: =ROUND(FV(0.02,8,,BN55)*-1,3) -> 13.392 | BP55: =BM55*'CALCULO GERAL'!$C$11 -> 57.36717 | BQ55: =BO55*'CALCULO GERAL'!$C$11 -> 67.214448 | BR55: =BN55*'CALCULO GERAL'!$C$11 -> 57.36717 | BS55: =BP55*N55 -> 917874.72 | BT55: =BS55-AT55 -> 248611.89 | BU55: =BR55*N55 -> 917874.72 | BV55: =BK55*N55 -> 804602.85 | BW55: =BS55-BV55 -> 113271.87 | BX55: =(((BK55*N55)-BS55)/BS55*-1) -> 0.12340668 | BY55: =ROUND(BL55,2) -> 0.74 | CE55: =CC55/BY55 -> 0 | CF55: =100%-CE55 -> 1 | CG55: =AVERAGE(CF55,CD55) -> 1
A56: JOGO DE CAMA POLIESTER 85GSM - BORDADO QUEEN | B56: 6302.32.00 | C56: 0.35 | D56: 0 | E56: 0.021 | F56: 0.1065 | G56: 0.0165 | H56: 0.076 | I56: 0.18 | J56: 0.04 | K56: 0.14 | L56: 0.015 | M56: N/A | N56: 16000 | T56: 6.19 | X56: =MIN(O56:W56) -> 6.19 | Y56: =AVERAGE(O56:W56) -> 6.19 | Z56: =Y56*N56 -> 99040 | AA56: ='CALCULO GERAL'!$G$10 -> 6300 | AB56: =Z56+AA56 -> 105340 | AC56: =AB56*'CALCULO GERAL'!$C$11 -> 528701.46 | AD56: =AC56*C56 -> 185045.51 | AE56: =(AC56+AD56)*D56 -> 0 | AF56: =AC56*E56 -> 11102.731 | AG56: =AC56*F56 -> 56306.705 | AH56: 154.23 | AI56: =((AA56*'CALCULO GERAL'!$C$11))*0.08+20 -> 2549.576 | AJ56: 1010 | AK56: 2500 | AL56: =(AA56*('CALCULO GERAL'!$C$11*1.02))-(AA56*'CALCULO GERAL'!$C$11) -> 632.394 | AM56: 1800 | AN56: 2600 | AO56: 9400 | AP56: 1000 | AQ56: =-AF56 -> -11102.731 | AR56: =-AG56 -> -56306.705 | AT56: =SUM(AC56:AS56) -> 735393.17 | AU56: =IFERROR((AT56/N56),0) -> 45.962073 | AV56: =IFERROR((BS56*'CALCULO GERAL'!$E$11)/N56,0) -> 1.2607728 | AW56: =AU56/'CALCULO GERAL'!$C$11 -> 9.1576157 | AX56: =BP56-BB56-BD56*'CALCULO GERAL'!$C$11 -> 62.09306 | AY56: =AX56*G56 -> 1.0245355 | AZ56: =AX56*H56 -> 4.7190726 | BA56: =BP56-BD56 -> 63.03864 | BB56: =BA56*L56 -> 0.9455796 | BC56: =BP56/(1+D56) -> 63.03864 | BD56: =BC56*D56 -> 0 | BE56: =BU56*0.08 -> 80689.459 | BF56: =BU56*0.12 -> 121034.19 | BG56: =(BF56*0.09)/N56 -> 0.68081731 | BH56: =(BE56*0.15)/N56 -> 0.75646368 | BI56: =IF(BE56>=$BY$1,($BY$1-BE56)*0.1,IF(BE56<=$BY$1,($BY$1*0)))/N56 -> -0.12930918 | BJ56: =(AY56+AZ56+BB56+AV56+BD56+BG56+BH56+BI56) -> 9.2579323 | BK56: =BJ56+AU56 -> 55.220005 | BL56: 0.74 | BM56: =ROUND((AW56/BL56)+((AW56*BL56)*'CALCULO GERAL'!$E$11)/BL56,2) -> 12.56 | BN56: =BM56 -> 12.56 | BO56: =ROUND(FV(0.02,8,,BN56)*-1,3) -> 14.716 | BP56: =BM56*'CALCULO GERAL'!$C$11 -> 63.03864 | BQ56: =BO56*'CALCULO GERAL'!$C$11 -> 73.859604 | BR56: =BN56*'CALCULO GERAL'!$C$11 -> 63.03864 | BS56: =BP56*N56 -> 1008618.2 | BT56: =BS56-AT56 -> 273225.07 | BU56: =BR56*N56 -> 1008618.2 | BV56: =BK56*N56 -> 883520.09 | BW56: =BS56-BV56 -> 125098.15 | BX56: =(((BK56*N56)-BS56)/BS56*-1) -> 0.12402924 | BY56: =ROUND(BL56,2) -> 0.74 | CE56: =CC56/BY56 -> 0 | CF56: =100%-CE56 -> 1 | CG56: =AVERAGE(CF56,CD56) -> 1
A57: JOGO DE CAMA POLIESTER 85GSM - BORDADO KING | B57: 6302.32.00 | C57: 0.35 | D57: 0 | E57: 0.021 | F57: 0.1065 | G57: 0.0165 | H57: 0.076 | I57: 0.18 | J57: 0.04 | K57: 0.14 | L57: 0.015 | M57: N/A | N57: 16000 | T57: 6.98 | X57: =MIN(O57:W57) -> 6.98 | Y57: =AVERAGE(O57:W57) -> 6.98 | Z57: =Y57*N57 -> 111680 | AA57: ='CALCULO GERAL'!$G$10 -> 6300 | AB57: =Z57+AA57 -> 117980 | AC57: =AB57*'CALCULO GERAL'!$C$11 -> 592141.62 | AD57: =AC57*C57 -> 207249.57 | AE57: =(AC57+AD57)*D57 -> 0 | AF57: =AC57*E57 -> 12434.974 | AG57: =AC57*F57 -> 63063.083 | AH57: 154.23 | AI57: =((AA57*'CALCULO GERAL'!$C$11))*0.08+20 -> 2549.576 | AJ57: 1010 | AK57: 2500 | AL57: =(AA57*('CALCULO GERAL'!$C$11*1.02))-(AA57*'CALCULO GERAL'!$C$11) -> 632.394 | AM57: 1800 | AN57: 2600 | AO57: 9400 | AP57: 1000 | AQ57: =-AF57 -> -12434.974 | AR57: =-AG57 -> -63063.083 | AT57: =SUM(AC57:AS57) -> 821037.39 | AU57: =IFERROR((AT57/N57),0) -> 51.314837 | AV57: =IFERROR((BS57*'CALCULO GERAL'!$E$11)/N57,0) -> 1.4073276 | AW57: =AU57/'CALCULO GERAL'!$C$11 -> 10.224116 | AX57: =BP57-BB57-BD57*'CALCULO GERAL'!$C$11 -> 69.310884 | AY57: =AX57*G57 -> 1.1436296 | AZ57: =AX57*H57 -> 5.2676272 | BA57: =BP57-BD57 -> 70.36638 | BB57: =BA57*L57 -> 1.0554957 | BC57: =BP57/(1+D57) -> 70.36638 | BD57: =BC57*D57 -> 0 | BE57: =BU57*0.08 -> 90068.966 | BF57: =BU57*0.12 -> 135103.45 | BG57: =(BF57*0.09)/N57 -> 0.7599569 | BH57: =(BE57*0.15)/N57 -> 0.84439656 | BI57: =IF(BE57>=$BY$1,($BY$1-BE57)*0.1,IF(BE57<=$BY$1,($BY$1*0)))/N57 -> -0.1879311 | BJ57: =(AY57+AZ57+BB57+AV57+BD57+BG57+BH57+BI57) -> 10.290502 | BK57: =BJ57+AU57 -> 61.605339 | BL57: 0.74 | BM57: =ROUND((AW57/BL57)+((AW57*BL57)*'CALCULO GERAL'!$E$11)/BL57,2) -> 14.02 | BN57: =BM57 -> 14.02 | BO57: =ROUND(FV(0.02,8,,BN57)*-1,3) -> 16.427 | BP57: =BM57*'CALCULO GERAL'!$C$11 -> 70.36638 | BQ57: =BO57*'CALCULO GERAL'!$C$11 -> 82.447113 | BR57: =BN57*'CALCULO GERAL'!$C$11 -> 70.36638 | BS57: =BP57*N57 -> 1125862.1 | BT57: =BS57-AT57 -> 304824.69 | BU57: =BR57*N57 -> 1125862.1 | BV57: =BK57*N57 -> 985685.43 | BW57: =BS57-BV57 -> 140176.65 | BX57: =(((BK57*N57)-BS57)/BS57*-1) -> 0.12450606 | BY57: =ROUND(BL57,2) -> 0.74 | CE57: =CC57/BY57 -> 0 | CF57: =100%-CE57 -> 1 | CG57: =AVERAGE(CF57,CD57) -> 1
... A69: JOGO DE CAMA POLIESTER 90GSM - PONTO PALITO KING | B69: 6302.32.00 | C69: 0.35 | D69: 0 | E69: 0.021 | F69: 0.1065 | G69: 0.0165 | H69: 0.076 | I69: 0.18 | J69: 0.04 | K69: 0.14 | L69: 0.015 | M69: N/A | N69: 7000 | T69: 5.414 | X69: =MIN(O69:W69) -> 5.414 | Y69: =AVERAGE(O69:W69) -> 5.414 | Z69: =Y69*N69 -> 37898 | AA69: ='CALCULO GERAL'!$G$10 -> 6300 | AB69: =Z69+AA69 -> 44198 | AC69: =AB69*'CALCULO GERAL'!$C$11 -> 221829.76 | AD69: =AC69*C69 -> 77640.417 | AE69: =(AC69+AD69)*D69 -> 0 | AF69: =AC69*E69 -> 4658.425 | AG69: =AC69*F69 -> 23624.87 | AH69: 154.23 | AI69: =((AA69*'CALCULO GERAL'!$C$11))*0.08+20 -> 2549.576 | AJ69: 1010 | AK69: 2500 | AL69: =(AA69*('CALCULO GERAL'!$C$11*1.02))-(AA69*'CALCULO GERAL'!$C$11) -> 632.394 | AM69: 1800 | AN69: 2600 | AO69: 9400 | AP69: 1000 | AQ69: =-AF69 -> -4658.425 | AR69: =-AG69 -> -23624.87 | AT69: =SUM(AC69:AS69) -> 321116.38 | AU69: =IFERROR((AT69/N69),0) -> 45.873768 | AV69: =IFERROR((BS69*'CALCULO GERAL'!$E$11)/N69,0) -> 1.2577614 | AW69: =AU69/'CALCULO GERAL'!$C$11 -> 9.1400216 | AX69: =BP69-BB69-BD69*'CALCULO GERAL'!$C$11 -> 61.944749 | AY69: =AX69*G69 -> 1.0220884 | AZ69: =AX69*H69 -> 4.7078009 | BA69: =BP69-BD69 -> 62.88807 | BB69: =BA69*L69 -> 0.94332105 | BC69: =BP69/(1+D69) -> 62.88807 | BD69: =BC69*D69 -> 0 | BE69: =BU69*0.08 -> 35217.319 | BF69: =BU69*0.12 -> 52825.979 | BG69: =(BF69*0.09)/N69 -> 0.67919116 | BH69: =(BE69*0.15)/N69 -> 0.75465684 | BI69: =IF(BE69>=$BY$1,($BY$1-BE69)*0.1,IF(BE69<=$BY$1,($BY$1*0)))/N69 -> 0 | BJ69: =(AY69+AZ69+BB69+AV69+BD69+BG69+BH69+BI69) -> 9.3648197 | BK69: =BJ69+AU69 -> 55.238588 | BL69: 0.74 | BM69: =ROUND((AW69/BL69)+((AW69*BL69)*'CALCULO GERAL'!$E$11)/BL69,2) -> 12.53 | BN69: =BM69 -> 12.53 | BO69: =ROUND(FV(0.02,8,,BN69)*-1,3) -> 14.681 | BP69: =BM69*'CALCULO GERAL'!$C$11 -> 62.88807 | BQ69: =BO69*'CALCULO GERAL'!$C$11 -> 73.683939 | BR69: =BN69*'CALCULO GERAL'!$C$11 -> 62.88807 | BS69: =BP69*N69 -> 440216.49 | BT69: =BS69-AT69 -> 119100.11 | BU69: =BR69*N69 -> 440216.49 | BV69: =BK69*N69 -> 386670.12 | BW69: =BS69-BV69 -> 53546.373 | BX69: =(((BK69*N69)-BS69)/BS69*-1) -> 0.12163645 | BY69: =ROUND(BL69,2) -> 0.74 | CE69: =CC69/BY69 -> 0 | CF69: =100%-CE69 -> 1 | CG69: =AVERAGE(CF69,CD69) -> 1
A70: JOGO DE CAMA POLIESTER 90GSM SOLTEIRO | B70: 6302.32.00 | C70: 0.35 | D70: 0 | E70: 0.021 | F70: 0.1065 | G70: 0.0165 | H70: 0.076 | I70: 0.18 | J70: 0.04 | K70: 0.14 | L70: 0.015 | M70: N/A | N70: 16000 | U70: 3.92 | X70: =MIN(O70:W70) -> 3.92 | Y70: =AVERAGE(O70:W70) -> 3.92 | Z70: =Y70*N70 -> 62720 | AA70: ='CALCULO GERAL'!$G$10 -> 6300 | AB70: =Z70+AA70 -> 69020 | AC70: =AB70*'CALCULO GERAL'!$C$11 -> 346411.38 | AD70: =AC70*C70 -> 121243.98 | AE70: =(AC70+AD70)*D70 -> 0 | AF70: =AC70*E70 -> 7274.639 | AG70: =AC70*F70 -> 36892.812 | AH70: 154.23 | AI70: =((AA70*'CALCULO GERAL'!$C$11))*0.08+20 -> 2549.576 | AJ70: 1010 | AK70: 2500 | AL70: =(AA70*('CALCULO GERAL'!$C$11*1.02))-(AA70*'CALCULO GERAL'!$C$11) -> 632.394 | AM70: 1800 | AN70: 2600 | AO70: 9400 | AP70: 1000 | AQ70: =-AF70 -> -7274.639 | AR70: =-AG70 -> -36892.812 | AT70: =SUM(AC70:AS70) -> 489301.56 | AU70: =IFERROR((AT70/N70),0) -> 30.581348 | AV70: =IFERROR((BS70*'CALCULO GERAL'!$E$11)/N70,0) -> 0.8391768 | AW70: =AU70/'CALCULO GERAL'!$C$11 -> 6.0931157 | AX70: =BP70-BB70-BD70*'CALCULO GERAL'!$C$11 -> 41.329457 | AY70: =AX70*G70 -> 0.68193605 | AZ70: =AX70*H70 -> 3.1410388 | BA70: =BP70-BD70 -> 41.95884 | BB70: =BA70*L70 -> 0.6293826 | BC70: =BP70/(1+D70) -> 41.95884 | BD70: =BC70*D70 -> 0 | BE70: =BU70*0.08 -> 53707.315 | BF70: =BU70*0.12 -> 80560.973 | BG70: =(BF70*0.09)/N70 -> 0.45315547 | BH70: =(BE70*0.15)/N70 -> 0.50350608 | BI70: =IF(BE70>=$BY$1,($BY$1-BE70)*0.1,IF(BE70<=$BY$1,($BY$1*0)))/N70 -> 0 | BJ70: =(AY70+AZ70+BB70+AV70+BD70+BG70+BH70+BI70) -> 6.2481958 | BK70: =BJ70+AU70 -> 36.829543 | BL70: 0.74 | BM70: =ROUND((AW70/BL70)+((AW70*BL70)*'CALCULO GERAL'!$E$11)/BL70,2) -> 8.36 | BN70: =BM70 -> 8.36 | BO70: =ROUND(FV(0.02,8,,BN70)*-1,3) -> 9.795 | BP70: =BM70*'CALCULO GERAL'!$C$11 -> 41.95884 | BQ70: =BO70*'CALCULO GERAL'!$C$11 -> 49.161105 | BR70: =BN70*'CALCULO GERAL'!$C$11 -> 41.95884 | BS70: =BP70*N70 -> 671341.44 | BT70: =BS70-AT70 -> 182039.88 | BU70: =BR70*N70 -> 671341.44 | BV70: =BK70*N70 -> 589272.7 | BW70: =BS70-BV70 -> 82068.745 | BX70: =(((BK70*N70)-BS70)/BS70*-1) -> 0.12224591 | BY70: =ROUND(BL70,2) -> 0.74 | CE70: =CC70/BY70 -> 0 | CF70: =100%-CE70 -> 1 | CG70: =AVERAGE(CF70,CD70) -> 1
A71: JOGO DE CAMA POLIESTER 90GSM CASAL | B71: 6302.32.00 | C71: 0.35 | D71: 0 | E71: 0.021 | F71: 0.1065 | G71: 0.0165 | H71: 0.076 | I71: 0.18 | J71: 0.04 | K71: 0.14 | L71: 0.015 | M71: N/A | N71: 14500 | U71: 5.34 | X71: =MIN(O71:W71) -> 5.34 | Y71: =AVERAGE(O71:W71) -> 5.34 | Z71: =Y71*N71 -> 77430 | AA71: ='CALCULO GERAL'!$G$10 -> 6300 | AB71: =Z71+AA71 -> 83730 | AC71: =AB71*'CALCULO GERAL'!$C$11 -> 420240.87 | AD71: =AC71*C71 -> 147084.3 | AE71: =(AC71+AD71)*D71 -> 0 | AF71: =AC71*E71 -> 8825.0583 | AG71: =AC71*F71 -> 44755.653 | AH71: 154.23 | AI71: =((AA71*'CALCULO GERAL'!$C$11))*0.08+20 -> 2549.576 | AJ71: 1010 | AK71: 2500 | AL71: =(AA71*('CALCULO GERAL'!$C$11*1.02))-(AA71*'CALCULO GERAL'!$C$11) -> 632.394 | AM71: 1800 | AN71: 2600 | AO71: 9400 | AP71: 1000 | AQ71: =-AF71 -> -8825.0583 | AR71: =-AG71 -> -44755.653 | AT71: =SUM(AC71:AS71) -> 588971.37 | AU71: =IFERROR((AT71/N71),0) -> 40.618715 | AV71: =IFERROR((BS71*'CALCULO GERAL'!$E$11)/N71,0) -> 1.114218 | AW71: =AU71/'CALCULO GERAL'!$C$11 -> 8.0929897 | AX71: =BP71-BB71-BD71*'CALCULO GERAL'!$C$11 -> 54.875236 | AY71: =AX71*G71 -> 0.9054414 | AZ71: =AX71*H71 -> 4.170518 | BA71: =BP71-BD71 -> 55.7109 | BB71: =BA71*L71 -> 0.8356635 | BC71: =BP71/(1+D71) -> 55.7109 | BD71: =BC71*D71 -> 0 | BE71: =BU71*0.08 -> 64624.644 | BF71: =BU71*0.12 -> 96936.966 | BG71: =(BF71*0.09)/N71 -> 0.60167772 | BH71: =(BE71*0.15)/N71 -> 0.6685308 | BI71: =IF(BE71>=$BY$1,($BY$1-BE71)*0.1,IF(BE71<=$BY$1,($BY$1*0)))/N71 -> -0.031894166 | BJ71: =(AY71+AZ71+BB71+AV71+BD71+BG71+BH71+BI71) -> 8.2641552 | BK71: =BJ71+AU71 -> 48.882871 | BL71: 0.74 | BM71: =ROUND((AW71/BL71)+((AW71*BL71)*'CALCULO GERAL'!$E$11)/BL71,2) -> 11.1 | BN71: =BM71 -> 11.1 | BO71: =ROUND(FV(0.02,8,,BN71)*-1,3) -> 13.005 | BP71: =BM71*'CALCULO GERAL'!$C$11 -> 55.7109 | BQ71: =BO71*'CALCULO GERAL'!$C$11 -> 65.272095 | BR71: =BN71*'CALCULO GERAL'!$C$11 -> 55.7109 | BS71: =BP71*N71 -> 807808.05 | BT71: =BS71-AT71 -> 218836.68 | BU71: =BR71*N71 -> 807808.05 | BV71: =BK71*N71 -> 708801.63 | BW71: =BS71-BV71 -> 99006.425 | BX71: =(((BK71*N71)-BS71)/BS71*-1) -> 0.12256182 | BY71: =ROUND(BL71,2) -> 0.74 | CE71: =CC71/BY71 -> 0 | CF71: =100%-CE71 -> 1 | CG71: =AVERAGE(CF71,CD71) -> 1
A72: JOGO DE CAMA POLIESTER 90GSM QUEEN | B72: 6302.32.00 | C72: 0.35 | D72: 0 | E72: 0.021 | F72: 0.1065 | G72: 0.0165 | H72: 0.076 | I72: 0.18 | J72: 0.04 | K72: 0.14 | L72: 0.015 | M72: N/A | N72: 12500 | U72: 5.92 | X72: =MIN(O72:W72) -> 5.92 | Y72: =AVERAGE(O72:W72) -> 5.92 | Z72: =Y72*N72 -> 74000 | AA72: ='CALCULO GERAL'!$G$10 -> 6300 | AB72: =Z72+AA72 -> 80300 | AC72: =AB72*'CALCULO GERAL'!$C$11 -> 403025.7 | AD72: =AC72*C72 -> 141058.99 | AE72: =(AC72+AD72)*D72 -> 0 | AF72: =AC72*E72 -> 8463.5397 | AG72: =AC72*F72 -> 42922.237 | AH72: 154.23 | AI72: =((AA72*'CALCULO GERAL'!$C$11))*0.08+20 -> 2549.576 | AJ72: 1010 | AK72: 2500 | AL72: =(AA72*('CALCULO GERAL'!$C$11*1.02))-(AA72*'CALCULO GERAL'!$C$11) -> 632.394 | AM72: 1800 | AN72: 2600 | AO72: 9400 | AP72: 1000 | AQ72: =-AF72 -> -8463.5397 | AR72: =-AG72 -> -42922.237 | AT72: =SUM(AC72:AS72) -> 565730.9 | AU72: =IFERROR((AT72/N72),0) -> 45.258472 | AV72: =IFERROR((BS72*'CALCULO GERAL'!$E$11)/N72,0) -> 1.2417006 | AW72: =AU72/'CALCULO GERAL'!$C$11 -> 9.0174281 | AX72: =BP72-BB72-BD72*'CALCULO GERAL'!$C$11 -> 61.153755 | AY72: =AX72*G72 -> 1.009037 | AZ72: =AX72*H72 -> 4.6476853 | BA72: =BP72-BD72 -> 62.08503 | BB72: =BA72*L72 -> 0.93127545 | BC72: =BP72/(1+D72) -> 62.08503 | BD72: =BC72*D72 -> 0 | BE72: =BU72*0.08 -> 62085.03 | BF72: =BU72*0.12 -> 93127.545 | BG72: =(BF72*0.09)/N72 -> 0.67051832 | BH72: =(BE72*0.15)/N72 -> 0.74502036 | BI72: =IF(BE72>=$BY$1,($BY$1-BE72)*0.1,IF(BE72<=$BY$1,($BY$1*0)))/N72 -> -0.01668032 | BJ72: =(AY72+AZ72+BB72+AV72+BD72+BG72+BH72+BI72) -> 9.2285567 | BK72: =BJ72+AU72 -> 54.487028 | BL72: 0.74 | BM72: =ROUND((AW72/BL72)+((AW72*BL72)*'CALCULO GERAL'!$E$11)/BL72,2) -> 12.37 | BN72: =BM72 -> 12.37 | BO72: =ROUND(FV(0.02,8,,BN72)*-1,3) -> 14.493 | BP72: =BM72*'CALCULO GERAL'!$C$11 -> 62.08503 | BQ72: =BO72*'CALCULO GERAL'!$C$11 -> 72.740367 | BR72: =BN72*'CALCULO GERAL'!$C$11 -> 62.08503 | BS72: =BP72*N72 -> 776062.88 | BT72: =BS72-AT72 -> 210331.98 | BU72: =BR72*N72 -> 776062.88 | BV72: =BK72*N72 -> 681087.85 | BW72: =BS72-BV72 -> 94975.021 | BX72: =(((BK72*N72)-BS72)/BS72*-1) -> 0.12238058 | BY72: =ROUND(BL72,2) -> 0.74 | CE72: =CC72/BY72 -> 0 | CF72: =100%-CE72 -> 1 | CG72: =AVERAGE(CF72,CD72) -> 1
A73: JOGO DE CAMA POLIESTER 90GSM KING | B73: 6302.32.00 | C73: 0.35 | D73: 0 | E73: 0.021 | F73: 0.1065 | G73: 0.0165 | H73: 0.076 | I73: 0.18 | J73: 0.04 | K73: 0.14 | L73: 0.015 | M73: N/A | N73: 10500 | U73: 6.71 | X73: =MIN(O73:W73) -> 6.71 | Y73: =AVERAGE(O73:W73) -> 6.71 | Z73: =Y73*N73 -> 70455 | AA73: ='CALCULO GERAL'!$G$10 -> 6300 | AB73: =Z73+AA73 -> 76755 | AC73: =AB73*'CALCULO GERAL'!$C$11 -> 385233.35 | AD73: =AC73*C73 -> 134831.67 | AE73: =(AC73+AD73)*D73 -> 0 | AF73: =AC73*E73 -> 8089.9002 | AG73: =AC73*F73 -> 41027.351 | AH73: 154.23 | AI73: =((AA73*'CALCULO GERAL'!$C$11))*0.08+20 -> 2549.576 | AJ73: 1010 | AK73: 2500 | AL73: =(AA73*('CALCULO GERAL'!$C$11*1.02))-(AA73*'CALCULO GERAL'!$C$11) -> 632.394 | AM73: 1800 | AN73: 2600 | AO73: 9400 | AP73: 1000 | AQ73: =-AF73 -> -8089.9002 | AR73: =-AG73 -> -41027.351 | AT73: =SUM(AC73:AS73) -> 541711.22 | AU73: =IFERROR((AT73/N73),0) -> 51.591544 | AV73: =IFERROR((BS73*'CALCULO GERAL'!$E$11)/N73,0) -> 1.415358 | AW73: =AU73/'CALCULO GERAL'!$C$11 -> 10.279248 | AX73: =BP73-BB73-BD73*'CALCULO GERAL'!$C$11 -> 69.706381 | AY73: =AX73*G73 -> 1.1501553 | AZ73: =AX73*H73 -> 5.297685 | BA73: =BP73-BD73 -> 70.7679 | BB73: =BA73*L73 -> 1.0615185 | BC73: =BP73/(1+D73) -> 70.7679 | BD73: =BC73*D73 -> 0 | BE73: =BU73*0.08 -> 59445.036 | BF73: =BU73*0.12 -> 89167.554 | BG73: =(BF73*0.09)/N73 -> 0.76429332 | BH73: =(BE73*0.15)/N73 -> 0.8492148 | BI73: =IF(BE73>=$BY$1,($BY$1-BE73)*0.1,IF(BE73<=$BY$1,($BY$1*0)))/N73 -> 0 | BJ73: =(AY73+AZ73+BB73+AV73+BD73+BG73+BH73+BI73) -> 10.538225 | BK73: =BJ73+AU73 -> 62.129769 | BL73: 0.74 | BM73: =ROUND((AW73/BL73)+((AW73*BL73)*'CALCULO GERAL'!$E$11)/BL73,2) -> 14.1 | BN73: =BM73 -> 14.1 | BO73: =ROUND(FV(0.02,8,,BN73)*-1,3) -> 16.52 | BP73: =BM73*'CALCULO GERAL'!$C$11 -> 70.7679 | BQ73: =BO73*'CALCULO GERAL'!$C$11 -> 82.91388 | BR73: =BN73*'CALCULO GERAL'!$C$11 -> 70.7679 | BS73: =BP73*N73 -> 743062.95 | BT73: =BS73-AT73 -> 201351.73 | BU73: =BR73*N73 -> 743062.95 | BV73: =BK73*N73 -> 652362.58 | BW73: =BS73-BV73 -> 90700.373 | BX73: =(((BK73*N73)-BS73)/BS73*-1) -> 0.12206284 | BY73: =ROUND(BL73,2) -> 0.74 | CE73: =CC73/BY73 -> 0 | CF73: =100%-CE73 -> 1 | CG73: =AVERAGE(CF73,CD73) -> 1
A74: JOGO DE CAMA PERCAL 400 FIOS LISOSOLTEIRO | B74: 6302.22.00 | C74: 0.35 | D74: 0 | E74: 0.021 | F74: 0.1065 | G74: 0.0165 | H74: 0.076 | I74: 0.18 | J74: 0.04 | K74: 0.14 | L74: 0.015 | M74: N/A | N74: 10500 | V74: 15.36 | X74: =MIN(O74:W74) -> 15.36 | Y74: =AVERAGE(O74:W74) -> 15.36 | Z74: =Y74*N74 -> 161280 | AA74: ='CALCULO GERAL'!$G$10 -> 6300 | AB74: =Z74+AA74 -> 167580 | AC74: =AB74*'CALCULO GERAL'!$C$11 -> 841084.02 | AD74: =AC74*C74 -> 294379.41 | AE74: =(AC74+AD74)*D74 -> 0 | AF74: =AC74*E74 -> 17662.764 | AG74: =AC74*F74 -> 89575.448 | AH74: 154.23 | AI74: =((AA74*'CALCULO GERAL'!$C$11))*0.08+20 -> 2549.576 | AJ74: 1010 | AK74: 2500 | AL74: =(AA74*('CALCULO GERAL'!$C$11*1.02))-(AA74*'CALCULO GERAL'!$C$11) -> 632.394 | AM74: 1800 | AN74: 2600 | AO74: 9400 | AP74: 1000 | AQ74: =-AF74 -> -17662.764 | AR74: =-AG74 -> -89575.448 | AT74: =SUM(AC74:AS74) -> 1157109.6 | AU74: =IFERROR((AT74/N74),0) -> 110.20092 | AV74: =IFERROR((BS74*'CALCULO GERAL'!$E$11)/N74,0) -> 3.0224418 | AW74: =AU74/'CALCULO GERAL'!$C$11 -> 21.956748 | AX74: =BP74-BB74-BD74*'CALCULO GERAL'!$C$11 -> 148.85526 | AY74: =AX74*G74 -> 2.4561118 | AZ74: =AX74*H74 -> 11.313 | BA74: =BP74-BD74 -> 151.12209 | BB74: =BA74*L74 -> 2.2668313 | BC74: =BP74/(1+D74) -> 151.12209 | BD74: =BC74*D74 -> 0 | BE74: =BU74*0.08 -> 126942.56 | BF74: =BU74*0.12 -> 190413.83 | BG74: =(BF74*0.09)/N74 -> 1.6321186 | BH74: =(BE74*0.15)/N74 -> 1.8134651 | BI74: =IF(BE74>=$BY$1,($BY$1-BE74)*0.1,IF(BE74<=$BY$1,($BY$1*0)))/N74 -> -0.63754824 | BJ74: =(AY74+AZ74+BB74+AV74+BD74+BG74+BH74+BI74) -> 21.86642 | BK74: =BJ74+AU74 -> 132.06734 | BL74: 0.74 | BM74: =ROUND((AW74/BL74)+((AW74*BL74)*'CALCULO GERAL'!$E$11)/BL74,2) -> 30.11 | BN74: =BM74 -> 30.11 | BO74: =ROUND(FV(0.02,8,,BN74)*-1,3) -> 35.279 | BP74: =BM74*'CALCULO GERAL'!$C$11 -> 151.12209 | BQ74: =BO74*'CALCULO GERAL'!$C$11 -> 177.0653 | BR74: =BN74*'CALCULO GERAL'!$C$11 -> 151.12209 | BS74: =BP74*N74 -> 1586781.9 | BT74: =BS74-AT74 -> 429672.32 | BU74: =BR74*N74 -> 1586781.9 | BV74: =BK74*N74 -> 1386707 | BW74: =BS74-BV74 -> 200074.91 | BX74: =(((BK74*N74)-BS74)/BS74*-1) -> 0.12608847 | BY74: =ROUND(BL74,2) -> 0.74 | CE74: =CC74/BY74 -> 0 | CF74: =100%-CE74 -> 1 | CG74: =AVERAGE(CF74,CD74) -> 1
A75: JOGO DE CAMA PERCAL 400 FIOS LISOCASAL | B75: 6302.22.00 | C75: 0.35 | D75: 0 | E75: 0.021 | F75: 0.1065 | G75: 0.0165 | H75: 0.076 | I75: 0.18 | J75: 0.04 | K75: 0.14 | L75: 0.015 | M75: N/A | N75: 8500 | V75: 20.86 | X75: =MIN(O75:W75) -> 20.86 | Y75: =AVERAGE(O75:W75) -> 20.86 | Z75: =Y75*N75 -> 177310 | AA75: ='CALCULO GERAL'!$G$10 -> 6300 | AB75: =Z75+AA75 -> 183610 | AC75: =AB75*'CALCULO GERAL'!$C$11 -> 921538.59 | AD75: =AC75*C75 -> 322538.51 | AE75: =(AC75+AD75)*D75 -> 0 | AF75: =AC75*E75 -> 19352.31 | AG75: =AC75*F75 -> 98143.86 | AH75: 154.23 | AI75: =((AA75*'CALCULO GERAL'!$C$11))*0.08+20 -> 2549.576 | AJ75: 1010 | AK75: 2500 | AL75: =(AA75*('CALCULO GERAL'!$C$11*1.02))-(AA75*'CALCULO GERAL'!$C$11) -> 632.394 | AM75: 1800 | AN75: 2600 | AO75: 9400 | AP75: 1000 | AQ75: =-AF75 -> -19352.31 | AR75: =-AG75 -> -98143.86 | AT75: =SUM(AC75:AS75) -> 1265723.3 | AU75: =IFERROR((AT75/N75),0) -> 148.90862 | AV75: =IFERROR((BS75*'CALCULO GERAL'!$E$11)/N75,0) -> 4.0844622 | AW75: =AU75/'CALCULO GERAL'!$C$11 -> 29.668982 | AX75: =BP75-BB75-BD75*'CALCULO GERAL'!$C$11 -> 201.15976 | AY75: =AX75*G75 -> 3.3191361 | AZ75: =AX75*H75 -> 15.288142 | BA75: =BP75-BD75 -> 204.22311 | BB75: =BA75*L75 -> 3.0633466 | BC75: =BP75/(1+D75) -> 204.22311 | BD75: =BC75*D75 -> 0 | BE75: =BU75*0.08 -> 138871.71 | BF75: =BU75*0.12 -> 208307.57 | BG75: =(BF75*0.09)/N75 -> 2.2056096 | BH75: =(BE75*0.15)/N75 -> 2.4506773 | BI75: =IF(BE75>=$BY$1,($BY$1-BE75)*0.1,IF(BE75<=$BY$1,($BY$1*0)))/N75 -> -0.92790264 | BJ75: =(AY75+AZ75+BB75+AV75+BD75+BG75+BH75+BI75) -> 29.483471 | BK75: =BJ75+AU75 -> 178.39209 | BL75: 0.74 | BM75: =ROUND((AW75/BL75)+((AW75*BL75)*'CALCULO GERAL'!$E$11)/BL75,2) -> 40.69 | BN75: =BM75 -> 40.69 | BO75: =ROUND(FV(0.02,8,,BN75)*-1,3) -> 47.675 | BP75: =BM75*'CALCULO GERAL'!$C$11 -> 204.22311 | BQ75: =BO75*'CALCULO GERAL'!$C$11 -> 239.28082 | BR75: =BN75*'CALCULO GERAL'!$C$11 -> 204.22311 | BS75: =BP75*N75 -> 1735896.4 | BT75: =BS75-AT75 -> 470173.14 | BU75: =BR75*N75 -> 1735896.4 | BV75: =BK75*N75 -> 1516332.8 | BW75: =BS75-BV75 -> 219563.63 | BX75: =(((BK75*N75)-BS75)/BS75*-1) -> 0.12648429 | BY75: =ROUND(BL75,2) -> 0.74 | CE75: =CC75/BY75 -> 0 | CF75: =100%-CE75 -> 1 | CG75: =AVERAGE(CF75,CD75) -> 1
A76: JOGO DE CAMA PERCAL 400 FIOS LISOQUEEN | B76: 6302.22.00 | C76: 0.35 | D76: 0 | E76: 0.021 | F76: 0.1065 | G76: 0.0165 | H76: 0.076 | I76: 0.18 | J76: 0.04 | K76: 0.14 | L76: 0.015 | M76: N/A | N76: 7000 | V76: 22.29 | X76: =MIN(O76:W76) -> 22.29 | Y76: =AVERAGE(O76:W76) -> 22.29 | Z76: =Y76*N76 -> 156030 | AA76: ='CALCULO GERAL'!$G$10 -> 6300 | AB76: =Z76+AA76 -> 162330 | AC76: =AB76*'CALCULO GERAL'!$C$11 -> 814734.27 | AD76: =AC76*C76 -> 285156.99 | AE76: =(AC76+AD76)*D76 -> 0 | AF76: =AC76*E76 -> 17109.42 | AG76: =AC76*F76 -> 86769.2 | AH76: 154.23 | AI76: =((AA76*'CALCULO GERAL'!$C$11))*0.08+20 -> 2549.576 | AJ76: 1010 | AK76: 2500 | AL76: =(AA76*('CALCULO GERAL'!$C$11*1.02))-(AA76*'CALCULO GERAL'!$C$11) -> 632.394 | AM76: 1800 | AN76: 2600 | AO76: 9400 | AP76: 1000 | AQ76: =-AF76 -> -17109.42 | AR76: =-AG76 -> -86769.2 | AT76: =SUM(AC76:AS76) -> 1121537.5 | AU76: =IFERROR((AT76/N76),0) -> 160.21964 | AV76: =IFERROR((BS76*'CALCULO GERAL'!$E$11)/N76,0) -> 4.3946364 | AW76: =AU76/'CALCULO GERAL'!$C$11 -> 31.922622 | AX76: =BP76-BB76-BD76*'CALCULO GERAL'!$C$11 -> 216.43584 | AY76: =AX76*G76 -> 3.5711914 | AZ76: =AX76*H76 -> 16.449124 | BA76: =BP76-BD76 -> 219.73182 | BB76: =BA76*L76 -> 3.2959773 | BC76: =BP76/(1+D76) -> 219.73182 | BD76: =BC76*D76 -> 0 | BE76: =BU76*0.08 -> 123049.82 | BF76: =BU76*0.12 -> 184574.73 | BG76: =(BF76*0.09)/N76 -> 2.3731037 | BH76: =(BE76*0.15)/N76 -> 2.6367818 | BI76: =IF(BE76>=$BY$1,($BY$1-BE76)*0.1,IF(BE76<=$BY$1,($BY$1*0)))/N76 -> -0.90071185 | BJ76: =(AY76+AZ76+BB76+AV76+BD76+BG76+BH76+BI76) -> 31.820103 | BK76: =BJ76+AU76 -> 192.03974 | BL76: 0.74 | BM76: =ROUND((AW76/BL76)+((AW76*BL76)*'CALCULO GERAL'!$E$11)/BL76,2) -> 43.78 | BN76: =BM76 -> 43.78 | BO76: =ROUND(FV(0.02,8,,BN76)*-1,3) -> 51.295 | BP76: =BM76*'CALCULO GERAL'!$C$11 -> 219.73182 | BQ76: =BO76*'CALCULO GERAL'!$C$11 -> 257.44961 | BR76: =BN76*'CALCULO GERAL'!$C$11 -> 219.73182 | BS76: =BP76*N76 -> 1538122.7 | BT76: =BS76-AT76 -> 416585.28 | BU76: =BR76*N76 -> 1538122.7 | BV76: =BK76*N76 -> 1344278.2 | BW76: =BS76-BV76 -> 193844.56 | BX76: =(((BK76*N76)-BS76)/BS76*-1) -> 0.12602671 | BY76: =ROUND(BL76,2) -> 0.74 | CE76: =CC76/BY76 -> 0 | CF76: =100%-CE76 -> 1 | CG76: =AVERAGE(CF76,CD76) -> 1
A77: JOGO DE CAMA PERCAL 400 FIOS LISOKING | B77: 6302.22.00 | C77: 0.35 | D77: 0 | E77: 0.021 | F77: 0.1065 | G77: 0.0165 | H77: 0.076 | I77: 0.18 | J77: 0.04 | K77: 0.14 | L77: 0.015 | M77: N/A | N77: 6200 | V77: 25.48 | X77: =MIN(O77:W77) -> 25.48 | Y77: =AVERAGE(O77:W77) -> 25.48 | Z77: =Y77*N77 -> 157976 | AA77: ='CALCULO GERAL'!$G$10 -> 6300 | AB77: =Z77+AA77 -> 164276 | AC77: =AB77*'CALCULO GERAL'!$C$11 -> 824501.24 | AD77: =AC77*C77 -> 288575.44 | AE77: =(AC77+AD77)*D77 -> 0 | AF77: =AC77*E77 -> 17314.526 | AG77: =AC77*F77 -> 87809.382 | AH77: 154.23 | AI77: =((AA77*'CALCULO GERAL'!$C$11))*0.08+20 -> 2549.576 | AJ77: 1010 | AK77: 2500 | AL77: =(AA77*('CALCULO GERAL'!$C$11*1.02))-(AA77*'CALCULO GERAL'!$C$11) -> 632.394 | AM77: 1800 | AN77: 2600 | AO77: 9400 | AP77: 1000 | AQ77: =-AF77 -> -17314.526 | AR77: =-AG77 -> -87809.382 | AT77: =SUM(AC77:AS77) -> 1134722.9 | AU77: =IFERROR((AT77/N77),0) -> 183.01982 | AV77: =IFERROR((BS77*'CALCULO GERAL'!$E$11)/N77,0) -> 5.0200038 | AW77: =AU77/'CALCULO GERAL'!$C$11 -> 36.465395 | AX77: =BP77-BB77-BD77*'CALCULO GERAL'!$C$11 -> 247.23519 | AY77: =AX77*G77 -> 4.0793806 | AZ77: =AX77*H77 -> 18.789874 | BA77: =BP77-BD77 -> 251.00019 | BB77: =BA77*L77 -> 3.7650029 | BC77: =BP77/(1+D77) -> 251.00019 | BD77: =BC77*D77 -> 0 | BE77: =BU77*0.08 -> 124496.09 | BF77: =BU77*0.12 -> 186744.14 | BG77: =(BF77*0.09)/N77 -> 2.7108021 | BH77: =(BE77*0.15)/N77 -> 3.0120023 | BI77: =IF(BE77>=$BY$1,($BY$1-BE77)*0.1,IF(BE77<=$BY$1,($BY$1*0)))/N77 -> -1.0402597 | BJ77: =(AY77+AZ77+BB77+AV77+BD77+BG77+BH77+BI77) -> 36.336806 | BK77: =BJ77+AU77 -> 219.35663 | BL77: 0.74 | BM77: =ROUND((AW77/BL77)+((AW77*BL77)*'CALCULO GERAL'!$E$11)/BL77,2) -> 50.01 | BN77: =BM77 -> 50.01 | BO77: =ROUND(FV(0.02,8,,BN77)*-1,3) -> 58.595 | BP77: =BM77*'CALCULO GERAL'!$C$11 -> 251.00019 | BQ77: =BO77*'CALCULO GERAL'!$C$11 -> 294.0883 | BR77: =BN77*'CALCULO GERAL'!$C$11 -> 251.00019 | BS77: =BP77*N77 -> 1556201.2 | BT77: =BS77-AT77 -> 421478.3 | BU77: =BR77*N77 -> 1556201.2 | BV77: =BK77*N77 -> 1360011.1 | BW77: =BS77-BV77 -> 196190.1 | BX77: =(((BK77*N77)-BS77)/BS77*-1) -> 0.12606988 | BY77: =ROUND(BL77,2) -> 0.74 | CE77: =CC77/BY77 -> 0 | CF77: =100%-CE77 -> 1 | CG77: =AVERAGE(CF77,CD77) -> 1
A78: JOGO DE CAMA PERCAL 400 FIOS COM BORDADOSOLTEIRO | B78: 6302.22.00 | C78: 0.35 | D78: 0 | E78: 0.021 | F78: 0.1065 | G78: 0.0165 | H78: 0.076 | I78: 0.18 | J78: 0.04 | K78: 0.14 | L78: 0.015 | M78: N/A | N78: 10000 | V78: 17.59 | X78: =MIN(O78:W78) -> 17.59 | Y78: =AVERAGE(O78:W78) -> 17.59 | Z78: =Y78*N78 -> 175900 | AA78: ='CALCULO GERAL'!$G$10 -> 6300 | AB78: =Z78+AA78 -> 182200 | AC78: =AB78*'CALCULO GERAL'!$C$11 -> 914461.8 | AD78: =AC78*C78 -> 320061.63 | AE78: =(AC78+AD78)*D78 -> 0 | AF78: =AC78*E78 -> 19203.698 | AG78: =AC78*F78 -> 97390.182 | AH78: 154.23 | AI78: =((AA78*'CALCULO GERAL'!$C$11))*0.08+20 -> 2549.576 | AJ78: 1010 | AK78: 2500 | AL78: =(AA78*('CALCULO GERAL'!$C$11*1.02))-(AA78*'CALCULO GERAL'!$C$11) -> 632.394 | AM78: 1800 | AN78: 2600 | AO78: 9400 | AP78: 1000 | AQ78: =-AF78 -> -19203.698 | AR78: =-AG78 -> -97390.182 | AT78: =SUM(AC78:AS78) -> 1256169.6 | AU78: =IFERROR((AT78/N78),0) -> 125.61696 | AV78: =IFERROR((BS78*'CALCULO GERAL'!$E$11)/N78,0) -> 3.4450416 | AW78: =AU78/'CALCULO GERAL'!$C$11 -> 25.028285 | AX78: =BP78-BB78-BD78*'CALCULO GERAL'!$C$11 -> 169.6683 | AY78: =AX78*G78 -> 2.7995269 | AZ78: =AX78*H78 -> 12.894791 | BA78: =BP78-BD78 -> 172.25208 | BB78: =BA78*L78 -> 2.5837812 | BC78: =BP78/(1+D78) -> 172.25208 | BD78: =BC78*D78 -> 0 | BE78: =BU78*0.08 -> 137801.66 | BF78: =BU78*0.12 -> 206702.5 | BG78: =(BF78*0.09)/N78 -> 1.8603225 | BH78: =(BE78*0.15)/N78 -> 2.067025 | BI78: =IF(BE78>=$BY$1,($BY$1-BE78)*0.1,IF(BE78<=$BY$1,($BY$1*0)))/N78 -> -0.77801674 | BJ78: =(AY78+AZ78+BB78+AV78+BD78+BG78+BH78+BI78) -> 24.872471 | BK78: =BJ78+AU78 -> 150.48943 | BL78: 0.74 | BM78: =ROUND((AW78/BL78)+((AW78*BL78)*'CALCULO GERAL'!$E$11)/BL78,2) -> 34.32 | BN78: =BM78 -> 34.32 | BO78: =ROUND(FV(0.02,8,,BN78)*-1,3) -> 40.211 | BP78: =BM78*'CALCULO GERAL'!$C$11 -> 172.25208 | BQ78: =BO78*'CALCULO GERAL'!$C$11 -> 201.81901 | BR78: =BN78*'CALCULO GERAL'!$C$11 -> 172.25208 | BS78: =BP78*N78 -> 1722520.8 | BT78: =BS78-AT78 -> 466351.17 | BU78: =BR78*N78 -> 1722520.8 | BV78: =BK78*N78 -> 1504894.3 | BW78: =BS78-BV78 -> 217626.46 | BX78: =(((BK78*N78)-BS78)/BS78*-1) -> 0.12634185 | BY78: =ROUND(BL78,2) -> 0.74 | CE78: =CC78/BY78 -> 0 | CF78: =100%-CE78 -> 1 | CG78: =AVERAGE(CF78,CD78) -> 1
A79: JOGO DE CAMA PERCAL 400 FIOS COM BORDADOCASAL | B79: 6302.22.00 | C79: 0.35 | D79: 0 | E79: 0.021 | F79: 0.1065 | G79: 0.0165 | H79: 0.076 | I79: 0.18 | J79: 0.04 | K79: 0.14 | L79: 0.015 | M79: N/A | N79: 10000 | V79: 24.12 | X79: =MIN(O79:W79) -> 24.12 | Y79: =AVERAGE(O79:W79) -> 24.12 | Z79: =Y79*N79 -> 241200 | AA79: ='CALCULO GERAL'!$G$10 -> 6300 | AB79: =Z79+AA79 -> 247500 | AC79: =AB79*'CALCULO GERAL'!$C$11 -> 1242202.5 | AD79: =AC79*C79 -> 434770.88 | AE79: =(AC79+AD79)*D79 -> 0 | AF79: =AC79*E79 -> 26086.253 | AG79: =AC79*F79 -> 132294.57 | AH79: 154.23 | AI79: =((AA79*'CALCULO GERAL'!$C$11))*0.08+20 -> 2549.576 | AJ79: 1010 | AK79: 2500 | AL79: =(AA79*('CALCULO GERAL'!$C$11*1.02))-(AA79*'CALCULO GERAL'!$C$11) -> 632.394 | AM79: 1800 | AN79: 2600 | AO79: 9400 | AP79: 1000 | AQ79: =-AF79 -> -26086.253 | AR79: =-AG79 -> -132294.57 | AT79: =SUM(AC79:AS79) -> 1698619.6 | AU79: =IFERROR((AT79/N79),0) -> 169.86196 | AV79: =IFERROR((BS79*'CALCULO GERAL'!$E$11)/N79,0) -> 4.6586358 | AW79: =AU79/'CALCULO GERAL'!$C$11 -> 33.843785 | AX79: =BP79-BB79-BD79*'CALCULO GERAL'!$C$11 -> 229.43781 | AY79: =AX79*G79 -> 3.7857239 | AZ79: =AX79*H79 -> 17.437274 | BA79: =BP79-BD79 -> 232.93179 | BB79: =BA79*L79 -> 3.4939768 | BC79: =BP79/(1+D79) -> 232.93179 | BD79: =BC79*D79 -> 0 | BE79: =BU79*0.08 -> 186345.43 | BF79: =BU79*0.12 -> 279518.15 | BG79: =(BF79*0.09)/N79 -> 2.5156633 | BH79: =(BE79*0.15)/N79 -> 2.7951815 | BI79: =IF(BE79>=$BY$1,($BY$1-BE79)*0.1,IF(BE79<=$BY$1,($BY$1*0)))/N79 -> -1.2634544 | BJ79: =(AY79+AZ79+BB79+AV79+BD79+BG79+BH79+BI79) -> 33.423001 | BK79: =BJ79+AU79 -> 203.28496 | BL79: 0.74 | BM79: =ROUND((AW79/BL79)+((AW79*BL79)*'CALCULO GERAL'!$E$11)/BL79,2) -> 46.41 | BN79: =BM79 -> 46.41 | BO79: =ROUND(FV(0.02,8,,BN79)*-1,3) -> 54.377 | BP79: =BM79*'CALCULO GERAL'!$C$11 -> 232.93179 | BQ79: =BO79*'CALCULO GERAL'!$C$11 -> 272.91816 | BR79: =BN79*'CALCULO GERAL'!$C$11 -> 232.93179 | BS79: =BP79*N79 -> 2329317.9 | BT79: =BS79-AT79 -> 630698.32 | BU79: =BR79*N79 -> 2329317.9 | BV79: =BK79*N79 -> 2032849.6 | BW79: =BS79-BV79 -> 296468.32 | BX79: =(((BK79*N79)-BS79)/BS79*-1) -> 0.12727688 | BY79: =ROUND(BL79,2) -> 0.74 | CE79: =CC79/BY79 -> 0 | CF79: =100%-CE79 -> 1 | CG79: =AVERAGE(CF79,CD79) -> 1
A80: JOGO DE CAMA PERCAL 400 FIOS COM BORDADOQUEEN | B80: 6302.22.00 | C80: 0.35 | D80: 0 | E80: 0.021 | F80: 0.1065 | G80: 0.0165 | H80: 0.076 | I80: 0.18 | J80: 0.04 | K80: 0.14 | L80: 0.015 | M80: N/A | N80: 10000 | V80: 25.78 | X80: =MIN(O80:W80) -> 25.78 | Y80: =AVERAGE(O80:W80) -> 25.78 | Z80: =Y80*N80 -> 257800 | AA80: ='CALCULO GERAL'!$G$10 -> 6300 | AB80: =Z80+AA80 -> 264100 | AC80: =AB80*'CALCULO GERAL'!$C$11 -> 1325517.9 | AD80: =AC80*C80 -> 463931.27 | AE80: =(AC80+AD80)*D80 -> 0 | AF80: =AC80*E80 -> 27835.876 | AG80: =AC80*F80 -> 141167.66 | AH80: 154.23 | AI80: =((AA80*'CALCULO GERAL'!$C$11))*0.08+20 -> 2549.576 | AJ80: 1010 | AK80: 2500 | AL80: =(AA80*('CALCULO GERAL'!$C$11*1.02))-(AA80*'CALCULO GERAL'!$C$11) -> 632.394 | AM80: 1800 | AN80: 2600 | AO80: 9400 | AP80: 1000 | AQ80: =-AF80 -> -27835.876 | AR80: =-AG80 -> -141167.66 | AT80: =SUM(AC80:AS80) -> 1811095.4 | AU80: =IFERROR((AT80/N80),0) -> 181.10954 | AV80: =IFERROR((BS80*'CALCULO GERAL'!$E$11)/N80,0) -> 4.9668024 | AW80: =AU80/'CALCULO GERAL'!$C$11 -> 36.084785 | AX80: =BP80-BB80-BD80*'CALCULO GERAL'!$C$11 -> 244.61502 | AY80: =AX80*G80 -> 4.0361478 | AZ80: =AX80*H80 -> 18.590741 | BA80: =BP80-BD80 -> 248.34012 | BB80: =BA80*L80 -> 3.7251018 | BC80: =BP80/(1+D80) -> 248.34012 | BD80: =BC80*D80 -> 0 | BE80: =BU80*0.08 -> 198672.1 | BF80: =BU80*0.12 -> 298008.14 | BG80: =(BF80*0.09)/N80 -> 2.6820733 | BH80: =(BE80*0.15)/N80 -> 2.9800814 | BI80: =IF(BE80>=$BY$1,($BY$1-BE80)*0.1,IF(BE80<=$BY$1,($BY$1*0)))/N80 -> -1.3867211 | BJ80: =(AY80+AZ80+BB80+AV80+BD80+BG80+BH80+BI80) -> 35.594227 | BK80: =BJ80+AU80 -> 216.70376 | BL80: 0.74 | BM80: =ROUND((AW80/BL80)+((AW80*BL80)*'CALCULO GERAL'!$E$11)/BL80,2) -> 49.48 | BN80: =BM80 -> 49.48 | BO80: =ROUND(FV(0.02,8,,BN80)*-1,3) -> 57.974 | BP80: =BM80*'CALCULO GERAL'!$C$11 -> 248.34012 | BQ80: =BO80*'CALCULO GERAL'!$C$11 -> 290.97151 | BR80: =BN80*'CALCULO GERAL'!$C$11 -> 248.34012 | BS80: =BP80*N80 -> 2483401.2 | BT80: =BS80-AT80 -> 672305.83 | BU80: =BR80*N80 -> 2483401.2 | BV80: =BK80*N80 -> 2167037.6 | BW80: =BS80-BV80 -> 316363.56 | BX80: =(((BK80*N80)-BS80)/BS80*-1) -> 0.12739124 | BY80: =ROUND(BL80,2) -> 0.74 | CE80: =CC80/BY80 -> 0 | CF80: =100%-CE80 -> 1 | CG80: =AVERAGE(CF80,CD80) -> 1
A81: JOGO DE CAMA PERCAL 400 FIOS COM BORDADOKING | B81: 6302.22.00 | C81: 0.35 | D81: 0 | E81: 0.021 | F81: 0.1065 | G81: 0.0165 | H81: 0.076 | I81: 0.18 | J81: 0.04 | K81: 0.14 | L81: 0.015 | M81: N/A | N81: 10000 | V81: 29.09 | X81: =MIN(O81:W81) -> 29.09 | Y81: =AVERAGE(O81:W81) -> 29.09 | Z81: =Y81*N81 -> 290900 | AA81: ='CALCULO GERAL'!$G$10 -> 6300 | AB81: =Z81+AA81 -> 297200 | AC81: =AB81*'CALCULO GERAL'!$C$11 -> 1491646.8 | AD81: =AC81*C81 -> 522076.38 | AE81: =(AC81+AD81)*D81 -> 0 | AF81: =AC81*E81 -> 31324.583 | AG81: =AC81*F81 -> 158860.38 | AH81: 154.23 | AI81: =((AA81*'CALCULO GERAL'!$C$11))*0.08+20 -> 2549.576 | AJ81: 1010 | AK81: 2500 | AL81: =(AA81*('CALCULO GERAL'!$C$11*1.02))-(AA81*'CALCULO GERAL'!$C$11) -> 632.394 | AM81: 1800 | AN81: 2600 | AO81: 9400 | AP81: 1000 | AQ81: =-AF81 -> -31324.583 | AR81: =-AG81 -> -158860.38 | AT81: =SUM(AC81:AS81) -> 2035369.4 | AU81: =IFERROR((AT81/N81),0) -> 203.53694 | AV81: =IFERROR((BS81*'CALCULO GERAL'!$E$11)/N81,0) -> 5.5821318 | AW81: =AU81/'CALCULO GERAL'!$C$11 -> 40.553285 | AX81: =BP81-BB81-BD81*'CALCULO GERAL'!$C$11 -> 274.91999 | AY81: =AX81*G81 -> 4.5361799 | AZ81: =AX81*H81 -> 20.893919 | BA81: =BP81-BD81 -> 279.10659 | BB81: =BA81*L81 -> 4.1865988 | BC81: =BP81/(1+D81) -> 279.10659 | BD81: =BC81*D81 -> 0 | BE81: =BU81*0.08 -> 223285.27 | BF81: =BU81*0.12 -> 334927.91 | BG81: =(BF81*0.09)/N81 -> 3.0143512 | BH81: =(BE81*0.15)/N81 -> 3.3492791 | BI81: =IF(BE81>=$BY$1,($BY$1-BE81)*0.1,IF(BE81<=$BY$1,($BY$1*0)))/N81 -> -1.6328528 | BJ81: =(AY81+AZ81+BB81+AV81+BD81+BG81+BH81+BI81) -> 39.929607 | BK81: =BJ81+AU81 -> 243.46655 | BL81: 0.74 | BM81: =ROUND((AW81/BL81)+((AW81*BL81)*'CALCULO GERAL'!$E$11)/BL81,2) -> 55.61 | BN81: =BM81 -> 55.61 | BO81: =ROUND(FV(0.02,8,,BN81)*-1,3) -> 65.156 | BP81: =BM81*'CALCULO GERAL'!$C$11 -> 279.10659 | BQ81: =BO81*'CALCULO GERAL'!$C$11 -> 327.01796 | BR81: =BN81*'CALCULO GERAL'!$C$11 -> 279.10659 | BS81: =BP81*N81 -> 2791065.9 | BT81: =BS81-AT81 -> 755696.52 | BU81: =BR81*N81 -> 2791065.9 | BV81: =BK81*N81 -> 2434665.5 | BW81: =BS81-BV81 -> 356400.45 | BX81: =(((BK81*N81)-BS81)/BS81*-1) -> 0.12769331 | BY81: =ROUND(BL81,2) -> 0.74 | CE81: =CC81/BY81 -> 0 | CF81: =100%-CE81 -> 1 | CG81: =AVERAGE(CF81,CD81) -> 1
A82: PILLOW TOP ALGODAO SOLTEIRO | B82: 9404.40.00 | C82: 0.144 | D82: 0 | E82: 0.021 | F82: 0.1065 | G82: 0.0165 | H82: 0.076 | I82: 0.18 | J82: 0.04 | K82: 0.14 | L82: 0.015 | M82: N/A | N82: 4600 | V82: 17.05 | X82: =MIN(O82:W82) -> 17.05 | Y82: =AVERAGE(O82:W82) -> 17.05 | Z82: =Y82*N82 -> 78430 | AA82: ='CALCULO GERAL'!$G$10 -> 6300 | AB82: =Z82+AA82 -> 84730 | AC82: =AB82*'CALCULO GERAL'!$C$11 -> 425259.87 | AD82: =AC82*C82 -> 61237.421 | AE82: =(AC82+AD82)*D82 -> 0 | AF82: =AC82*E82 -> 8930.4573 | AG82: =AC82*F82 -> 45290.176 | AH82: 154.23 | AI82: =((AA82*'CALCULO GERAL'!$C$11))*0.08+20 -> 2549.576 | AJ82: 1010 | AK82: 2500 | AL82: =(AA82*('CALCULO GERAL'!$C$11*1.02))-(AA82*'CALCULO GERAL'!$C$11) -> 632.394 | AM82: 1800 | AN82: 2600 | AO82: 9400 | AP82: 1000 | AQ82: =-AF82 -> -8930.4573 | AR82: =-AG82 -> -45290.176 | AT82: =SUM(AC82:AS82) -> 508143.49 | AU82: =IFERROR((AT82/N82),0) -> 110.46598 | AV82: =IFERROR((BS82*'CALCULO GERAL'!$E$11)/N82,0) -> 0 | AW82: =AU82/'CALCULO GERAL'!$C$11 -> 22.009559 | AX82: =BP82-BB82-BD82*'CALCULO GERAL'!$C$11 -> #DIV/0! | AY82: =AX82*G82 -> #DIV/0! | AZ82: =AX82*H82 -> #DIV/0! | BA82: =BP82-BD82 -> #DIV/0! | BB82: =BA82*L82 -> #DIV/0! | BC82: =BP82/(1+D82) -> #DIV/0! | BD82: =BC82*D82 -> #DIV/0! | BE82: =BU82*0.08 -> #DIV/0! | BF82: =BU82*0.12 -> #DIV/0! | BG82: =(BF82*0.09)/N82 -> #DIV/0! | BH82: =(BE82*0.15)/N82 -> #DIV/0! | BI82: =IF(BE82>=$BY$1,($BY$1-BE82)*0.1,IF(BE82<=$BY$1,($BY$1*0)))/N82 -> #DIV/0! | BJ82: =(AY82+AZ82+BB82+AV82+BD82+BG82+BH82+BI82) -> #DIV/0! | BK82: =BJ82+AU82 -> #DIV/0! | BL82: #DIV/0! | BM82: =ROUND((AW82/BL82)+((AW82*BL82)*'CALCULO GERAL'!$E$11)/BL82,2) -> #DIV/0! | BN82: =BM82 -> #DIV/0! | BO82: =ROUND(FV(0.02,8,,BN82)*-1,3) -> #DIV/0! | BP82: =BM82*'CALCULO GERAL'!$C$11 -> #DIV/0! | BQ82: =BO82*'CALCULO GERAL'!$C$11 -> #DIV/0! | BR82: =BN82*'CALCULO GERAL'!$C$11 -> #DIV/0! | BS82: =BP82*N82 -> #DIV/0! | BT82: =BS82-AT82 -> #DIV/0! | BU82: =BR82*N82 -> #DIV/0! | BV82: =BK82*N82 -> #DIV/0! | BW82: =BS82-BV82 -> #DIV/0! | BX82: =(((BK82*N82)-BS82)/BS82*-1) -> #DIV/0! | BY82: =ROUND(BL82,2) -> #DIV/0! | CE82: =CC82/BY82 -> #DIV/0! | CF82: =100%-CE82 -> #DIV/0! | CG82: =AVERAGE(CF82,CD82) -> #DIV/0!
A83: PILLOW TOP ALGODAO CASAL | B83: 9404.40.00 | C83: 0.144 | D83: 0 | E83: 0.021 | F83: 0.1065 | G83: 0.0165 | H83: 0.076 | I83: 0.18 | J83: 0.04 | K83: 0.14 | L83: 0.015 | M83: N/A | N83: 3840 | V83: 21.88 | X83: =MIN(O83:W83) -> 21.88 | Y83: =AVERAGE(O83:W83) -> 21.88 | Z83: =Y83*N83 -> 84019.2 | AA83: ='CALCULO GERAL'!$G$10 -> 6300 | AB83: =Z83+AA83 -> 90319.2 | AC83: =AB83*'CALCULO GERAL'!$C$11 -> 453312.06 | AD83: =AC83*C83 -> 65276.937 | AE83: =(AC83+AD83)*D83 -> 0 | AF83: =AC83*E83 -> 9519.5534 | AG83: =AC83*F83 -> 48277.735 | AH83: 154.23 | AI83: =((AA83*'CALCULO GERAL'!$C$11))*0.08+20 -> 2549.576 | AJ83: 1010 | AK83: 2500 | AL83: =(AA83*('CALCULO GERAL'!$C$11*1.02))-(AA83*'CALCULO GERAL'!$C$11) -> 632.394 | AM83: 1800 | AN83: 2600 | AO83: 9400 | AP83: 1000 | AQ83: =-AF83 -> -9519.5534 | AR83: =-AG83 -> -48277.735 | AT83: =SUM(AC83:AS83) -> 540235.2 | AU83: =IFERROR((AT83/N83),0) -> 140.68625 | AV83: =IFERROR((BS83*'CALCULO GERAL'!$E$11)/N83,0) -> 3.66387 | AW83: =AU83/'CALCULO GERAL'!$C$11 -> 28.030733 | AX83: =BP83-BB83-BD83*'CALCULO GERAL'!$C$11 -> 180.4456 | AY83: =AX83*G83 -> 2.9773524 | AZ83: =AX83*H83 -> 13.713865 | BA83: =BP83-BD83 -> 183.1935 | BB83: =BA83*L83 -> 2.7479025 | BC83: =BP83/(1+D83) -> 183.1935 | BD83: =BC83*D83 -> 0 | BE83: =BU83*0.08 -> 56277.043 | BF83: =BU83*0.12 -> 84415.565 | BG83: =(BF83*0.09)/N83 -> 1.9784898 | BH83: =(BE83*0.15)/N83 -> 2.198322 | BI83: =IF(BE83>=$BY$1,($BY$1-BE83)*0.1,IF(BE83<=$BY$1,($BY$1*0)))/N83 -> 0 | BJ83: =(AY83+AZ83+BB83+AV83+BD83+BG83+BH83+BI83) -> 27.279802 | BK83: =BJ83+AU83 -> 167.96605 | BL83: 0.78 | BM83: =ROUND((AW83/BL83)+((AW83*BL83)*'CALCULO GERAL'!$E$11)/BL83,2) -> 36.5 | BN83: =BM83 -> 36.5 | BO83: =ROUND(FV(0.02,8,,BN83)*-1,3) -> 42.766 | BP83: =BM83*'CALCULO GERAL'!$C$11 -> 183.1935 | BQ83: =BO83*'CALCULO GERAL'!$C$11 -> 214.64255 | BR83: =BN83*'CALCULO GERAL'!$C$11 -> 183.1935 | BS83: =BP83*N83 -> 703463.04 | BT83: =BS83-AT83 -> 163227.84 | BU83: =BR83*N83 -> 703463.04 | BV83: =BK83*N83 -> 644989.64 | BW83: =BS83-BV83 -> 58473.398 | BX83: =(((BK83*N83)-BS83)/BS83*-1) -> 0.083122203 | BY83: =ROUND(BL83,2) -> 0.78 | CE83: =CC83/BY83 -> 0 | CF83: =100%-CE83 -> 1 | CG83: =AVERAGE(CF83,CD83) -> 1
A84: PILLOW TOP ALGODAO QUEEN | B84: 9404.40.00 | C84: 0.144 | D84: 0 | E84: 0.021 | F84: 0.1065 | G84: 0.0165 | H84: 0.076 | I84: 0.18 | J84: 0.04 | K84: 0.14 | L84: 0.015 | M84: N/A | N84: 2944 | V84: 24.62 | X84: =MIN(O84:W84) -> 24.62 | Y84: =AVERAGE(O84:W84) -> 24.62 | Z84: =Y84*N84 -> 72481.28 | AA84: ='CALCULO GERAL'!$G$10 -> 6300 | AB84: =Z84+AA84 -> 78781.28 | AC84: =AB84*'CALCULO GERAL'!$C$11 -> 395403.24 | AD84: =AC84*C84 -> 56938.067 | AE84: =(AC84+AD84)*D84 -> 0 | AF84: =AC84*E84 -> 8303.4681 | AG84: =AC84*F84 -> 42110.446 | AH84: 154.23 | AI84: =((AA84*'CALCULO GERAL'!$C$11))*0.08+20 -> 2549.576 | AJ84: 1010 | AK84: 2500 | AL84: =(AA84*('CALCULO GERAL'!$C$11*1.02))-(AA84*'CALCULO GERAL'!$C$11) -> 632.394 | AM84: 1800 | AN84: 2600 | AO84: 9400 | AP84: 1000 | AQ84: =-AF84 -> -8303.4681 | AR84: =-AG84 -> -42110.446 | AT84: =SUM(AC84:AS84) -> 473987.51 | AU84: =IFERROR((AT84/N84),0) -> 161.00119 | AV84: =IFERROR((BS84*'CALCULO GERAL'!$E$11)/N84,0) -> 4.246074 | AW84: =AU84/'CALCULO GERAL'!$C$11 -> 32.078341 | AX84: =BP84-BB84-BD84*'CALCULO GERAL'!$C$11 -> 209.11914 | AY84: =AX84*G84 -> 3.4504659 | AZ84: =AX84*H84 -> 15.893055 | BA84: =BP84-BD84 -> 212.3037 | BB84: =BA84*L84 -> 3.1845555 | BC84: =BP84/(1+D84) -> 212.3037 | BD84: =BC84*D84 -> 0 | BE84: =BU84*0.08 -> 50001.767 | BF84: =BU84*0.12 -> 75002.651 | BG84: =(BF84*0.09)/N84 -> 2.29288 | BH84: =(BE84*0.15)/N84 -> 2.5476444 | BI84: =IF(BE84>=$BY$1,($BY$1-BE84)*0.1,IF(BE84<=$BY$1,($BY$1*0)))/N84 -> 0 | BJ84: =(AY84+AZ84+BB84+AV84+BD84+BG84+BH84+BI84) -> 31.614675 | BK84: =BJ84+AU84 -> 192.61587 | BL84: 0.77 | BM84: =ROUND((AW84/BL84)+((AW84*BL84)*'CALCULO GERAL'!$E$11)/BL84,2) -> 42.3 | BN84: =BM84 -> 42.3 | BO84: =ROUND(FV(0.02,8,,BN84)*-1,3) -> 49.561 | BP84: =BM84*'CALCULO GERAL'!$C$11 -> 212.3037 | BQ84: =BO84*'CALCULO GERAL'!$C$11 -> 248.74666 | BR84: =BN84*'CALCULO GERAL'!$C$11 -> 212.3037 | BS84: =BP84*N84 -> 625022.09 | BT84: =BS84-AT84 -> 151034.58 | BU84: =BR84*N84 -> 625022.09 | BV84: =BK84*N84 -> 567061.11 | BW84: =BS84-BV84 -> 57960.979 | BX84: =(((BK84*N84)-BS84)/BS84*-1) -> 0.092734288 | BY84: =ROUND(BL84,2) -> 0.77 | CE84: =CC84/BY84 -> 0 | CF84: =100%-CE84 -> 1 | CG84: =AVERAGE(CF84,CD84) -> 1
A85: PILLOW TOP ALGODAO KING | B85: 9404.40.00 | C85: 0.144 | D85: 0 | E85: 0.021 | F85: 0.1065 | G85: 0.0165 | H85: 0.076 | I85: 0.18 | J85: 0.04 | K85: 0.14 | L85: 0.015 | M85: N/A | N85: 1920 | V85: 28.34 | X85: =MIN(O85:W85) -> 28.34 | Y85: =AVERAGE(O85:W85) -> 28.34 | Z85: =Y85*N85 -> 54412.8 | AA85: ='CALCULO GERAL'!$G$10 -> 6300 | AB85: =Z85+AA85 -> 60712.8 | AC85: =AB85*'CALCULO GERAL'!$C$11 -> 304717.54 | AD85: =AC85*C85 -> 43879.326 | AE85: =(AC85+AD85)*D85 -> 0 | AF85: =AC85*E85 -> 6399.0684 | AG85: =AC85*F85 -> 32452.418 | AH85: 154.23 | AI85: =((AA85*'CALCULO GERAL'!$C$11))*0.08+20 -> 2549.576 | AJ85: 1010 | AK85: 2500 | AL85: =(AA85*('CALCULO GERAL'!$C$11*1.02))-(AA85*'CALCULO GERAL'!$C$11) -> 632.394 | AM85: 1800 | AN85: 2600 | AO85: 9400 | AP85: 1000 | AQ85: =-AF85 -> -6399.0684 | AR85: =-AG85 -> -32452.418 | AT85: =SUM(AC85:AS85) -> 370243.07 | AU85: =IFERROR((AT85/N85),0) -> 192.83493 | AV85: =IFERROR((BS85*'CALCULO GERAL'!$E$11)/N85,0) -> 5.0862546 | AW85: =AU85/'CALCULO GERAL'!$C$11 -> 38.420987 | AX85: =BP85-BB85-BD85*'CALCULO GERAL'!$C$11 -> 250.49804 | AY85: =AX85*G85 -> 4.1332176 | AZ85: =AX85*H85 -> 19.037851 | BA85: =BP85-BD85 -> 254.31273 | BB85: =BA85*L85 -> 3.814691 | BC85: =BP85/(1+D85) -> 254.31273 | BD85: =BC85*D85 -> 0 | BE85: =BU85*0.08 -> 39062.435 | BF85: =BU85*0.12 -> 58593.653 | BG85: =(BF85*0.09)/N85 -> 2.7465775 | BH85: =(BE85*0.15)/N85 -> 3.0517528 | BI85: =IF(BE85>=$BY$1,($BY$1-BE85)*0.1,IF(BE85<=$BY$1,($BY$1*0)))/N85 -> 0 | BJ85: =(AY85+AZ85+BB85+AV85+BD85+BG85+BH85+BI85) -> 37.870344 | BK85: =BJ85+AU85 -> 230.70528 | BL85: 0.77 | BM85: =ROUND((AW85/BL85)+((AW85*BL85)*'CALCULO GERAL'!$E$11)/BL85,2) -> 50.67 | BN85: =BM85 -> 50.67 | BO85: =ROUND(FV(0.02,8,,BN85)*-1,3) -> 59.368 | BP85: =BM85*'CALCULO GERAL'!$C$11 -> 254.31273 | BQ85: =BO85*'CALCULO GERAL'!$C$11 -> 297.96799 | BR85: =BN85*'CALCULO GERAL'!$C$11 -> 254.31273 | BS85: =BP85*N85 -> 488280.44 | BT85: =BS85-AT85 -> 118037.37 | BU85: =BR85*N85 -> 488280.44 | BV85: =BK85*N85 -> 442954.13 | BW85: =BS85-BV85 -> 45326.311 | BX85: =(((BK85*N85)-BS85)/BS85*-1) -> 0.092828438 | BY85: =ROUND(BL85,2) -> 0.77 | CE85: =CC85/BY85 -> 0 | CF85: =100%-CE85 -> 1 | CG85: =AVERAGE(CF85,CD85) -> 1
A86: PILLOW TOP POLIESTER SOLTEIRO | B86: 9404.40.00 | C86: 0.162 | D86: 0 | E86: 0.021 | F86: 0.1065 | G86: 0.0165 | H86: 0.076 | I86: 0.18 | J86: 0.04 | K86: 0.14 | L86: 0.015 | M86: N/A | N86: 4600 | U86: 3.69 | V86: 4.11 | X86: =MIN(O86:W86) -> 3.69 | Y86: =AVERAGE(O86:W86) -> 3.9 | Z86: =Y86*N86 -> 17940 | AA86: ='CALCULO GERAL'!$G$10 -> 6300 | AB86: =Z86+AA86 -> 24240 | AC86: =AB86*'CALCULO GERAL'!$C$11 -> 121660.56 | AD86: =AC86*C86 -> 19709.011 | AE86: =(AC86+AD86)*D86 -> 0 | AF86: =AC86*E86 -> 2554.8718 | AG86: =AC86*F86 -> 12956.85 | AH86: 154.23 | AI86: =((AA86*'CALCULO GERAL'!$C$11))*0.08+20 -> 2549.576 | AJ86: 1010 | AK86: 2500 | AL86: =(AA86*('CALCULO GERAL'!$C$11*1.02))-(AA86*'CALCULO GERAL'!$C$11) -> 632.394 | AM86: 1800 | AN86: 2600 | AO86: 9400 | AP86: 1000 | AQ86: =-AF86 -> -2554.8718 | AR86: =-AG86 -> -12956.85 | AT86: =SUM(AC86:AS86) -> 163015.77 | AU86: =IFERROR((AT86/N86),0) -> 35.438211 | AV86: =IFERROR((BS86*'CALCULO GERAL'!$E$11)/N86,0) -> 0.9596328 | AW86: =AU86/'CALCULO GERAL'!$C$11 -> 7.0608111 | AX86: =BP86-BB86-BD86*'CALCULO GERAL'!$C$11 -> 47.261915 | AY86: =AX86*G86 -> 0.7798216 | AZ86: =AX86*H86 -> 3.5919056 | BA86: =BP86-BD86 -> 47.98164 | BB86: =BA86*L86 -> 0.7197246 | BC86: =BP86/(1+D86) -> 47.98164 | BD86: =BC86*D86 -> 0 | BE86: =BU86*0.08 -> 17657.244 | BF86: =BU86*0.12 -> 26485.865 | BG86: =(BF86*0.09)/N86 -> 0.51820171 | BH86: =(BE86*0.15)/N86 -> 0.57577968 | BI86: =IF(BE86>=$BY$1,($BY$1-BE86)*0.1,IF(BE86<=$BY$1,($BY$1*0)))/N86 -> 0 | BJ86: =(AY86+AZ86+BB86+AV86+BD86+BG86+BH86+BI86) -> 7.145066 | BK86: =BJ86+AU86 -> 42.583277 | BL86: 0.75 | BM86: =ROUND((AW86/BL86)+((AW86*BL86)*'CALCULO GERAL'!$E$11)/BL86,2) -> 9.56 | BN86: =BM86 -> 9.56 | BO86: =ROUND(FV(0.02,8,,BN86)*-1,3) -> 11.201 | BP86: =BM86*'CALCULO GERAL'!$C$11 -> 47.98164 | BQ86: =BO86*'CALCULO GERAL'!$C$11 -> 56.217819 | BR86: =BN86*'CALCULO GERAL'!$C$11 -> 47.98164 | BS86: =BP86*N86 -> 220715.54 | BT86: =BS86-AT86 -> 57699.773 | BU86: =BR86*N86 -> 220715.54 | BV86: =BK86*N86 -> 195883.07 | BW86: =BS86-BV86 -> 24832.47 | BX86: =(((BK86*N86)-BS86)/BS86*-1) -> 0.11250893 | BY86: =ROUND(BL86,2) -> 0.75 | CE86: =CC86/BY86 -> 0 | CF86: =100%-CE86 -> 1 | CG86: =AVERAGE(CF86,CD86) -> 1
A87: PILLOW TOP POLIESTER CASAL | B87: 9404.40.00 | C87: 0.162 | D87: 0 | E87: 0.021 | F87: 0.1065 | G87: 0.0165 | H87: 0.076 | I87: 0.18 | J87: 0.04 | K87: 0.14 | L87: 0.015 | M87: N/A | N87: 3840 | U87: 5.18 | V87: 5.65 | X87: =MIN(O87:W87) -> 5.18 | Y87: =AVERAGE(O87:W87) -> 5.415 | Z87: =Y87*N87 -> 20793.6 | AA87: ='CALCULO GERAL'!$G$10 -> 6300 | AB87: =Z87+AA87 -> 27093.6 | AC87: =AB87*'CALCULO GERAL'!$C$11 -> 135982.78 | AD87: =AC87*C87 -> 22029.21 | AE87: =(AC87+AD87)*D87 -> 0 | AF87: =AC87*E87 -> 2855.6383 | AG87: =AC87*F87 -> 14482.166 | AH87: 154.23 | AI87: =((AA87*'CALCULO GERAL'!$C$11))*0.08+20 -> 2549.576 | AJ87: 1010 | AK87: 2500 | AL87: =(AA87*('CALCULO GERAL'!$C$11*1.02))-(AA87*'CALCULO GERAL'!$C$11) -> 632.394 | AM87: 1800 | AN87: 2600 | AO87: 9400 | AP87: 1000 | AQ87: =-AF87 -> -2855.6383 | AR87: =-AG87 -> -14482.166 | AT87: =SUM(AC87:AS87) -> 179658.19 | AU87: =IFERROR((AT87/N87),0) -> 46.785987 | AV87: =IFERROR((BS87*'CALCULO GERAL'!$E$11)/N87,0) -> 1.2667956 | AW87: =AU87/'CALCULO GERAL'!$C$11 -> 9.3217746 | AX87: =BP87-BB87-BD87*'CALCULO GERAL'!$C$11 -> 62.389683 | AY87: =AX87*G87 -> 1.0294298 | AZ87: =AX87*H87 -> 4.7416159 | BA87: =BP87-BD87 -> 63.33978 | BB87: =BA87*L87 -> 0.9500967 | BC87: =BP87/(1+D87) -> 63.33978 | BD87: =BC87*D87 -> 0 | BE87: =BU87*0.08 -> 19457.98 | BF87: =BU87*0.12 -> 29186.971 | BG87: =(BF87*0.09)/N87 -> 0.68406962 | BH87: =(BE87*0.15)/N87 -> 0.76007736 | BI87: =IF(BE87>=$BY$1,($BY$1-BE87)*0.1,IF(BE87<=$BY$1,($BY$1*0)))/N87 -> 0 | BJ87: =(AY87+AZ87+BB87+AV87+BD87+BG87+BH87+BI87) -> 9.432085 | BK87: =BJ87+AU87 -> 56.218072 | BL87: 0.75 | BM87: =ROUND((AW87/BL87)+((AW87*BL87)*'CALCULO GERAL'!$E$11)/BL87,2) -> 12.62 | BN87: =BM87 -> 12.62 | BO87: =ROUND(FV(0.02,8,,BN87)*-1,3) -> 14.786 | BP87: =BM87*'CALCULO GERAL'!$C$11 -> 63.33978 | BQ87: =BO87*'CALCULO GERAL'!$C$11 -> 74.210934 | BR87: =BN87*'CALCULO GERAL'!$C$11 -> 63.33978 | BS87: =BP87*N87 -> 243224.76 | BT87: =BS87-AT87 -> 63566.567 | BU87: =BR87*N87 -> 243224.76 | BV87: =BK87*N87 -> 215877.39 | BW87: =BS87-BV87 -> 27347.36 | BX87: =(((BK87*N87)-BS87)/BS87*-1) -> 0.11243658 | BY87: =ROUND(BL87,2) -> 0.75 | CE87: =CC87/BY87 -> 0 | CF87: =100%-CE87 -> 1 | CG87: =AVERAGE(CF87,CD87) -> 1
A88: PILLOW TOP POLIESTER QUEEN | B88: 9404.40.00 | C88: 0.162 | D88: 0 | E88: 0.021 | F88: 0.1065 | G88: 0.0165 | H88: 0.076 | I88: 0.18 | J88: 0.04 | K88: 0.14 | L88: 0.015 | M88: N/A | N88: 2944 | U88: 5.99 | V88: 6.39 | X88: =MIN(O88:W88) -> 5.99 | Y88: =AVERAGE(O88:W88) -> 6.19 | Z88: =Y88*N88 -> 18223.36 | AA88: ='CALCULO GERAL'!$G$10 -> 6300 | AB88: =Z88+AA88 -> 24523.36 | AC88: =AB88*'CALCULO GERAL'!$C$11 -> 123082.74 | AD88: =AC88*C88 -> 19939.405 | AE88: =(AC88+AD88)*D88 -> 0 | AF88: =AC88*E88 -> 2584.7376 | AG88: =AC88*F88 -> 13108.312 | AH88: 154.23 | AI88: =((AA88*'CALCULO GERAL'!$C$11))*0.08+20 -> 2549.576 | AJ88: 1010 | AK88: 2500 | AL88: =(AA88*('CALCULO GERAL'!$C$11*1.02))-(AA88*'CALCULO GERAL'!$C$11) -> 632.394 | AM88: 1800 | AN88: 2600 | AO88: 9400 | AP88: 1000 | AQ88: =-AF88 -> -2584.7376 | AR88: =-AG88 -> -13108.312 | AT88: =SUM(AC88:AS88) -> 164668.35 | AU88: =IFERROR((AT88/N88),0) -> 55.933542 | AV88: =IFERROR((BS88*'CALCULO GERAL'!$E$11)/N88,0) -> 1.5338064 | AW88: =AU88/'CALCULO GERAL'!$C$11 -> 11.14436 | AX88: =BP88-BB88-BD88*'CALCULO GERAL'!$C$11 -> 75.539965 | AY88: =AX88*G88 -> 1.2464094 | AZ88: =AX88*H88 -> 5.7410374 | BA88: =BP88-BD88 -> 76.69032 | BB88: =BA88*L88 -> 1.1503548 | BC88: =BP88/(1+D88) -> 76.69032 | BD88: =BC88*D88 -> 0 | BE88: =BU88*0.08 -> 18062.104 | BF88: =BU88*0.12 -> 27093.156 | BG88: =(BF88*0.09)/N88 -> 0.82825546 | BH88: =(BE88*0.15)/N88 -> 0.92028384 | BI88: =IF(BE88>=$BY$1,($BY$1-BE88)*0.1,IF(BE88<=$BY$1,($BY$1*0)))/N88 -> 0 | BJ88: =(AY88+AZ88+BB88+AV88+BD88+BG88+BH88+BI88) -> 11.420147 | BK88: =BJ88+AU88 -> 67.35369 | BL88: 0.74 | BM88: =ROUND((AW88/BL88)+((AW88*BL88)*'CALCULO GERAL'!$E$11)/BL88,2) -> 15.28 | BN88: =BM88 -> 15.28 | BO88: =ROUND(FV(0.02,8,,BN88)*-1,3) -> 17.903 | BP88: =BM88*'CALCULO GERAL'!$C$11 -> 76.69032 | BQ88: =BO88*'CALCULO GERAL'!$C$11 -> 89.855157 | BR88: =BN88*'CALCULO GERAL'!$C$11 -> 76.69032 | BS88: =BP88*N88 -> 225776.3 | BT88: =BS88-AT88 -> 61107.954 | BU88: =BR88*N88 -> 225776.3 | BV88: =BK88*N88 -> 198289.26 | BW88: =BS88-BV88 -> 27487.04 | BX88: =(((BK88*N88)-BS88)/BS88*-1) -> 0.12174458 | BY88: =ROUND(BL88,2) -> 0.74 | CE88: =CC88/BY88 -> 0 | CF88: =100%-CE88 -> 1 | CG88: =AVERAGE(CF88,CD88) -> 1
A89: PILLOW TOP POLIESTER KING | B89: 9404.40.00 | C89: 0.162 | D89: 0 | E89: 0.021 | F89: 0.1065 | G89: 0.0165 | H89: 0.076 | I89: 0.18 | J89: 0.04 | K89: 0.14 | L89: 0.015 | M89: N/A | N89: 1920 | U89: 6.95 | V89: 7.58 | X89: =MIN(O89:W89) -> 6.95 | Y89: =AVERAGE(O89:W89) -> 7.265 | Z89: =Y89*N89 -> 13948.8 | AA89: ='CALCULO GERAL'!$G$10 -> 6300 | AB89: =Z89+AA89 -> 20248.8 | AC89: =AB89*'CALCULO GERAL'!$C$11 -> 101628.73 | AD89: =AC89*C89 -> 16463.854 | AE89: =(AC89+AD89)*D89 -> 0 | AF89: =AC89*E89 -> 2134.2033 | AG89: =AC89*F89 -> 10823.459 | AH89: 154.23 | AI89: =((AA89*'CALCULO GERAL'!$C$11))*0.08+20 -> 2549.576 | AJ89: 1010 | AK89: 2500 | AL89: =(AA89*('CALCULO GERAL'!$C$11*1.02))-(AA89*'CALCULO GERAL'!$C$11) -> 632.394 | AM89: 1800 | AN89: 2600 | AO89: 9400 | AP89: 1000 | AQ89: =-AF89 -> -2134.2033 | AR89: =-AG89 -> -10823.459 | AT89: =SUM(AC89:AS89) -> 139738.78 | AU89: =IFERROR((AT89/N89),0) -> 72.780615 | AV89: =IFERROR((BS89*'CALCULO GERAL'!$E$11)/N89,0) -> 1.9965582 | AW89: =AU89/'CALCULO GERAL'!$C$11 -> 14.501019 | AX89: =BP89-BB89-BD89*'CALCULO GERAL'!$C$11 -> 98.330491 | AY89: =AX89*G89 -> 1.6224531 | AZ89: =AX89*H89 -> 7.4731173 | BA89: =BP89-BD89 -> 99.82791 | BB89: =BA89*L89 -> 1.4974186 | BC89: =BP89/(1+D89) -> 99.82791 | BD89: =BC89*D89 -> 0 | BE89: =BU89*0.08 -> 15333.567 | BF89: =BU89*0.12 -> 23000.35 | BG89: =(BF89*0.09)/N89 -> 1.0781414 | BH89: =(BE89*0.15)/N89 -> 1.1979349 | BI89: =IF(BE89>=$BY$1,($BY$1-BE89)*0.1,IF(BE89<=$BY$1,($BY$1*0)))/N89 -> 0 | BJ89: =(AY89+AZ89+BB89+AV89+BD89+BG89+BH89+BI89) -> 14.865624 | BK89: =BJ89+AU89 -> 87.646239 | BL89: 0.74 | BM89: =ROUND((AW89/BL89)+((AW89*BL89)*'CALCULO GERAL'!$E$11)/BL89,2) -> 19.89 | BN89: =BM89 -> 19.89 | BO89: =ROUND(FV(0.02,8,,BN89)*-1,3) -> 23.304 | BP89: =BM89*'CALCULO GERAL'!$C$11 -> 99.82791 | BQ89: =BO89*'CALCULO GERAL'!$C$11 -> 116.96278 | BR89: =BN89*'CALCULO GERAL'!$C$11 -> 99.82791 | BS89: =BP89*N89 -> 191669.59 | BT89: =BS89-AT89 -> 51930.806 | BU89: =BR89*N89 -> 191669.59 | BV89: =BK89*N89 -> 168280.78 | BW89: =BS89-BV89 -> 23388.809 | BX89: =(((BK89*N89)-BS89)/BS89*-1) -> 0.12202671 | BY89: =ROUND(BL89,2) -> 0.74 | CE89: =CC89/BY89 -> 0 | CF89: =100%-CE89 -> 1 | CG89: =AVERAGE(CF89,CD89) -> 1
A90: MOTO A COMBUSTAO 110CC | B90: 8711.20.10 | C90: 0.18 | D90: 0.35 | E90: 0.021 | F90: 0.0965 | G90: 0.0165 | H90: 0.076 | I90: 0.18 | J90: 0.04 | K90: 0.14 | L90: 0.015 | M90: N/A | N90: 70 | V90: 430 | X90: =MIN(O90:W90) -> 430 | Y90: =AVERAGE(O90:W90) -> 430 | Z90: =Y90*N90 -> 30100 | AA90: ='CALCULO GERAL'!$G$10 -> 6300 | AB90: =Z90+AA90 -> 36400 | AC90: =AB90*'CALCULO GERAL'!$C$11 -> 182691.6 | AD90: =AC90*C90 -> 32884.488 | AE90: =(AC90+AD90)*D90 -> 75451.631 | AF90: =AC90*E90 -> 3836.5236 | AG90: =AC90*F90 -> 17629.739 | AH90: 154.23 | AI90: =((AA90*'CALCULO GERAL'!$C$11))*0.08+20 -> 2549.576 | AJ90: 1010 | AK90: 2500 | AL90: =(AA90*('CALCULO GERAL'!$C$11*1.02))-(AA90*'CALCULO GERAL'!$C$11) -> 632.394 | AM90: 1800 | AN90: 2600 | AO90: 9400 | AP90: 1000 | AQ90: =-AF90 -> -3836.5236 | AR90: =-AG90 -> -17629.739 | AT90: =SUM(AC90:AS90) -> 312673.92 | AU90: =IFERROR((AT90/N90),0) -> 4466.7703 | AV90: =IFERROR((BS90*'CALCULO GERAL'!$E$11)/N90,0) -> 129.40889 | AW90: =AU90/'CALCULO GERAL'!$C$11 -> 889.97216 | AX90: =BP90-BB90-BD90*'CALCULO GERAL'!$C$11 -> -2020.9355 | AY90: =AX90*G90 -> -33.345436 | AZ90: =AX90*H90 -> -153.5911 | BA90: =BP90-BD90 -> 4792.9219 | BB90: =BA90*L90 -> 71.893829 | BC90: =BP90/(1+D90) -> 4792.9219 | BD90: =BC90*D90 -> 1677.5227 | BE90: =BU90*0.08 -> 36234.49 | BF90: =BU90*0.12 -> 54351.735 | BG90: =(BF90*0.09)/N90 -> 69.880802 | BH90: =(BE90*0.15)/N90 -> 77.645335 | BI90: =IF(BE90>=$BY$1,($BY$1-BE90)*0.1,IF(BE90<=$BY$1,($BY$1*0)))/N90 -> 0 | BJ90: =(AY90+AZ90+BB90+AV90+BD90+BG90+BH90+BI90) -> 1839.415 | BK90: =BJ90+AU90 -> 6306.1853 | BL90: 0.7 | BM90: =ROUND((AW90/BL90)+((AW90*BL90)*'CALCULO GERAL'!$E$11)/BL90,2) -> 1289.19 | BN90: =BM90 -> 1289.19 | BO90: =ROUND(FV(0.02,8,,BN90)*-1,3) -> 1510.492 | BP90: =BM90*'CALCULO GERAL'!$C$11 -> 6470.4446 | BQ90: =BO90*'CALCULO GERAL'!$C$11 -> 7581.1593 | BR90: =BN90*'CALCULO GERAL'!$C$11 -> 6470.4446 | BS90: =BP90*N90 -> 452931.12 | BT90: =BS90-AT90 -> 140257.2 | BU90: =BR90*N90 -> 452931.12 | BV90: =BK90*N90 -> 441432.97 | BW90: =BS90-BV90 -> 11498.154 | BX90: =(((BK90*N90)-BS90)/BS90*-1) -> 0.025386098 | BY90: =ROUND(BL90,2) -> 0.7 | CE90: =CC90/BY90 -> 0 | CF90: =100%-CE90 -> 1 | CG90: =AVERAGE(CF90,CD90) -> 1
A91: CAPACETE | B91: 6506.10.00 | C91: 0.18 | D91: 0 | E91: 0.021 | F91: 0.0965 | G91: 0.0165 | H91: 0.076 | I91: 0.18 | J91: 0.04 | K91: 0.14 | L91: 0.015 | M91: N/A | N91: 2790 | V91: 13.45 | X91: =MIN(O91:W91) -> 13.45 | Y91: =AVERAGE(O91:W91) -> 13.45 | Z91: =Y91*N91 -> 37525.5 | AA91: ='CALCULO GERAL'!$G$10 -> 6300 | AB91: =Z91+AA91 -> 43825.5 | AC91: =AB91*'CALCULO GERAL'!$C$11 -> 219960.18 | AD91: =AC91*C91 -> 39592.833 | AE91: =(AC91+AD91)*D91 -> 0 | AF91: =AC91*E91 -> 4619.1639 | AG91: =AC91*F91 -> 21226.158 | AH91: 154.23 | AI91: =((AA91*'CALCULO GERAL'!$C$11))*0.08+20 -> 2549.576 | AJ91: 1010 | AK91: 2500 | AL91: =(AA91*('CALCULO GERAL'!$C$11*1.02))-(AA91*'CALCULO GERAL'!$C$11) -> 632.394 | AM91: 1800 | AN91: 2600 | AO91: 9400 | AP91: 1000 | AQ91: =-AF91 -> -4619.1639 | AR91: =-AG91 -> -21226.158 | AT91: =SUM(AC91:AS91) -> 281199.22 | AU91: =IFERROR((AT91/N91),0) -> 100.78825 | AV91: =IFERROR((BS91*'CALCULO GERAL'!$E$11)/N91,0) -> 2.9200542 | AW91: =AU91/'CALCULO GERAL'!$C$11 -> 20.081341 | AX91: =BP91-BB91-BD91*'CALCULO GERAL'!$C$11 -> 143.81267 | AY91: =AX91*G91 -> 2.372909 | AZ91: =AX91*H91 -> 10.929763 | BA91: =BP91-BD91 -> 146.00271 | BB91: =BA91*L91 -> 2.1900406 | BC91: =BP91/(1+D91) -> 146.00271 | BD91: =BC91*D91 -> 0 | BE91: =BU91*0.08 -> 32587.805 | BF91: =BU91*0.12 -> 48881.707 | BG91: =(BF91*0.09)/N91 -> 1.5768293 | BH91: =(BE91*0.15)/N91 -> 1.7520325 | BI91: =IF(BE91>=$BY$1,($BY$1-BE91)*0.1,IF(BE91<=$BY$1,($BY$1*0)))/N91 -> 0 | BJ91: =(AY91+AZ91+BB91+AV91+BD91+BG91+BH91+BI91) -> 21.741629 | BK91: =BJ91+AU91 -> 122.52988 | BL91: 0.7 | BM91: =ROUND((AW91/BL91)+((AW91*BL91)*'CALCULO GERAL'!$E$11)/BL91,2) -> 29.09 | BN91: =BM91 -> 29.09 | BO91: =ROUND(FV(0.02,8,,BN91)*-1,3) -> 34.084 | BP91: =BM91*'CALCULO GERAL'!$C$11 -> 146.00271 | BQ91: =BO91*'CALCULO GERAL'!$C$11 -> 171.0676 | BR91: =BN91*'CALCULO GERAL'!$C$11 -> 146.00271 | BS91: =BP91*N91 -> 407347.56 | BT91: =BS91-AT91 -> 126148.34 | BU91: =BR91*N91 -> 407347.56 | BV91: =BK91*N91 -> 341858.36 | BW91: =BS91-BV91 -> 65489.2 | BX91: =(((BK91*N91)-BS91)/BS91*-1) -> 0.16076983 | BY91: =ROUND(BL91,2) -> 0.7 | CE91: =CC91/BY91 -> 0 | CF91: =100%-CE91 -> 1 | CG91: =AVERAGE(CF91,CD91) -> 1
A92: PARAFINA GRANULADA | B92: 2712.20.00 | C92: 0.036 | D92: 0 | E92: 0.021 | F92: 0.0965 | G92: 0.0165 | H92: 0.076 | I92: 0.18 | J92: 0.04 | K92: 0.14 | L92: 0.015 | M92: N/A | N92: 2790 | V92: 13.45 | X92: =MIN(O92:W92) -> 13.45 | Y92: =AVERAGE(O92:W92) -> 13.45 | Z92: =Y92*N92 -> 37525.5 | AA92: ='CALCULO GERAL'!$G$10 -> 6300 | AB92: =Z92+AA92 -> 43825.5 | AC92: =AB92*'CALCULO GERAL'!$C$11 -> 219960.18 | AD92: =AC92*C92 -> 7918.5666 | AE92: =(AC92+AD92)*D92 -> 0 | AF92: =AC92*E92 -> 4619.1639 | AG92: =AC92*F92 -> 21226.158 | AH92: 154.23 | AI92: =((AA92*'CALCULO GERAL'!$C$11))*0.08+20 -> 2549.576 | AJ92: 1010 | AK92: 2500 | AL92: =(AA92*('CALCULO GERAL'!$C$11*1.02))-(AA92*'CALCULO GERAL'!$C$11) -> 632.394 | AM92: 1800 | AN92: 2600 | AO92: 9400 | AP92: 1000 | AQ92: =-AF92 -> -4619.1639 | AR92: =-AG92 -> -21226.158 | AT92: =SUM(AC92:AS92) -> 249524.95 | AU92: =IFERROR((AT92/N92),0) -> 89.435466 | AV92: =IFERROR((BS92*'CALCULO GERAL'!$E$11)/N92,0) -> 2.5908078 | AW92: =AU92/'CALCULO GERAL'!$C$11 -> 17.81938 | AX92: =BP92-BB92-BD92*'CALCULO GERAL'!$C$11 -> 127.59728 | AY92: =AX92*G92 -> 2.1053552 | AZ92: =AX92*H92 -> 9.6973936 | BA92: =BP92-BD92 -> 129.54039 | BB92: =BA92*L92 -> 1.9431059 | BC92: =BP92/(1+D92) -> 129.54039 | BD92: =BC92*D92 -> 0 | BE92: =BU92*0.08 -> 28913.415 | BF92: =BU92*0.12 -> 43370.123 | BG92: =(BF92*0.09)/N92 -> 1.3990362 | BH92: =(BE92*0.15)/N92 -> 1.5544847 | BI92: =IF(BE92>=$BY$1,($BY$1-BE92)*0.1,IF(BE92<=$BY$1,($BY$1*0)))/N92 -> 0 | BJ92: =(AY92+AZ92+BB92+AV92+BD92+BG92+BH92+BI92) -> 19.290183 | BK92: =BJ92+AU92 -> 108.72565 | BL92: 0.7 | BM92: =ROUND((AW92/BL92)+((AW92*BL92)*'CALCULO GERAL'!$E$11)/BL92,2) -> 25.81 | BN92: =BM92 -> 25.81 | BO92: =ROUND(FV(0.02,8,,BN92)*-1,3) -> 30.241 | BP92: =BM92*'CALCULO GERAL'!$C$11 -> 129.54039 | BQ92: =BO92*'CALCULO GERAL'!$C$11 -> 151.77958 | BR92: =BN92*'CALCULO GERAL'!$C$11 -> 129.54039 | BS92: =BP92*N92 -> 361417.69 | BT92: =BS92-AT92 -> 111892.74 | BU92: =BR92*N92 -> 361417.69 | BV92: =BK92*N92 -> 303344.56 | BW92: =BS92-BV92 -> 58073.125 | BX92: =(((BK92*N92)-BS92)/BS92*-1) -> 0.16068147 | BY92: =ROUND(BL92,2) -> 0.7 | CE92: =CC92/BY92 -> 0 | CF92: =100%-CE92 -> 1 | CG92: =AVERAGE(CF92,CD92) -> 1
A93: COMPUTADOR ALL-IN-ONE | B93: 8417.41.00 | C93: 0.16 | D93: 0.1131 | E93: 0.021 | F93: 0.0965 | G93: 0.0165 | H93: 0.076 | I93: 0.18 | J93: 0.04 | K93: 0.14 | L93: 0.015 | M93: N/A | N93: 28 | V93: 1120 | X93: =MIN(O93:W93) -> 1120 | Y93: =AVERAGE(O93:W93) -> 1120 | Z93: =Y93*N93 -> 31360 | AA93: ='CALCULO GERAL'!$G$10 -> 6300 | AB93: =Z93+AA93 -> 37660 | AC93: =AB93*'CALCULO GERAL'!$C$11 -> 189015.54 | AD93: =AC93*C93 -> 30242.486 | AE93: =(AC93+AD93)*D93 -> 24798.083 | AF93: =AC93*E93 -> 3969.3263 | AG93: =AC93*F93 -> 18240 | AH93: 154.23 | AI93: =((AA93*'CALCULO GERAL'!$C$11))*0.08+20 -> 2549.576 | AJ93: 1010 | AK93: 2500 | AL93: =(AA93*('CALCULO GERAL'!$C$11*1.02))-(AA93*'CALCULO GERAL'!$C$11) -> 632.394 | AM93: 1800 | AN93: 2600 | AO93: 9400 | AP93: 1000 | AQ93: =-AF93 -> -3969.3263 | AR93: =-AG93 -> -18240 | AT93: =SUM(AC93:AS93) -> 265702.31 | AU93: =IFERROR((AT93/N93),0) -> 9489.3682 | AV93: =IFERROR((BS93*'CALCULO GERAL'!$E$11)/N93,0) -> 274.92074 | AW93: =AU93/'CALCULO GERAL'!$C$11 -> 1890.689 | AX93: =BP93-BB93-BD93*'CALCULO GERAL'!$C$11 -> 6550.7147 | AY93: =AX93*G93 -> 108.08679 | AZ93: =AX93*H93 -> 497.85432 | BA93: =BP93-BD93 -> 12349.328 | BB93: =BA93*L93 -> 185.23992 | BC93: =BP93/(1+D93) -> 12349.328 | BD93: =BC93*D93 -> 1396.709 | BE93: =BU93*0.08 -> 30791.123 | BF93: =BU93*0.12 -> 46186.685 | BG93: =(BF93*0.09)/N93 -> 148.4572 | BH93: =(BE93*0.15)/N93 -> 164.95245 | BI93: =IF(BE93>=$BY$1,($BY$1-BE93)*0.1,IF(BE93<=$BY$1,($BY$1*0)))/N93 -> 0 | BJ93: =(AY93+AZ93+BB93+AV93+BD93+BG93+BH93+BI93) -> 2776.2204 | BK93: =BJ93+AU93 -> 12265.589 | BL93: 0.7 | BM93: =ROUND((AW93/BL93)+((AW93*BL93)*'CALCULO GERAL'!$E$11)/BL93,2) -> 2738.8 | BN93: =BM93 -> 2738.8 | BO93: =ROUND(FV(0.02,8,,BN93)*-1,3) -> 3208.941 | BP93: =BM93*'CALCULO GERAL'!$C$11 -> 13746.037 | BQ93: =BO93*'CALCULO GERAL'!$C$11 -> 16105.675 | BR93: =BN93*'CALCULO GERAL'!$C$11 -> 13746.037 | BS93: =BP93*N93 -> 384889.04 | BT93: =BS93-AT93 -> 119186.73 | BU93: =BR93*N93 -> 384889.04 | BV93: =BK93*N93 -> 343436.48 | BW93: =BS93-BV93 -> 41452.56 | BX93: =(((BK93*N93)-BS93)/BS93*-1) -> 0.10770003 | BY93: =ROUND(BL93,2) -> 0.7 | CE93: =CC93/BY93 -> 0 | CF93: =100%-CE93 -> 1 | CG93: =AVERAGE(CF93,CD93) -> 1
A94: MAQUINA MATELASSÊ | B94: 8447.20.29 | C94: 0.126 | D94: 0 | E94: 0.021 | F94: 0.1045 | G94: 0.0165 | H94: 0.076 | I94: 0.18 | J94: 0.04 | K94: 0.14 | L94: 0.015 | M94: N/A | N94: 1 | V94: 33800 | X94: =MIN(O94:W94) -> 33800 | Y94: =AVERAGE(O94:W94) -> 33800 | Z94: =Y94*N94 -> 33800 | AA94: ='CALCULO GERAL'!$G$10 -> 6300 | AB94: =Z94+AA94 -> 40100 | AC94: =AB94*'CALCULO GERAL'!$C$11 -> 201261.9 | AD94: =AC94*C94 -> 25358.999 | AE94: =(AC94+AD94)*D94 -> 0 | AF94: =AC94*E94 -> 4226.4999 | AG94: =AC94*F94 -> 21031.869 | AH94: 154.23 | AI94: =((AA94*'CALCULO GERAL'!$C$11))*0.08+20 -> 2549.576 | AJ94: 1010 | AK94: 2500 | AL94: =(AA94*('CALCULO GERAL'!$C$11*1.02))-(AA94*'CALCULO GERAL'!$C$11) -> 632.394 | AM94: 1800 | AN94: 2600 | AO94: 9400 | AP94: 1000 | AQ94: =-AF94 -> -4226.4999 | AR94: =-AG94 -> -21031.869 | AT94: =SUM(AC94:AS94) -> 248267.1 | AU94: =IFERROR((AT94/N94),0) -> 248267.1 | AV94: =IFERROR((BS94*'CALCULO GERAL'!$E$11)/N94,0) -> 7192.6526 | AW94: =AU94/'CALCULO GERAL'!$C$11 -> 49465.451 | AX94: =BP94-BB94-BD94*'CALCULO GERAL'!$C$11 -> 354238.14 | AY94: =AX94*G94 -> 5844.9293 | AZ94: =AX94*H94 -> 26922.099 | BA94: =BP94-BD94 -> 359632.63 | BB94: =BA94*L94 -> 5394.4895 | BC94: =BP94/(1+D94) -> 359632.63 | BD94: =BC94*D94 -> 0 | BE94: =BU94*0.08 -> 28770.61 | BF94: =BU94*0.12 -> 43155.916 | BG94: =(BF94*0.09)/N94 -> 3884.0324 | BH94: =(BE94*0.15)/N94 -> 4315.5916 | BI94: =IF(BE94>=$BY$1,($BY$1-BE94)*0.1,IF(BE94<=$BY$1,($BY$1*0)))/N94 -> 0 | BJ94: =(AY94+AZ94+BB94+AV94+BD94+BG94+BH94+BI94) -> 53553.794 | BK94: =BJ94+AU94 -> 301820.89 | BL94: 0.7 | BM94: =ROUND((AW94/BL94)+((AW94*BL94)*'CALCULO GERAL'!$E$11)/BL94,2) -> 71654.24 | BN94: =BM94 -> 71654.24 | BO94: =ROUND(FV(0.02,8,,BN94)*-1,3) -> 83954.362 | BP94: =BM94*'CALCULO GERAL'!$C$11 -> 359632.63 | BQ94: =BO94*'CALCULO GERAL'!$C$11 -> 421366.94 | BR94: =BN94*'CALCULO GERAL'!$C$11 -> 359632.63 | BS94: =BP94*N94 -> 359632.63 | BT94: =BS94-AT94 -> 111365.53 | BU94: =BR94*N94 -> 359632.63 | BV94: =BK94*N94 -> 301820.89 | BW94: =BS94-BV94 -> 57811.737 | BX94: =(((BK94*N94)-BS94)/BS94*-1) -> 0.1607522 | BY94: =ROUND(BL94,2) -> 0.7 | CE94: =CC94/BY94 -> 0 | CF94: =100%-CE94 -> 1 | CG94: =AVERAGE(CF94,CD94) -> 1
A95: MAQUINA ROBO INDUSTRIAL | B95: 8479.50.00 | C95: 0 | D95: 0 | E95: 0.021 | F95: 0.1025 | G95: 0.0165 | H95: 0.076 | I95: 0.18 | J95: 0.04 | K95: 0.14 | L95: 0.015 | M95: N/A | N95: 1 | V95: 33800 | X95: =MIN(O95:W95) -> 33800 | Y95: =AVERAGE(O95:W95) -> 33800 | Z95: =Y95*N95 -> 33800 | AA95: ='CALCULO GERAL'!$G$10 -> 6300 | AB95: =Z95+AA95 -> 40100 | AC95: =AB95*'CALCULO GERAL'!$C$11 -> 201261.9 | AD95: =AC95*C95 -> 0 | AE95: =(AC95+AD95)*D95 -> 0 | AF95: =AC95*E95 -> 4226.4999 | AG95: =AC95*F95 -> 20629.345 | AH95: 154.23 | AI95: =((AA95*'CALCULO GERAL'!$C$11))*0.08+20 -> 2549.576 | AJ95: 1010 | AK95: 2500 | AL95: =(AA95*('CALCULO GERAL'!$C$11*1.02))-(AA95*'CALCULO GERAL'!$C$11) -> 632.394 | AM95: 1800 | AN95: 2600 | AO95: 9400 | AP95: 1000 | AQ95: =-AF95 -> -4226.4999 | AR95: =-AG95 -> -20629.345 | AT95: =SUM(AC95:AS95) -> 222908.1 | AU95: =IFERROR((AT95/N95),0) -> 222908.1 | AV95: =IFERROR((BS95*'CALCULO GERAL'!$E$11)/N95,0) -> 6457.9664 | AW95: =AU95/'CALCULO GERAL'!$C$11 -> 44412.851 | AX95: =BP95-BB95-BD95*'CALCULO GERAL'!$C$11 -> 318054.84 | AY95: =AX95*G95 -> 5247.9049 | AZ95: =AX95*H95 -> 24172.168 | BA95: =BP95-BD95 -> 322898.32 | BB95: =BA95*L95 -> 4843.4748 | BC95: =BP95/(1+D95) -> 322898.32 | BD95: =BC95*D95 -> 0 | BE95: =BU95*0.08 -> 25831.865 | BF95: =BU95*0.12 -> 38747.798 | BG95: =(BF95*0.09)/N95 -> 3487.3018 | BH95: =(BE95*0.15)/N95 -> 3874.7798 | BI95: =IF(BE95>=$BY$1,($BY$1-BE95)*0.1,IF(BE95<=$BY$1,($BY$1*0)))/N95 -> 0 | BJ95: =(AY95+AZ95+BB95+AV95+BD95+BG95+BH95+BI95) -> 48083.596 | BK95: =BJ95+AU95 -> 270991.7 | BL95: 0.7 | BM95: =ROUND((AW95/BL95)+((AW95*BL95)*'CALCULO GERAL'!$E$11)/BL95,2) -> 64335.19 | BN95: =BM95 -> 64335.19 | BO95: =ROUND(FV(0.02,8,,BN95)*-1,3) -> 75378.929 | BP95: =BM95*'CALCULO GERAL'!$C$11 -> 322898.32 | BQ95: =BO95*'CALCULO GERAL'!$C$11 -> 378326.84 | BR95: =BN95*'CALCULO GERAL'!$C$11 -> 322898.32 | BS95: =BP95*N95 -> 322898.32 | BT95: =BS95-AT95 -> 99990.219 | BU95: =BR95*N95 -> 322898.32 | BV95: =BK95*N95 -> 270991.7 | BW95: =BS95-BV95 -> 51906.623 | BX95: =(((BK95*N95)-BS95)/BS95*-1) -> 0.16075222 | BY95: =ROUND(BL95,2) -> 0.7 | CE95: =CC95/BY95 -> 0 | CF95: =100%-CE95 -> 1 | CG95: =AVERAGE(CF95,CD95) -> 1
A96: MONITOR | B96: 8528.52.00 | C96: 0.128 | D96: 0.1099 | E96: 0.021 | F96: 0.0965 | G96: 0.0165 | H96: 0.076 | I96: 0.18 | J96: 0.04 | K96: 0.14 | L96: 0.015 | M96: N/A | N96: 1300 | V96: 41.5 | X96: =MIN(O96:W96) -> 41.5 | Y96: =AVERAGE(O96:W96) -> 41.5 | Z96: =Y96*N96 -> 53950 | AA96: ='CALCULO GERAL'!$G$10 -> 6300 | AB96: =Z96+AA96 -> 60250 | AC96: =AB96*'CALCULO GERAL'!$C$11 -> 302394.75 | AD96: =AC96*C96 -> 38706.528 | AE96: =(AC96+AD96)*D96 -> 37487.03 | AF96: =AC96*E96 -> 6350.2898 | AG96: =AC96*F96 -> 29181.093 | AH96: 154.23 | AI96: =((AA96*'CALCULO GERAL'!$C$11))*0.08+20 -> 2549.576 | AJ96: 1010 | AK96: 2500 | AL96: =(AA96*('CALCULO GERAL'!$C$11*1.02))-(AA96*'CALCULO GERAL'!$C$11) -> 632.394 | AM96: 1800 | AN96: 2600 | AO96: 9400 | AP96: 1000 | AQ96: =-AF96 -> -6350.2898 | AR96: =-AG96 -> -29181.093 | AT96: =SUM(AC96:AS96) -> 400234.51 | AU96: =IFERROR((AT96/N96),0) -> 307.8727 | AV96: =IFERROR((BS96*'CALCULO GERAL'!$E$11)/N96,0) -> 8.9197668 | AW96: =AU96/'CALCULO GERAL'!$C$11 -> 61.341442 | AX96: =BP96-BB96-BD96*'CALCULO GERAL'!$C$11 -> 218.31766 | AY96: =AX96*G96 -> 3.6022414 | AZ96: =AX96*H96 -> 16.592142 | BA96: =BP96-BD96 -> 401.8275 | BB96: =BA96*L96 -> 6.0274125 | BC96: =BP96/(1+D96) -> 401.8275 | BD96: =BC96*D96 -> 44.160842 | BE96: =BU96*0.08 -> 46382.787 | BF96: =BU96*0.12 -> 69574.181 | BG96: =(BF96*0.09)/N96 -> 4.8166741 | BH96: =(BE96*0.15)/N96 -> 5.3518601 | BI96: =IF(BE96>=$BY$1,($BY$1-BE96)*0.1,IF(BE96<=$BY$1,($BY$1*0)))/N96 -> 0 | BJ96: =(AY96+AZ96+BB96+AV96+BD96+BG96+BH96+BI96) -> 89.470939 | BK96: =BJ96+AU96 -> 397.34364 | BL96: 0.7 | BM96: =ROUND((AW96/BL96)+((AW96*BL96)*'CALCULO GERAL'!$E$11)/BL96,2) -> 88.86 | BN96: =BM96 -> 88.86 | BO96: =ROUND(FV(0.02,8,,BN96)*-1,3) -> 104.114 | BP96: =BM96*'CALCULO GERAL'!$C$11 -> 445.98834 | BQ96: =BO96*'CALCULO GERAL'!$C$11 -> 522.54817 | BR96: =BN96*'CALCULO GERAL'!$C$11 -> 445.98834 | BS96: =BP96*N96 -> 579784.84 | BT96: =BS96-AT96 -> 179550.33 | BU96: =BR96*N96 -> 579784.84 | BV96: =BK96*N96 -> 516546.73 | BW96: =BS96-BV96 -> 63238.113 | BX96: =(((BK96*N96)-BS96)/BS96*-1) -> 0.10907169 | BY96: =ROUND(BL96,2) -> 0.7 | CE96: =CC96/BY96 -> 0 | CF96: =100%-CE96 -> 1 | CG96: =AVERAGE(CF96,CD96) -> 1
A97: FRAGRÂNCIA - CHEIRINHO PARA CARRO | B97: 3307.49.00 | C97: 0.16 | D97: 0.2556 | E97: 0.0352 | F97: 0.1648 | G97: 0.0165 | H97: 0.076 | I97: 0.18 | J97: 0.04 | K97: 0.14 | L97: 0.015 | M97: N/A | N97: 100 | X97: =MIN(O97:W97) -> 0 | Y97: =AVERAGE(O97:W97) -> #DIV/0! | Z97: =Y97*N97 -> #DIV/0! | AA97: ='CALCULO GERAL'!$G$10 -> 6300 | AB97: =Z97+AA97 -> #DIV/0! | AC97: =AB97*'CALCULO GERAL'!$C$11 -> #DIV/0! | AD97: =AC97*C97 -> #DIV/0! | AE97: =(AC97+AD97)*D97 -> #DIV/0! | AF97: =AC97*E97 -> #DIV/0! | AG97: =AC97*F97 -> #DIV/0! | AH97: 154.23 | AI97: =((AA97*'CALCULO GERAL'!$C$11))*0.08+20 -> 2549.576 | AJ97: 1010 | AK97: 2500 | AL97: =(AA97*('CALCULO GERAL'!$C$11*1.02))-(AA97*'CALCULO GERAL'!$C$11) -> 632.394 | AM97: 1800 | AN97: 2600 | AO97: 9400 | AP97: 1000 | AQ97: =-AF97 -> #DIV/0! | AR97: =-AG97 -> #DIV/0! | AT97: =SUM(AC97:AS97) -> #DIV/0! | AU97: =IFERROR((AT97/N97),0) -> 0 | AV97: =IFERROR((BS97*'CALCULO GERAL'!$E$11)/N97,0) -> 0 | AW97: =AU97/'CALCULO GERAL'!$C$11 -> 0 | AX97: =BP97-BB97-BD97*'CALCULO GERAL'!$C$11 -> 0 | AY97: =AX97*G97 -> 0 | AZ97: =AX97*H97 -> 0 | BA97: =BP97-BD97 -> 0 | BB97: =BA97*L97 -> 0 | BC97: =BP97/(1+D97) -> 0 | BD97: =BC97*D97 -> 0 | BE97: =BU97*0.08 -> 0 | BF97: =BU97*0.12 -> 0 | BG97: =(BF97*0.09)/N97 -> 0 | BH97: =(BE97*0.15)/N97 -> 0 | BI97: =IF(BE97>=$BY$1,($BY$1-BE97)*0.1,IF(BE97<=$BY$1,($BY$1*0)))/N97 -> 0 | BJ97: =(AY97+AZ97+BB97+AV97+BD97+BG97+BH97+BI97) -> 0 | BK97: =BJ97+AU97 -> 0 | BL97: 0.7 | BM97: =ROUND((AW97/BL97)+((AW97*BL97)*'CALCULO GERAL'!$E$11)/BL97,2) -> 0 | BN97: =BM97 -> 0 | BO97: =ROUND(FV(0.02,8,,BN97)*-1,3) -> 0 | BP97: =BM97*'CALCULO GERAL'!$C$11 -> 0 | BQ97: =BO97*'CALCULO GERAL'!$C$11 -> 0 | BR97: =BN97*'CALCULO GERAL'!$C$11 -> 0 | BS97: =BP97*N97 -> 0 | BT97: =BS97-AT97 -> #DIV/0! | BU97: =BR97*N97 -> 0 | BV97: =BK97*N97 -> 0 | BW97: =BS97-BV97 -> 0 | BX97: =(((BK97*N97)-BS97)/BS97*-1) -> #DIV/0! | BY97: =ROUND(BL97,2) -> 0.7 | CE97: =CC97/BY97 -> 0 | CF97: =100%-CE97 -> 1 | CG97: =AVERAGE(CF97,CD97) -> 1
A98: COOLER DE BEBIDAS ELETRICO | B98: 9617.00.10 | C98: 0.162 | D98: 0.1132 | E98: 0.021 | F98: 0.0965 | G98: 0.0165 | H98: 0.076 | I98: 0.18 | J98: 0.04 | K98: 0.14 | L98: 0.015 | M98: N/A | N98: 250000 | V98: 0.33 | X98: =MIN(O98:W98) -> 0.33 | Y98: =AVERAGE(O98:W98) -> 0.33 | Z98: =Y98*N98 -> 82500 | AA98: ='CALCULO GERAL'!$G$10 -> 6300 | AB98: =Z98+AA98 -> 88800 | AC98: =AB98*'CALCULO GERAL'!$C$11 -> 445687.2 | AD98: =AC98*C98 -> 72201.326 | AE98: =(AC98+AD98)*D98 -> 58624.981 | AF98: =AC98*E98 -> 9359.4312 | AG98: =AC98*F98 -> 43008.815 | AH98: 154.23 | AI98: =((AA98*'CALCULO GERAL'!$C$11))*0.08+20 -> 2549.576 | AJ98: 1010 | AK98: 2500 | AL98: =(AA98*('CALCULO GERAL'!$C$11*1.02))-(AA98*'CALCULO GERAL'!$C$11) -> 632.394 | AM98: 1800 | AN98: 2600 | AO98: 9400 | AP98: 1000 | AQ98: =-AF98 -> -9359.4312 | AR98: =-AG98 -> -43008.815 | AT98: =SUM(AC98:AS98) -> 598159.71 | AU98: =IFERROR((AT98/N98),0) -> 2.3926388 | AV98: =IFERROR((BS98*'CALCULO GERAL'!$E$11)/N98,0) -> 0.0692622 | AW98: =AU98/'CALCULO GERAL'!$C$11 -> 0.47671624 | AX98: =BP98-BB98-BD98*'CALCULO GERAL'!$C$11 -> 1.6489568 | AY98: =AX98*G98 -> 0.027207787 | AZ98: =AX98*H98 -> 0.12532072 | BA98: =BP98-BD98 -> 3.1109504 | BB98: =BA98*L98 -> 0.046664256 | BC98: =BP98/(1+D98) -> 3.1109504 | BD98: =BC98*D98 -> 0.35215959 | BE98: =BU98*0.08 -> 69262.2 | BF98: =BU98*0.12 -> 103893.3 | BG98: =(BF98*0.09)/N98 -> 0.037401588 | BH98: =(BE98*0.15)/N98 -> 0.04155732 | BI98: =IF(BE98>=$BY$1,($BY$1-BE98)*0.1,IF(BE98<=$BY$1,($BY$1*0)))/N98 -> -0.003704884 | BJ98: =(AY98+AZ98+BB98+AV98+BD98+BG98+BH98+BI98) -> 0.69586857 | BK98: =BJ98+AU98 -> 3.0885074 | BL98: 0.7 | BM98: =ROUND((AW98/BL98)+((AW98*BL98)*'CALCULO GERAL'!$E$11)/BL98,2) -> 0.69 | BN98: =BM98 -> 0.69 | BO98: =ROUND(FV(0.02,8,,BN98)*-1,3) -> 0.808 | BP98: =BM98*'CALCULO GERAL'!$C$11 -> 3.46311 | BQ98: =BO98*'CALCULO GERAL'!$C$11 -> 4.055352 | BR98: =BN98*'CALCULO GERAL'!$C$11 -> 3.46311 | BS98: =BP98*N98 -> 865777.5 | BT98: =BS98-AT98 -> 267617.79 | BU98: =BR98*N98 -> 865777.5 | BV98: =BK98*N98 -> 772126.85 | BW98: =BS98-BV98 -> 93650.65 | BX98: =(((BK98*N98)-BS98)/BS98*-1) -> 0.10816942 | BY98: =ROUND(BL98,2) -> 0.7 | CE98: =CC98/BY98 -> 0 | CF98: =100%-CE98 -> 1 | CG98: =AVERAGE(CF98,CD98) -> 1
A99: MALA VIAGEM COM MOTOR E RODAS | B99: 4202.12.10 | C99: 0.18 | D99: 0.0767 | E99: 0.021 | F99: 0.0965 | G99: 0.0165 | H99: 0.076 | I99: 0.18 | J99: 0.04 | K99: 0.14 | L99: 0.015 | M99: N/A | N99: 750 | X99: =MIN(O99:W99) -> 0 | Y99: =AVERAGE(O99:W99) -> #DIV/0! | Z99: =Y99*N99 -> #DIV/0! | AA99: ='CALCULO GERAL'!$G$10 -> 6300 | AB99: =Z99+AA99 -> #DIV/0! | AC99: =AB99*'CALCULO GERAL'!$C$11 -> #DIV/0! | AD99: =AC99*C99 -> #DIV/0! | AE99: =(AC99+AD99)*D99 -> #DIV/0! | AF99: =AC99*E99 -> #DIV/0! | AG99: =AC99*F99 -> #DIV/0! | AH99: 154.23 | AI99: =((AA99*'CALCULO GERAL'!$C$11))*0.08+20 -> 2549.576 | AJ99: 1010 | AK99: 2500 | AL99: =(AA99*('CALCULO GERAL'!$C$11*1.02))-(AA99*'CALCULO GERAL'!$C$11) -> 632.394 | AM99: 1800 | AN99: 2600 | AO99: 9400 | AP99: 1000 | AQ99: =-AF99 -> #DIV/0! | AR99: =-AG99 -> #DIV/0! | AT99: =SUM(AC99:AS99) -> #DIV/0! | AU99: =IFERROR((AT99/N99),0) -> 0 | AV99: =IFERROR((BS99*'CALCULO GERAL'!$E$11)/N99,0) -> 0 | AW99: =AU99/'CALCULO GERAL'!$C$11 -> 0 | AX99: =BP99-BB99-BD99*'CALCULO GERAL'!$C$11 -> 0 | AY99: =AX99*G99 -> 0 | AZ99: =AX99*H99 -> 0 | BA99: =BP99-BD99 -> 0 | BB99: =BA99*L99 -> 0 | BC99: =BP99/(1+D99) -> 0 | BD99: =BC99*D99 -> 0 | BE99: =BU99*0.08 -> 0 | BF99: =BU99*0.12 -> 0 | BG99: =(BF99*0.09)/N99 -> 0 | BH99: =(BE99*0.15)/N99 -> 0 | BI99: =IF(BE99>=$BY$1,($BY$1-BE99)*0.1,IF(BE99<=$BY$1,($BY$1*0)))/N99 -> 0 | BJ99: =(AY99+AZ99+BB99+AV99+BD99+BG99+BH99+BI99) -> 0 | BK99: =BJ99+AU99 -> 0 | BL99: 0.7 | BM99: =ROUND((AW99/BL99)+((AW99*BL99)*'CALCULO GERAL'!$E$11)/BL99,2) -> 0 | BN99: =BM99 -> 0 | BO99: =ROUND(FV(0.02,8,,BN99)*-1,3) -> 0 | BP99: =BM99*'CALCULO GERAL'!$C$11 -> 0 | BQ99: =BO99*'CALCULO GERAL'!$C$11 -> 0 | BR99: =BN99*'CALCULO GERAL'!$C$11 -> 0 | BS99: =BP99*N99 -> 0 | BT99: =BS99-AT99 -> #DIV/0! | BU99: =BR99*N99 -> 0 | BV99: =BK99*N99 -> 0 | BW99: =BS99-BV99 -> 0 | BX99: =(((BK99*N99)-BS99)/BS99*-1) -> #DIV/0! | BY99: =ROUND(BL99,2) -> 0.7 | CE99: =CC99/BY99 -> 0 | CF99: =100%-CE99 -> 1 | CG99: =AVERAGE(CF99,CD99) -> 1
